Workbook

Sheet Summary Snapshot
A1: DIGITAL PRODUCT SUMMARY SNAPSHOT | B1: 2025 | C1: 2025 | D1: 2026
A2: METRICS: | B2: Budget | C2: Actual | D2: Budget | F2: High level points:
A3: Total # of employees | C3: =B18 -> 2 | D3: =E18 -> 4 | F3: * $ 153,359 EHA cost of Anubhav (fees $142,173, Travel reimb $11,186 , total $153,359) was in RMM in 2025 budget not in GLobal Digital Products.
A4: Total # of EHA | C4: =C18 -> 1 | D4: =F18 -> 0 | F4: * A total sum of $ 80,177.$ 37,825 staff salary of Yashaswini Kumar and Sangeetha H M and 2 EHA of $ 16,060 were in Mediacal, 5 EHAs of $26,292 were in Health Com not in Digital Product.
A5: Digital Products | F5: * Total FTE staff increase =22. In India> 8, Bangaldesh > 6 , Indonesia> 7 and Nepal >1.
A6: Global Product | B6: =B532 -> 0 | C6: =C532 -> 0 | D6: ='Shared Summary by Dept_US$'!C14 -> 326653.49 | F6: * Total EHA Increase = 6. In India> 2, Bangaldesh > (-4) , Indonesia> 5 and Nepal> 3.
A7: Global Engineering | D7: ='Shared Summary by Dept_US$'!C15 -> 570322.05 | F7: * Software & subscription budget is maintained in US because of regulatory restriction in payment from India, INDO and BD
A8: Country Product | B8: =B133+B247+B361+B418+B589+B646 -> 1125183 | C8: =C133+C247+C361+C418+C589+C646 -> 935056.41 | D8: ='Shared Summary by Dept_US$'!C4+'Shared Summary by Dept_US$'!C5+'Shared Summary by Dept_US$'!C8+'Shared Summary by Dept_US$'!C11+'Shared Summary by Dept_US$'!C19 -> 895016.69 | F8: *Turn.io pricing increase not included post April 1st, 2026 - could be as high as $1.2M.
A9: Country Engineering | B9: =B190+B304+B475+B703 -> 837040 | C9: =C190+C304+C475+C703 -> 758116.78 | D9: ='Shared Summary by Dept_US$'!C6+'Shared Summary by Dept_US$'!C9+'Shared Summary by Dept_US$'!C12+'Shared Summary by Dept_US$'!C17+'Shared Summary by Dept_US$'!C20 -> 390274.27 | F9: * All new hires budget in India, INDO, BD and Nepal is from April 2026.
A10: Total Annual Budget | B10: =SUM(B6:B9) -> 1962223 | C10: =SUM(C6:C9) -> 1693173.2 | D10: =SUM(D6:D9) -> 2182266.5 | E10: =(D10-C10)/C10 -> 0.28886195 | F10: * 2025 Budget /Actual of Shared Platform Engineering / Software is reported under Engineering. In 2026, its budget /staff is moved to Global Digital Product.
F11: * Last year, out of 14 staff in Global Digital product , 8 staff joined over the year. Full 12 months salary is budgted in 2026
A13: # of People | B13: 2025 (Actual) | E13: 2026
B14: FTEs | C14: Contractors | D14: TOTAL | E14: FTEs | F14: Contractors | G14: TOTAL
A15: Global Product | B15: ='Staff Numbers'!B15 -> 14 | C15: ='Staff Numbers'!C15 -> 2 | D15: =SUM(B15:C15) -> 16 | E15: ='Staff Numbers'!F15 -> 5 | F15: ='Staff Numbers'!G15 -> 1 | G15: =SUM(E15:F15) -> 6 | H15: =E15-B15 -> -9 | I15: =F15-C15 -> -1
A16: Global Engineering | B16: ='Staff Numbers'!B16 -> 0 | C16: ='Staff Numbers'!C16 -> 0 | D16: =SUM(B16:C16) -> 0 | E16: ='Staff Numbers'!F16 -> 14 | F16: ='Staff Numbers'!G16 -> 1 | G16: =SUM(E16:F16) -> 15 | H16: =E16-B16 -> 14 | I16: =F16-C16 -> 1
A17: Country Product | B17: ='Staff Numbers'!B5+'Staff Numbers'!B6+'Staff Numbers'!B9+'Staff Numbers'!B12+'Staff Numbers'!B18+'Staff Numbers'!B20 -> 31 | C17: ='Staff Numbers'!C5+'Staff Numbers'!C6+'Staff Numbers'!C9+'Staff Numbers'!C12+'Staff Numbers'!C18+'Staff Numbers'!C20 -> 32 | D17: =SUM(B17:C17) -> 63 | E17: ='Staff Numbers'!F5+'Staff Numbers'!F6+'Staff Numbers'!F9+'Staff Numbers'!F12+'Staff Numbers'!F18+'Staff Numbers'!F20 -> 50 | F17: ='Staff Numbers'!G5+'Staff Numbers'!G6+'Staff Numbers'!G9+'Staff Numbers'!G12+'Staff Numbers'!G18+'Staff Numbers'!G20 -> 52 | G17: =SUM(E17:F17) -> 102 | H17: =E17-B17 -> 19 | I17: =F17-C17 -> 20
A18: Country Engineering | B18: ='Staff Numbers'!B7+'Staff Numbers'!B10+'Staff Numbers'!B13+'Staff Numbers'!B21 -> 2 | C18: ='Staff Numbers'!C7+'Staff Numbers'!C10+'Staff Numbers'!C13+'Staff Numbers'!C21 -> 1 | D18: =SUM(B18:C18) -> 3 | E18: ='Staff Numbers'!F7+'Staff Numbers'!F10+'Staff Numbers'!F13+'Staff Numbers'!F21 -> 4 | F18: ='Staff Numbers'!G7+'Staff Numbers'!G10+'Staff Numbers'!G13+'Staff Numbers'!G21 -> 0 | G18: =SUM(E18:F18) -> 4 | H18: =E18-B18 -> 2 | I18: =F18-C18 -> -1
A19: TOTAL | B19: =SUM(B15:B18) -> 47 | C19: =SUM(C15:C18) -> 35 | D19: =SUM(D15:D18) -> 82 | E19: =SUM(E15:E18) -> 73 | F19: =SUM(F15:F18) -> 54 | G19: =SUM(G15:G18) -> 127
A21: Analytical Review | B21: 2025 | C21: 2025 | D21: 2025 | E21: 2026
A22: Digital Product | B22: Budget | C22: Utilisation | D22: Variance | E22: Budget
A23: Salaries and Wages | B23: =SUBTOTAL(9,B24:B33) -> 1136023 | C23: =SUBTOTAL(9,C24:C33) -> 862831.9 | D23: =(C23-B23)/B23 -> -0.24048026 | E23: =SUBTOTAL(9,E24:E33) -> 1251050.8 | F23: =(E23-C23)/C23 -> 0.44993577 | J23: =E23/$E$75 -> 0.5732805
A24: Salaries and Wages | B24: =B82+B139+B196+B253+B310+B367+B424+B481+B538+B595+B652 -> 1121412 | C24: =C82+C139+C196+C253+C310+C367+C424+C481+C538+C595+C652 -> 855460.57 | D24: =(C24-B24) -> -265951.43 | E24: =SUMIF('Digital Product Summary by COA'!$C$3:$C$47,$A24,'Digital Product Summary by COA'!$E$3:$E$47) -> 1229549.1 | J24: =E24/$E$75 -> 0.56342755
A25: Gratuity & Bonus | B25: =B83+B140+B197+B254+B311+B368+B425+B482+B539+B596+B653 -> 14611 | C25: =C83+C140+C197+C254+C311+C368+C425+C482+C539+C596+C653 -> 6986.6873 | D25: =(C25-B25) -> -7624.3127 | E25: =SUMIF('Digital Product Summary by COA'!$C$3:$C$47,$A25,'Digital Product Summary by COA'!$E$3:$E$47) -> 21501.757 | J25: =E25/$E$75 -> 0.0098529472
A26: Staff Insurance | B26: =B84+B141+B198+B255+B312+B369+B426+B483+B540+B597+B654 -> 0 | C26: =C84+C141+C198+C255+C312+C369+C426+C483+C540+C597+C654 -> 384.63641 | D26: =(C26-B26) -> 384.63641 | E26: =SUMIF('Digital Product Summary by COA'!$C$3:$C$47,$A26,'Digital Product Summary by COA'!$E$3:$E$47) -> 0 | J26: =E26/$E$75 -> 0
A27: Internal meetings | B27: =B85+B142+B199+B256+B313+B370+B427+B484+B541+B598+B655 -> 0 | C27: =C85+C142+C199+C256+C313+C370+C427+C484+C541+C598+C655 -> 0 | D27: =(C27-B27) -> 0 | E27: =SUMIF('Digital Product Summary by COA'!$C$3:$C$47,$A27,'Digital Product Summary by COA'!$E$3:$E$47) -> 0 | J27: =E27/$E$75 -> 0
A28: Staff Training, Learning & Development Exp | B28: =B86+B143+B200+B257+B314+B371+B428+B485+B542+B599+B656 -> 0 | C28: =C86+C143+C200+C257+C314+C371+C428+C485+C542+C599+C656 -> 0 | D28: =(C28-B28) -> 0 | E28: =SUMIF('Digital Product Summary by COA'!$C$3:$C$47,$A28,'Digital Product Summary by COA'!$E$3:$E$47) -> 0 | J28: =E28/$E$75 -> 0
A29: Recruitment Expenses | B29: =B87+B144+B201+B258+B315+B372+B429+B486+B543+B600+B657 -> 0 | C29: =C87+C144+C201+C258+C315+C372+C429+C486+C543+C600+C657 -> 0 | D29: =(C29-B29) -> 0 | E29: =SUMIF('Digital Product Summary by COA'!$C$3:$C$47,$A29,'Digital Product Summary by COA'!$E$3:$E$47) -> 0 | J29: =E29/$E$75 -> 0
A30: Birthday expenses | B30: =B88+B145+B202+B259+B316+B373+B430+B487+B544+B601+B658 -> 0 | C30: =C88+C145+C202+C259+C316+C373+C430+C487+C544+C601+C658 -> 0 | D30: =(C30-B30) -> 0 | E30: =SUMIF('Digital Product Summary by COA'!$C$3:$C$47,$A30,'Digital Product Summary by COA'!$E$3:$E$47) -> 0 | J30: =E30/$E$75 -> 0
A31: Staff Relocation costs | B31: =B89+B146+B203+B260+B317+B374+B431+B488+B545+B602+B659 -> 0 | C31: =C89+C146+C203+C260+C317+C374+C431+C488+C545+C602+C659 -> 0 | D31: =(C31-B31) -> 0 | E31: =SUMIF('Digital Product Summary by COA'!$C$3:$C$47,$A31,'Digital Product Summary by COA'!$E$3:$E$47) -> 0 | J31: =E31/$E$75 -> 0
A32: ATR Expenses | B32: =B90+B147+B204+B261+B318+B375+B432+B489+B546+B603+B660 -> 0 | C32: =C90+C147+C204+C261+C318+C375+C432+C489+C546+C603+C660 -> 0 | D32: =(C32-B32) -> 0 | E32: =SUMIF('Digital Product Summary by COA'!$C$3:$C$47,$A32,'Digital Product Summary by COA'!$E$3:$E$47) -> 0 | J32: =E32/$E$75 -> 0
A33: Staff Insurance (Employee Medical Insurance) | B33: =B91+B148+B205+B262+B319+B376+B433+B490+B547+B604+B661 -> 0 | C33: =C91+C148+C205+C262+C319+C376+C433+C490+C547+C604+C661 -> 0 | D33: =(C33-B33) -> 0 | E33: =SUMIF('Digital Product Summary by COA'!$C$3:$C$47,$A33,'Digital Product Summary by COA'!$E$3:$E$47) -> 0 | J33: =E33/$E$75 -> 0
A34: Resource Persons | B34: =SUBTOTAL(9,B35) -> 434459 | C34: =SUBTOTAL(9,C35) -> 406523.37 | D34: =(C34-B34)/B34 -> -0.064299799 | E34: =SUBTOTAL(9,E35) -> 439613.03 | F34: =(E34-C34)/C34 -> 0.081396691 | J34: =E34/$E$75 -> 0.20144791
A35: Program Resource Consultant (EHA) | B35: =B93+B150+B207+B264+B321+B378+B435+B492+B549+B606+B663 -> 434459 | C35: =C93+C150+C207+C264+C321+C378+C435+C492+C549+C606+C663 -> 406523.37 | D35: =(C35-B35) -> -27935.626 | E35: =SUMIF('Digital Product Summary by COA'!$C$3:$C$47,$A35,'Digital Product Summary by COA'!$E$3:$E$47) -> 439613.03 | J35: =E35/$E$75 -> 0.20144791
A36: Travel & Lodging Expenses | B36: =SUBTOTAL(9,B37:B42) -> 83637 | C36: =SUBTOTAL(9,C37:C42) -> 54160.169 | D36: =(C36-B36)/B36 -> -0.35243769 | E36: =SUBTOTAL(9,E37:E42) -> 65150.505 | F36: =(E36-C36)/C36 -> 0.20292285 | G36: cut to 2025 levels | J36: =E36/$E$75 -> 0.029854513
A37: Hotel Accomodation | B37: =B95+B152+B209+B266+B323+B380+B437+B494+B551+B608+B665 -> 25883 | C37: =C95+C152+C209+C266+C323+C380+C437+C494+C551+C608+C665 -> 14787.752 | D37: =(C37-B37) -> -11095.248 | E37: =SUMIF('Digital Product Summary by COA'!$C$3:$C$47,$A37,'Digital Product Summary by COA'!$E$3:$E$47) -> 15450.467 | J37: =E37/$E$75 -> 0.0070800092
A38: Food Expenses | B38: =B96+B153+B210+B267+B324+B381+B438+B495+B552+B609+B666 -> 12849 | C38: =C96+C153+C210+C267+C324+C381+C438+C495+C552+C609+C666 -> 7289.9264 | D38: =(C38-B38) -> -5559.0736 | E38: =SUMIF('Digital Product Summary by COA'!$C$3:$C$47,$A38,'Digital Product Summary by COA'!$E$3:$E$47) -> 8600.7328 | J38: =E38/$E$75 -> 0.0039411927
A39: Air fare | B39: =B97+B154+B211+B268+B325+B382+B439+B496+B553+B610+B667 -> 27488 | C39: =C97+C154+C211+C268+C325+C382+C439+C496+C553+C610+C667 -> 25465.248 | D39: =(C39-B39) -> -2022.7524 | E39: =SUMIF('Digital Product Summary by COA'!$C$3:$C$47,$A39,'Digital Product Summary by COA'!$E$3:$E$47) -> 22907.007 | J39: =E39/$E$75 -> 0.010496888
A40: Cab/Auto | B40: =B98+B155+B212+B269+B326+B383+B440+B497+B554+B611+B668 -> 14009 | C40: =C98+C155+C212+C269+C326+C383+C440+C497+C554+C611+C668 -> 3252.0521 | D40: =(C40-B40) -> -10756.948 | E40: =SUMIF('Digital Product Summary by COA'!$C$3:$C$47,$A40,'Digital Product Summary by COA'!$E$3:$E$47) -> 13490.036 | J40: =E40/$E$75 -> 0.0061816629
A41: Bus/Train | B41: =B99+B156+B213+B270+B327+B384+B441+B498+B555+B612+B669 -> 614 | C41: =C99+C156+C213+C270+C327+C384+C441+C498+C555+C612+C669 -> 944.93865 | D41: =(C41-B41) -> 330.93865 | E41: =SUMIF('Digital Product Summary by COA'!$C$3:$C$47,$A41,'Digital Product Summary by COA'!$E$3:$E$47) -> 842.75862 | J41: =E41/$E$75 -> 0.00038618501
A42: Other incidental travel costs | B42: =B100+B157+B214+B271+B328+B385+B442+B499+B556+B613+B670 -> 2794 | C42: =C100+C157+C214+C271+C328+C385+C442+C499+C556+C613+C670 -> 2420.2516 | D42: =(C42-B42) -> -373.74841 | E42: =SUMIF('Digital Product Summary by COA'!$C$3:$C$47,$A42,'Digital Product Summary by COA'!$E$3:$E$47) -> 3859.5036 | J42: =E42/$E$75 -> 0.0017685757
A43: Supplies & Printing Costs | B43: =SUBTOTAL(9,B44:B48) -> 57831 | C43: =SUBTOTAL(9,C44:C48) -> 29933.126 | D43: =(C43-B43)/B43 -> -0.48240345 | E43: =SUBTOTAL(9,E44:E48) -> 44292.385 | F43: =(E43-C43)/C43 -> 0.47971131 | J43: =E43/$E$75 -> 0.020296506
A44: Other Direct Expenses | B44: =B102+B159+B216+B273+B330+B387+B444+B501+B558+B615+B672 -> 0 | C44: =C102+C159+C216+C273+C330+C387+C444+C501+C558+C615+C672 -> 97.705597 | D44: =(C44-B44) -> 97.705597 | E44: =SUMIF('Digital Product Summary by COA'!$C$3:$C$47,$A44,'Digital Product Summary by COA'!$E$3:$E$47) -> 5747.1264 | J44: =E44/$E$75 -> 0.0026335585
A45: Prototyping expenses (SAMPLING) | B45: =B103+B160+B217+B274+B331+B388+B445+B502+B559+B616+B673 -> 0 | C45: =C103+C160+C217+C274+C331+C388+C445+C502+C559+C616+C673 -> 0 | D45: =(C45-B45) -> 0 | E45: =SUMIF('Digital Product Summary by COA'!$C$3:$C$47,$A45,'Digital Product Summary by COA'!$E$3:$E$47) -> 0 | J45: =E45/$E$75 -> 0
A46: Other Direct Costs - Film | B46: =B104+B161+B218+B275+B332+B389+B446+B503+B560+B617+B674 -> 0 | C46: =C104+C161+C218+C275+C332+C389+C446+C503+C560+C617+C674 -> 0 | D46: =(C46-B46) -> 0 | E46: =SUMIF('Digital Product Summary by COA'!$C$3:$C$47,$A46,'Digital Product Summary by COA'!$E$3:$E$47) -> 0 | J46: =E46/$E$75 -> 0
A47: RES (Exotel Expensess) | B47: =B105+B162+B219+B276+B333+B390+B447+B504+B561+B618+B675 -> 57831 | C47: =C105+C162+C219+C276+C333+C390+C447+C504+C561+C618+C675 -> 29786.479 | D47: =(C47-B47) -> -28044.521 | E47: =SUMIF('Digital Product Summary by COA'!$C$3:$C$47,$A47,'Digital Product Summary by COA'!$E$3:$E$47) -> 34482.759 | J47: =E47/$E$75 -> 0.015801351
A48: Printing expenses | B48: =B106+B163+B220+B277+B334+B391+B448+B505+B562+B619+B676 -> 0 | C48: =C106+C163+C220+C277+C334+C391+C448+C505+C562+C619+C676 -> 48.941092 | D48: =(C48-B48) -> 48.941092 | E48: =SUMIF('Digital Product Summary by COA'!$C$3:$C$47,$A48,'Digital Product Summary by COA'!$E$3:$E$47) -> 4062.5 | J48: =E48/$E$75 -> 0.0018615966
A49: Communication Cost | B49: =SUBTOTAL(9,B50:B52) -> 0 | C49: =SUBTOTAL(9,C50:C52) -> 409.77196 | D49: =(C49-B49)/B49 -> #DIV/0! | E49: =SUBTOTAL(9,E50:E52) -> 0 | J49: =E49/$E$75 -> 0
A50: Internet Expenses | B50: =B108+B165+B222+B279+B336+B393+B450+B507+B564+B621+B678 -> 0 | C50: =C108+C165+C222+C279+C336+C393+C450+C507+C564+C621+C678 -> 1.3209528 | D50: =(C50-B50) -> 1.3209528 | E50: =SUMIF('Digital Product Summary by COA'!$C$3:$C$47,$A50,'Digital Product Summary by COA'!$E$3:$E$47) -> 0 | J50: =E50/$E$75 -> 0
A51: Postage & Courier Expenses | B51: =B109+B166+B223+B280+B337+B394+B451+B508+B565+B622+B679 -> 0 | C51: =C109+C166+C223+C280+C337+C394+C451+C508+C565+C622+C679 -> 368.32461 | D51: =(C51-B51) -> 368.32461 | E51: =SUMIF('Digital Product Summary by COA'!$C$3:$C$47,$A51,'Digital Product Summary by COA'!$E$3:$E$47) -> 0 | J51: =E51/$E$75 -> 0
A52: Telecommunication expenses | B52: =B110+B167+B224+B281+B338+B395+B452+B509+B566+B623+B680 -> 0 | C52: =C110+C167+C224+C281+C338+C395+C452+C509+C566+C623+C680 -> 40.126398 | D52: =(C52-B52) -> 40.126398 | E52: =SUMIF('Digital Product Summary by COA'!$C$3:$C$47,$A52,'Digital Product Summary by COA'!$E$3:$E$47) -> 0 | J52: =E52/$E$75 -> 0
A53: Office Expenses | B53: =SUBTOTAL(9,B54:B68) -> 199796 | C53: =SUBTOTAL(9,C54:C68) -> 313953.67 | D53: =(C53-B53)/B53 -> 0.57137117 | E53: =SUBTOTAL(9,E54:E68) -> 300232.05 | F53: =(E53-C53)/C53 -> -0.043705881 | J53: =E53/$E$75 -> 0.13757809
A54: Software and Subscriptions | B54: =B112+B169+B226+B283+B340+B397+B454+B511+B568+B625+B682 -> 199796 | C54: =C112+C169+C226+C283+C340+C397+C454+C511+C568+C625+C682 -> 313801.52 | D54: =(C54-B54)/B54 -> 0.57060963 | E54: =SUMIF('Digital Product Summary by COA'!$C$3:$C$47,$A54,'Digital Product Summary by COA'!$E$3:$E$47) -> 300013.66 | J54: =E54/$E$75 -> 0.13747801
A55: Gas, Water, Electricity | B55: =B113+B170+B227+B284+B341+B398+B455+B512+B569+B626+B683 -> 0 | C55: =C113+C170+C227+C284+C341+C398+C455+C512+C569+C626+C683 -> 0 | D55: =(C55-B55) -> 0 | E55: =SUMIF('Digital Product Summary by COA'!$C$3:$C$47,$A55,'Digital Product Summary by COA'!$E$3:$E$47) -> 0 | J55: =E55/$E$75 -> 0
A56: Books & Periodicals | B56: =B114+B171+B228+B285+B342+B399+B456+B513+B570+B627+B684 -> 0 | C56: =C114+C171+C228+C285+C342+C399+C456+C513+C570+C627+C684 -> 0 | D56: =(C56-B56) -> 0 | E56: =SUMIF('Digital Product Summary by COA'!$C$3:$C$47,$A56,'Digital Product Summary by COA'!$E$3:$E$47) -> 0 | J56: =E56/$E$75 -> 0
A57: Stationery & Consumables | B57: =B115+B172+B229+B286+B343+B400+B457+B514+B571+B628+B685 -> 0 | C57: =C115+C172+C229+C286+C343+C400+C457+C514+C571+C628+C685 -> 4.4411345 | D57: =(C57-B57) -> 4.4411345 | E57: =SUMIF('Digital Product Summary by COA'!$C$3:$C$47,$A57,'Digital Product Summary by COA'!$E$3:$E$47) -> 218.3908 | J57: =E57/$E$75 -> 0.00010007522
A58: Office Equipment Expense | B58: =B116+B173+B230+B287+B344+B401+B458+B515+B572+B629+B686 -> 0 | C58: =C116+C173+C230+C287+C344+C401+C458+C515+C572+C629+C686 -> 147.71018 | D58: =(C58-B58) -> 147.71018 | E58: =SUMIF('Digital Product Summary by COA'!$C$3:$C$47,$A58,'Digital Product Summary by COA'!$E$3:$E$47) -> 0 | J58: =E58/$E$75 -> 0
A59: Repair & Maintenance | B59: =B117+B174+B231+B288+B345+B402+B459+B516+B573+B630+B687 -> 0 | C59: =C117+C174+C231+C288+C345+C402+C459+C516+C573+C630+C687 -> 0 | D59: =(C59-B59) -> 0 | E59: =SUMIF('Digital Product Summary by COA'!$C$3:$C$47,$A59,'Digital Product Summary by COA'!$E$3:$E$47) -> 0 | J59: =E59/$E$75 -> 0
A60: Insurance (other than staff insurance) | B60: =B118+B175+B232+B289+B346+B403+B460+B517+B574+B631+B688 -> 0 | C60: =C118+C175+C232+C289+C346+C403+C460+C517+C574+C631+C688 -> 0 | D60: =(C60-B60) -> 0 | E60: =SUMIF('Digital Product Summary by COA'!$C$3:$C$47,$A60,'Digital Product Summary by COA'!$E$3:$E$47) -> 0 | J60: =E60/$E$75 -> 0
A61: Office Rent | B61: =B119+B176+B233+B290+B347+B404+B461+B518+B575+B632+B689 -> 0 | C61: =C119+C176+C233+C290+C347+C404+C461+C518+C575+C632+C689 -> 0 | D61: =(C61-B61) -> 0 | E61: =SUMIF('Digital Product Summary by COA'!$C$3:$C$47,$A61,'Digital Product Summary by COA'!$E$3:$E$47) -> 0 | J61: =E61/$E$75 -> 0
A62: Office Security Service | B62: =B120+B177+B234+B291+B348+B405+B462+B519+B576+B633+B690 -> 0 | C62: =C120+C177+C234+C291+C348+C405+C462+C519+C576+C633+C690 -> 0 | D62: =(C62-B62) -> 0 | E62: =SUMIF('Digital Product Summary by COA'!$C$3:$C$47,$A62,'Digital Product Summary by COA'!$E$3:$E$47) -> 0 | J62: =E62/$E$75 -> 0
A63: Vehicle Fuel & Maintenance | B63: =B121+B178+B235+B292+B349+B406+B463+B520+B577+B634+B691 -> 0 | C63: =C121+C178+C235+C292+C349+C406+C463+C520+C577+C634+C691 -> 0 | D63: =(C63-B63) -> 0 | E63: =SUMIF('Digital Product Summary by COA'!$C$3:$C$47,$A63,'Digital Product Summary by COA'!$E$3:$E$47) -> 0 | J63: =E63/$E$75 -> 0
A64: Bank charges | B64: =B122+B179+B236+B293+B350+B407+B464+B521+B578+B635+B692 -> 0 | C64: =C122+C179+C236+C293+C350+C407+C464+C521+C578+C635+C692 -> 0 | D64: =(C64-B64) -> 0 | E64: =SUMIF('Digital Product Summary by COA'!$C$3:$C$47,$A64,'Digital Product Summary by COA'!$E$3:$E$47) -> 0 | J64: =E64/$E$75 -> 0
A65: Pantry Consumbles | B65: =B123+B180+B237+B294+B351+B408+B465+B522+B579+B636+B693 -> 0 | C65: =C123+C180+C237+C294+C351+C408+C465+C522+C579+C636+C693 -> 0 | D65: =(C65-B65) -> 0 | E65: =SUMIF('Digital Product Summary by COA'!$C$3:$C$47,$A65,'Digital Product Summary by COA'!$E$3:$E$47) -> 0 | J65: =E65/$E$75 -> 0
A66: House Keeping Consumables | B66: =B124+B181+B238+B295+B352+B409+B466+B523+B580+B637+B694 -> 0 | C66: =C124+C181+C238+C295+C352+C409+C466+C523+C580+C637+C694 -> 0 | D66: =(C66-B66) -> 0 | E66: =SUMIF('Digital Product Summary by COA'!$C$3:$C$47,$A66,'Digital Product Summary by COA'!$E$3:$E$47) -> 0 | J66: =E66/$E$75 -> 0
... A68: Noora U Session | B68: =B126+B183+B240+B297+B354+B411+B468+B525+B582+B639+B696 -> 0 | C68: =C126+C183+C240+C297+C354+C411+C468+C525+C582+C639+C696 -> 0 | D68: =(C68-B68) -> 0 | E68: =SUMIF('Digital Product Summary by COA'!$C$3:$C$47,$A68,'Digital Product Summary by COA'!$E$3:$E$47) -> 0 | J68: =E68/$E$75 -> 0
A69: Professional & Consultancy Charges | B69: =SUBTOTAL(9,B70:B72) -> 12500 | C69: =SUBTOTAL(9,C70:C72) -> 3546.038 | D69: =(C69-B69)/B69 -> -0.71631696 | E69: =SUBTOTAL(9,E70:E72) -> 36041.207 | F69: =(E69-C69)/C69 -> 9.1637961 | G69: $55,172 for Security & Compliance Consultant (Ankit) and Design Consultant (Divya/others). $27,586 each | J69: =E69/$E$75 -> 0.016515493
A70: Audit Fees & Expenses | B70: =B128+B185+B242+B299+B356+B413+B470+B527+B584+B641+B698 -> 0 | C70: =C128+C185+C242+C299+C356+C413+C470+C527+C584+C641+C698 -> 0 | D70: =(C70-B70) -> 0 | E70: =SUMIF('Digital Product Summary by COA'!$C$3:$C$47,$A70,'Digital Product Summary by COA'!$E$3:$E$47) -> 0 | J70: =E70/$E$75 -> 0
A71: Legal Expenses | B71: =B129+B186+B243+B300+B357+B414+B471+B528+B585+B642+B699 -> 0 | C71: =C129+C186+C243+C300+C357+C414+C471+C528+C585+C642+C699 -> 0 | D71: =(C71-B71) -> 0 | E71: =SUMIF('Digital Product Summary by COA'!$C$3:$C$47,$A71,'Digital Product Summary by COA'!$E$3:$E$47) -> 0 | J71: =E71/$E$75 -> 0
A72: Admin Consultants | B72: =B130+B187+B244+B301+B358+B415+B472+B529+B586+B643+B700 -> 12500 | C72: =C130+C187+C244+C301+C358+C415+C472+C529+C586+C643+C700 -> 3546.038 | D72: =(C72-B72) -> -8953.962 | E72: =SUMIF('Digital Product Summary by COA'!$C$3:$C$47,$A72,'Digital Product Summary by COA'!$E$3:$E$47) -> 36041.207 | J72: =E72/$E$75 -> 0.016515493
A73: Fixed Assets | B73: =SUBTOTAL(9,B74) -> 37977 | C73: =SUBTOTAL(9,C74) -> 21815.14 | D73: =(C73-B73)/B73 -> -0.4255697 | E73: =SUBTOTAL(9,E74) -> 45886.494 | J73: =E73/$E$75 -> 0.021026989
A74: Laptop/ Printer | B74: =B132+B189+B246+B303+B360+B417+B474+B531+B588+B645+B702 -> 37977 | C74: =C132+C189+C246+C303+C360+C417+C474+C531+C588+C645+C702 -> 21815.14 | E74: =SUMIF('Digital Product Summary by COA'!$C$3:$C$47,$A74,'Digital Product Summary by COA'!$E$3:$E$47) -> 45886.494
B75: =SUBTOTAL(9,B24:B74) -> 1962223 | C75: =SUBTOTAL(9,C24:C74) -> 1693173.2 | D75: =(C75-B75)/B75 -> -0.1371148 | E75: =SUBTOTAL(9,E24:E74) -> 2182266.5 | F75: =(E75-C75)/C75 -> 0.28886195 | G75: Product, Design, Medical | H75: =E81+E92+E195+E206+E309+E320+E366+E377+E480+E491 -> #NAME? | I75: =H75/H78 -> #NAME?
E76: ='Shared Summary by Dept_US$'!C21 -> 2182266.5 | G76: Engineering | H76: =E138+E149+E252+E263+E423+E537+E548+E651+E662+E708+E719 -> #NAME? | I76: =H76/H78 -> #NAME?
E77: =E75-E76 -> 0 | G77: Contact Center Ops
H78: =SUM(H75:H77) -> #NAME? | I78: =H78/H78 -> #NAME?
A79: BD-Product Management | B79: 2025 | C79: 2025 | D79: 2025 | E79: 2026 | J79: Actual | K79: Actual
A80: BD-Digital Product- Country Product | B80: Budget | C80: Actual | D80: Variance | E80: Budget | J80: Jan to Nov 2025 | K80: 45992
A81: Salaries and Wages | B81: =SUBTOTAL(9,B82:B91) -> 70668 | C81: =SUBTOTAL(9,C82:C91) -> 42326 | D81: =SUBTOTAL(9,D82:D91) -> -28342 | E81: =SUBTOTAL(9,E82:E91) -> #NAME? | J81: =SUBTOTAL(9,J82:J91) -> 39040 | K81: =SUBTOTAL(9,K82:K91) -> 3286
A82: Salaries and Wages | B82: 70668 | C82: =J82+K82 -> 42326 | D82: =C82-B82 -> -28342 | E82: =SUMIFS('Digital Product Summary by COA'!$S$54:$S$325,'Digital Product Summary by COA'!$T$54:$T$325,$A$80,'Digital Product Summary by COA'!$C$54:$C$325,$A82) -> #NAME? | J82: 39040 | K82: 3286
A83: Gratuity & Bonus | B83: 0 | C83: =J83+K83 -> 0 | D83: =C83-B83 -> 0 | E83: =SUMIFS('Digital Product Summary by COA'!$S$54:$S$325,'Digital Product Summary by COA'!$T$54:$T$325,$A$80,'Digital Product Summary by COA'!$C$54:$C$325,$A83) -> #NAME?
A84: Staff Insurance | B84: 0 | C84: =J84+K84 -> 0 | D84: =C84-B84 -> 0 | E84: =SUMIFS('Digital Product Summary by COA'!$S$54:$S$325,'Digital Product Summary by COA'!$T$54:$T$325,$A$80,'Digital Product Summary by COA'!$C$54:$C$325,$A84) -> 0
A85: Internal meetings | B85: 0 | C85: =J85+K85 -> 0 | D85: =C85-B85 -> 0 | E85: =SUMIFS('Digital Product Summary by COA'!$S$54:$S$325,'Digital Product Summary by COA'!$T$54:$T$325,$A$80,'Digital Product Summary by COA'!$C$54:$C$325,$A85) -> 0
A86: Staff Training, Learning & Development Exp | B86: 0 | C86: =J86+K86 -> 0 | D86: =C86-B86 -> 0 | E86: =SUMIFS('Digital Product Summary by COA'!$S$54:$S$325,'Digital Product Summary by COA'!$T$54:$T$325,$A$80,'Digital Product Summary by COA'!$C$54:$C$325,$A86) -> #NAME?
A87: Recruitment Expenses | B87: 0 | C87: =J87+K87 -> 0 | D87: =C87-B87 -> 0 | E87: =SUMIFS('Digital Product Summary by COA'!$S$54:$S$325,'Digital Product Summary by COA'!$T$54:$T$325,$A$80,'Digital Product Summary by COA'!$C$54:$C$325,$A87) -> 0
A88: Birthday expenses | B88: 0 | C88: =J88+K88 -> 0 | D88: =C88-B88 -> 0 | E88: =SUMIFS('Digital Product Summary by COA'!$S$54:$S$325,'Digital Product Summary by COA'!$T$54:$T$325,$A$80,'Digital Product Summary by COA'!$C$54:$C$325,$A88) -> 0
A89: Staff Relocation costs | B89: 0 | C89: =J89+K89 -> 0 | D89: =C89-B89 -> 0 | E89: =SUMIFS('Digital Product Summary by COA'!$S$54:$S$325,'Digital Product Summary by COA'!$T$54:$T$325,$A$80,'Digital Product Summary by COA'!$C$54:$C$325,$A89) -> 0
A90: ATR Expenses | B90: 0 | C90: =J90+K90 -> 0 | D90: =C90-B90 -> 0 | E90: =SUMIFS('Digital Product Summary by COA'!$S$54:$S$325,'Digital Product Summary by COA'!$T$54:$T$325,$A$80,'Digital Product Summary by COA'!$C$54:$C$325,$A90) -> 0
A91: Staff Insurance (Employee Medical Insurance) | B91: 0 | C91: =J91+K91 -> 0 | D91: =C91-B91 -> 0 | E91: =SUMIFS('Digital Product Summary by COA'!$S$54:$S$325,'Digital Product Summary by COA'!$T$54:$T$325,$A$80,'Digital Product Summary by COA'!$C$54:$C$325,$A91) -> 0
A92: Resource Persons | B92: =SUBTOTAL(9,B93) -> 93913 | C92: =SUBTOTAL(9,C93) -> 73646 | D92: =SUBTOTAL(9,D93) -> -20267 | E92: =SUBTOTAL(9,E93) -> #NAME? | J92: =SUBTOTAL(9,J93) -> 68123 | K92: =SUBTOTAL(9,K93) -> 5523
A93: Program Resource Consultant (EHA) | B93: 93913 | C93: =J93+K93 -> 73646 | D93: =C93-B93 -> -20267 | E93: =SUMIFS('Digital Product Summary by COA'!$S$54:$S$325,'Digital Product Summary by COA'!$T$54:$T$325,$A$80,'Digital Product Summary by COA'!$C$54:$C$325,$A93) -> #NAME? | J93: 68123 | K93: 5523
A94: Travel & Lodging Expenses | B94: =SUBTOTAL(9,B95:B100) -> 15085 | C94: =SUBTOTAL(9,C95:C100) -> 6950 | D94: =SUBTOTAL(9,D95:D100) -> -8135 | E94: =SUBTOTAL(9,E95:E100) -> #NAME? | J94: =SUBTOTAL(9,J95:J100) -> 6587 | K94: =SUBTOTAL(9,K95:K100) -> 363
A95: Hotel Accomodation | B95: 3814 | C95: =J95+K95 -> 1023 | D95: =C95-B95 -> -2791 | E95: =SUMIFS('Digital Product Summary by COA'!$S$54:$S$325,'Digital Product Summary by COA'!$T$54:$T$325,$A$80,'Digital Product Summary by COA'!$C$54:$C$325,$A95) -> #NAME? | J95: 1023
A96: Food Expenses | B96: 4568 | C96: =J96+K96 -> 4283 | D96: =C96-B96 -> -285 | E96: =SUMIFS('Digital Product Summary by COA'!$S$54:$S$325,'Digital Product Summary by COA'!$T$54:$T$325,$A$80,'Digital Product Summary by COA'!$C$54:$C$325,$A96) -> #NAME? | J96: 4283
A97: Air fare | B97: 3631 | C97: =J97+K97 -> 697 | D97: =C97-B97 -> -2934 | E97: =SUMIFS('Digital Product Summary by COA'!$S$54:$S$325,'Digital Product Summary by COA'!$T$54:$T$325,$A$80,'Digital Product Summary by COA'!$C$54:$C$325,$A97) -> #NAME? | J97: 454 | K97: 243
A98: Cab/Auto | B98: 1589 | C98: =J98+K98 -> 127 | D98: =C98-B98 -> -1462 | E98: =SUMIFS('Digital Product Summary by COA'!$S$54:$S$325,'Digital Product Summary by COA'!$T$54:$T$325,$A$80,'Digital Product Summary by COA'!$C$54:$C$325,$A98) -> #NAME? | J98: 127
A99: Bus/Train | B99: 0 | C99: =J99+K99 -> 1 | D99: =C99-B99 -> 1 | E99: =SUMIFS('Digital Product Summary by COA'!$S$54:$S$325,'Digital Product Summary by COA'!$T$54:$T$325,$A$80,'Digital Product Summary by COA'!$C$54:$C$325,$A99) -> #NAME? | J99: 1
A100: Other incidental travel costs | B100: 1483 | C100: =J100+K100 -> 819 | D100: =C100-B100 -> -664 | E100: =SUMIFS('Digital Product Summary by COA'!$S$54:$S$325,'Digital Product Summary by COA'!$T$54:$T$325,$A$80,'Digital Product Summary by COA'!$C$54:$C$325,$A100) -> #NAME? | J100: 699 | K100: 120
A101: Supplies & Printing Costs | B101: =SUBTOTAL(9,B102:B106) -> 0 | C101: =SUBTOTAL(9,C102:C106) -> 15 | D101: =SUBTOTAL(9,D102:D106) -> 15 | E101: =SUBTOTAL(9,E102:E106) -> #NAME? | J101: =SUBTOTAL(9,J102:J106) -> 15 | K101: =SUBTOTAL(9,K102:K106) -> 0
A102: Other Direct Expenses | B102: 0 | C102: =J102+K102 -> 14 | D102: =C102-B102 -> 14 | E102: =SUMIFS('Digital Product Summary by COA'!$S$54:$S$325,'Digital Product Summary by COA'!$T$54:$T$325,$A$80,'Digital Product Summary by COA'!$C$54:$C$325,$A102) -> #NAME? | J102: 14
A103: Prototyping expenses (SAMPLING) | B103: 0 | C103: =J103+K103 -> 0 | D103: =C103-B103 -> 0 | E103: =SUMIFS('Digital Product Summary by COA'!$S$54:$S$325,'Digital Product Summary by COA'!$T$54:$T$325,$A$80,'Digital Product Summary by COA'!$C$54:$C$325,$A103) -> 0
...

Sheet Staff Numbers
A1: 2025 | B1: 2025 | C1: 2025 | E1: Digital Product | F1: 2026 | G1: 2026
B2: FTE | C2: EHA | E2: India, BD, INDO, US | F2: FTE | G2: EHA
A3: Group | D3: Country | E3: Group
D4: India | E4: Country Product
A5: INDIA-Product Management | B5: 23 | C5: 3 | D5: India | E5: Product Management | F5: 23 | G5: 9
A6: INDIA-Platforms-Product Management | D6: India | E6: Country Product | F6: 7 | G6: 10
B7: 1 | C7: 0 | D7: India | E7: Country Engineering | F7: 1 | G7: 0
D8: INDO | E8: Country Product
A9: INDO-Product Management | B9: 2 | C9: 7 | D9: INDO | E9: Country Product | F9: =2+6 -> 8 | G9: =7+5 -> 12
A10: INDO-Tech Ops | B10: 1 | C10: 0 | D10: INDO | E10: Country Engineering | F10: =1+1 -> 2 | G10: 0
D11: BD | E11: Country Product
A12: BD-Product Management | B12: 6 | C12: 22 | D12: BD | E12: Country Product | F12: =6+5 -> 11 | G12: =22-4 -> 18
A13: BD-Tech Ops | B13: 0 | C13: 0 | D13: BD | E13: Country Engineering | F13: =0+1 -> 1 | G13: 0
D14: India | E14: Global Product
A15: INDIA-Platforms-Platforms-Engineering/Software Development | B15: 14 | C15: 2 | D15: India | E15: Global Product | F15: 5 | G15: 1
D16: India | E16: Global Engineering | F16: 14 | G16: 1
D17: Nepal | E17: Country Product
B18: 0 | C18: 0 | D18: Nepal | E18: Country Product | F18: =0+1 -> 1 | G18: =0+3 -> 3
D19: US | E19: Country Product
B20: 0 | C20: 0 | D20: US | E20: Country Product | F20: 0 | G20: 0
A21: Shared Program-Platform | B21: 0 | C21: 1 | D21: US | E21: Country Engineering | F21: 0 | G21: 0
B22: =SUM(B5:B21) -> 47 | C22: =SUM(C5:C21) -> 35 | F22: =SUM(F5:F21) -> 73 | G22: =SUM(G5:G21) -> 54
H25: Increase | I25: Increase
B26: FTE | C26: EHA | F26: FTE | G26: EHA | H26: FTE | I26: EHA
B27: =B5+B6+B7+B15 -> 38 | C27: =C5+C6+C7+C15 -> 5 | E27: India | F27: =F5+F6+F7+F15 -> 36 | G27: =G5+G6+G7+G15 -> 20 | H27: =F27-B27 -> -2 | I27: =G27-C27 -> 15
B28: =B12+B13 -> 6 | C28: =C12+C13 -> 22 | E28: BD | F28: =F12+F13 -> 12 | G28: =G12+G13 -> 18 | H28: =F28-B28 -> 6 | I28: =G28-C28 -> -4
B29: =B9+B10 -> 3 | C29: =C9+C10 -> 7 | E29: INDO | F29: =F9+F10 -> 10 | G29: =G9+G10 -> 12 | H29: =F29-B29 -> 7 | I29: =G29-C29 -> 5
B30: =B18 -> 0 | C30: =C18 -> 0 | E30: Nepal | F30: =F18 -> 1 | G30: =G18 -> 3 | H30: =F30-B30 -> 1 | I30: =G30-C30 -> 3
B31: =B21 -> 0 | C31: =C21 -> 1 | E31: US | F31: =F21 -> 0 | G31: =G21 -> 0 | H31: =F31-B31 -> 0 | I31: =G31-C31 -> -1
B32: =SUM(B27:B31) -> 47 | C32: =SUM(C27:C31) -> 35 | F32: =SUM(F27:F31) -> 59 | G32: =SUM(G27:G31) -> 53 | H32: =F32-B32 -> 12 | I32: =G32-C32 -> 18
B35: FTE | C35: EHA
A44: India | B44: FTE | C44: EHA
A45: Shared Engineering+Product | B45: 15 | C45: 1
A46: India Engineering | B46: 1 | C46: 0
A47: India Product Ops (All MSE's) | B47: 24 | C47: 22
A49: Indonesia
A50: Indo Product | B50: 0 | C50: 9
A51: Indo Product Ops | B51: 0 | C51: 0
A52: Indo Engineering | B52: 1 | C52: 0
A54: Bangladesh
A55: BD Product | B55: 1 | C55: 0
A56: BD Product Ops | B56: 4 | C56: 22
A57: BD Engineering | B57: 1 | C57: 0
A59: US
A60: Engineering | B60: 0 | C60: 1

Sheet Shared Summary by Dept_US$
C1: Total CY-2026 | D1: 46023 | E1: 46054 | F1: 46082 | G1: 46113 | H1: 46143 | I1: 46174 | J1: 46204 | K1: 46235 | L1: 46266 | M1: 46296 | N1: 46327 | O1: 46357
A2: Country | B2: Group | C2: Budgets | D2: Budgets | E2: Budgets | F2: Budgets | G2: Budgets | H2: Budgets | I2: Budgets | J2: Budgets | K2: Budgets | L2: Budgets | M2: Budgets | N2: Budgets | O2: Budgets
A3: India | B3: Country Product | C3: =SUM(C4:C6) -> 531665.33 | D3: =SUM(D4:D6) -> 43770.841 | E3: =SUM(E4:E6) -> 38870.098 | F3: =SUM(F4:F6) -> 57666.615 | G3: =SUM(G4:G6) -> 56133.971 | H3: =SUM(H4:H6) -> 42531.098 | I3: =SUM(I4:I6) -> 41541.443 | J3: =SUM(J4:J6) -> 42942.592 | ... O3: =SUM(O4:O6) -> 40321.902
A4: India | B4: Product Management (YosAid) | C4: =SUM(D4:O4) -> 289991.06 | D4: =('India- Tech Build Out'!J24+'India- Tech Build Out'!J47+'India- Tech Build Out'!J119)/$B$31 -> 31928.162 | E4: =('India- Tech Build Out'!K24+'India- Tech Build Out'!K47+'India- Tech Build Out'!K119)/$B$31 -> 26228.178 | F4: =('India- Tech Build Out'!L24+'India- Tech Build Out'!L47+'India- Tech Build Out'!L119)/$B$31 -> 41079.484 | G4: =('India- Tech Build Out'!M24+'India- Tech Build Out'!M47+'India- Tech Build Out'!M119)/$B$31 -> 23720.407 | H4: =('India- Tech Build Out'!N24+'India- Tech Build Out'!N47+'India- Tech Build Out'!N119)/$B$31 -> 20735.925 | I4: =('India- Tech Build Out'!O24+'India- Tech Build Out'!O47+'India- Tech Build Out'!O119)/$B$31 -> 20643.97 | J4: =('India- Tech Build Out'!P24+'India- Tech Build Out'!P47+'India- Tech Build Out'!P119)/$B$31 -> 20643.97 | K4: =('India- Tech Build Out'!Q24+'India- Tech Build Out'!Q47+'India- Tech Build Out'!Q119)/$B$31 -> 21392.246 | ... O4: =('India- Tech Build Out'!U24+'India- Tech Build Out'!U47+'India- Tech Build Out'!U119)/$B$31 -> 20643.97
A5: India | B5: Country Product | C5: =SUM(D5:O5) -> 223283.46 | D5: ='India- Tech Build Out'!J70/$B$31 -> 10310.112 | E5: ='India- Tech Build Out'!K70/$B$31 -> 11109.353 | F5: ='India- Tech Build Out'!L70/$B$31 -> 15054.564 | G5: ='India- Tech Build Out'!M70/$B$31 -> 30880.997 | H5: ='India- Tech Build Out'!N70/$B$31 -> 20262.606 | I5: ='India- Tech Build Out'!O70/$B$31 -> 19364.905 | J5: ='India- Tech Build Out'!P70/$B$31 -> 20766.055 | K5: ='India- Tech Build Out'!Q70/$B$31 -> 19113.181 | ... O5: ='India- Tech Build Out'!U70/$B$31 -> 18145.365
A6: India | B6: Country Engineering | C6: =SUM(D6:O6) -> 18390.805 | D6: ='India- Tech Build Out'!J92/$B$31 -> 1532.567 | E6: ='India- Tech Build Out'!K92/$B$31 -> 1532.567 | F6: ='India- Tech Build Out'!L92/$B$31 -> 1532.567 | G6: ='India- Tech Build Out'!M92/$B$31 -> 1532.567 | H6: ='India- Tech Build Out'!N92/$B$31 -> 1532.567 | I6: ='India- Tech Build Out'!O92/$B$31 -> 1532.567 | J6: ='India- Tech Build Out'!P92/$B$31 -> 1532.567 | K6: ='India- Tech Build Out'!Q92/$B$31 -> 1532.567 | ... O6: ='India- Tech Build Out'!U92/$B$31 -> 1532.567
A7: INDO | B7: Country Product | C7: =SUM(C8:C9) -> 242826.62 | D7: =SUM(D8:D9) -> 9458.1778 | E7: =SUM(E8:E9) -> 12795.886 | F7: =SUM(F8:F9) -> 14350.067 | G7: =SUM(G8:G9) -> 29523.507 | H7: =SUM(H8:H9) -> 18447.401 | I7: =SUM(I8:I9) -> 20644.086 | J7: =SUM(J8:J9) -> 21373.295 | ... O7: =SUM(O8:O9) -> 23369.213
A8: INDO | B8: Country Product | C8: =SUM(D8:O8) -> 196165.93 | D8: ='INDO- Tech Build-Out'!J23/$B$32 -> 7422.5314 | E8: ='INDO- Tech Build-Out'!K23/$B$32 -> 9650.0829 | F8: ='INDO- Tech Build-Out'!L23/$B$32 -> 7808.1704 | G8: ='INDO- Tech Build-Out'!M23/$B$32 -> 21539.475 | H8: ='INDO- Tech Build-Out'!N23/$B$32 -> 15113.369 | I8: ='INDO- Tech Build-Out'!O23/$B$32 -> 17310.054 | J8: ='INDO- Tech Build-Out'!P23/$B$32 -> 18039.263 | K8: ='INDO- Tech Build-Out'!Q23/$B$32 -> 17994.429 | ... O8: ='INDO- Tech Build-Out'!U23/$B$32 -> 20035.181
A9: INDO | B9: Engineering | C9: =SUM(D9:O9) -> 46660.691 | D9: ='INDO- Tech Build-Out'!J46/$B$32 -> 2035.6464 | E9: ='INDO- Tech Build-Out'!K46/$B$32 -> 3145.8027 | F9: ='INDO- Tech Build-Out'!L46/$B$32 -> 6541.8964 | G9: ='INDO- Tech Build-Out'!M46/$B$32 -> 7984.0314 | H9: ='INDO- Tech Build-Out'!N46/$B$32 -> 3334.0314 | I9: ='INDO- Tech Build-Out'!O46/$B$32 -> 3334.0314 | J9: ='INDO- Tech Build-Out'!P46/$B$32 -> 3334.0314 | K9: ='INDO- Tech Build-Out'!Q46/$B$32 -> 3334.0314 | ... O9: ='INDO- Tech Build-Out'!U46/$B$32 -> 3334.0314
A10: BD | B10: Country Product | C10: =SUM(C11:C12) -> 200751.23 | D10: =SUM(D11:D12) -> 10962.56 | E10: =SUM(E11:E12) -> 27383.84 | F10: =SUM(F11:F12) -> 16089.138 | G10: =SUM(G11:G12) -> 15430.804 | H10: =SUM(H11:H12) -> 19475.507 | I10: =SUM(I11:I12) -> 16001.638 | J10: =SUM(J11:J12) -> 17316.221 | ... O10: =SUM(O11:O12) -> 15026.638
A11: BD | B11: Country Product | C11: =SUM(D11:O11) -> 185576.23 | D11: ='BD- Tech Build-Out'!J23/$B$33 -> 10962.56 | E11: ='BD- Tech Build-Out'!K23/$B$33 -> 25300.507 | F11: ='BD- Tech Build-Out'!L23/$B$33 -> 14826.638 | G11: ='BD- Tech Build-Out'!M23/$B$33 -> 13934.971 | H11: ='BD- Tech Build-Out'!N23/$B$33 -> 18213.007 | I11: ='BD- Tech Build-Out'!O23/$B$33 -> 14739.138 | J11: ='BD- Tech Build-Out'!P23/$B$33 -> 16053.721 | K11: ='BD- Tech Build-Out'!Q23/$B$33 -> 14539.138 | ... O11: ='BD- Tech Build-Out'!U23/$B$33 -> 13764.138
A12: BD | B12: Engineering | C12: =SUM(D12:O12) -> 15175 | D12: ='BD- Tech Build-Out'!J46/$B$33 -> 0 | E12: ='BD- Tech Build-Out'!K46/$B$33 -> 2083.3333 | F12: ='BD- Tech Build-Out'!L46/$B$33 -> 1262.5 | G12: ='BD- Tech Build-Out'!M46/$B$33 -> 1495.8333 | H12: ='BD- Tech Build-Out'!N46/$B$33 -> 1262.5 | I12: ='BD- Tech Build-Out'!O46/$B$33 -> 1262.5 | J12: ='BD- Tech Build-Out'!P46/$B$33 -> 1262.5 | K12: ='BD- Tech Build-Out'!Q46/$B$33 -> 1495.8333 | ... O12: ='BD- Tech Build-Out'!U46/$B$33 -> 1262.5
A13: India | B13: Global Product | C13: =SUM(C14:C15) -> 896975.54 | D13: =SUM(D14:D15) -> 57857.212 | E13: =SUM(E14:E15) -> 57857.212 | F13: =SUM(F14:F15) -> 77009.702 | G13: =SUM(G14:G15) -> 77578.668 | H13: =SUM(H14:H15) -> 86056.062 | I13: =SUM(I14:I15) -> 84623.412 | J13: =SUM(J14:J15) -> 75497.154 | ... O13: =SUM(O14:O15) -> 75497.154
A14: India | B14: Global Product | C14: =SUM(D14:O14) -> 326653.49 | D14: ='India- Tech Build Out'!J115/$B$31 -> 27028.395 | E14: ='India- Tech Build Out'!K115/$B$31 -> 27028.395 | F14: ='India- Tech Build Out'!L115/$B$31 -> 30184.716 | G14: ='India- Tech Build Out'!M115/$B$31 -> 31131.843 | H14: ='India- Tech Build Out'!N115/$B$31 -> 34053.682 | I14: ='India- Tech Build Out'!O115/$B$31 -> 31438.273 | J14: ='India- Tech Build Out'!P115/$B$31 -> 23978.682 | K14: ='India- Tech Build Out'!Q115/$B$31 -> 23978.682 | ... O14: ='India- Tech Build Out'!U115/$B$31 -> 23978.682
A15: India | B15: Global Engineering | C15: =SUM(D15:O15) -> 570322.05 | D15: ='India- Tech Build Out'!J142/$B$31 -> 30828.817 | E15: ='India- Tech Build Out'!K142/$B$31 -> 30828.817 | F15: ='India- Tech Build Out'!L142/$B$31 -> 46824.986 | G15: ='India- Tech Build Out'!M142/$B$31 -> 46446.825 | H15: ='India- Tech Build Out'!N142/$B$31 -> 52002.38 | I15: ='India- Tech Build Out'!O142/$B$31 -> 53185.139 | J15: ='India- Tech Build Out'!P142/$B$31 -> 51518.472 | K15: ='India- Tech Build Out'!Q142/$B$31 -> 52612.725 | ... O15: ='India- Tech Build Out'!U142/$B$31 -> 51518.472
A16: Nepal | B16: Country Product | C16: =SUM(C17) -> 21193.778 | D16: =SUM(D17) -> 1025.4074 | E16: =SUM(E17) -> 1025.4074 | F16: =SUM(F17) -> 1580.963 | G16: =SUM(G17) -> 1580.963 | H16: =SUM(H17) -> 1580.963 | I16: =SUM(I17) -> 1580.963 | J16: =SUM(J17) -> 2136.5185 | ... O16: =SUM(O17) -> 2136.5185
A17: Nepal | B17: Engineering | C17: =SUM(D17:O17) -> 21193.778 | D17: ='Nepal- Tech Build Out'!J23/$B$34 -> 1025.4074 | E17: ='Nepal- Tech Build Out'!K23/$B$34 -> 1025.4074 | F17: ='Nepal- Tech Build Out'!L23/$B$34 -> 1580.963 | G17: ='Nepal- Tech Build Out'!M23/$B$34 -> 1580.963 | H17: ='Nepal- Tech Build Out'!N23/$B$34 -> 1580.963 | I17: ='Nepal- Tech Build Out'!O23/$B$34 -> 1580.963 | J17: ='Nepal- Tech Build Out'!P23/$B$34 -> 2136.5185 | K17: ='Nepal- Tech Build Out'!Q23/$B$34 -> 2136.5185 | ... O17: ='Nepal- Tech Build Out'!U23/$B$34 -> 2136.5185
A18: US | B18: Country Product | C18: =SUM(C19:C20) -> 288854 | D18: =SUM(D19:D20) -> 37152.667 | E18: =SUM(E19:E20) -> 24685.667 | F18: =SUM(F19:F20) -> 25525.667 | G18: =SUM(G19:G20) -> 22182.667 | H18: =SUM(H19:H20) -> 22758.667 | I18: =SUM(I19:I20) -> 21745.667 | J18: =SUM(J19:J20) -> 24333.667 | ... O18: =SUM(O19:O20) -> 21770.667
A19: US | B19: Country Product | C19: =SUM(D19:O19) -> 0 | D19: ='US- Tech Build Out'!J23 -> 0 | E19: ='US- Tech Build Out'!K23 -> 0 | F19: ='US- Tech Build Out'!L23 -> 0 | G19: ='US- Tech Build Out'!M23 -> 0 | H19: ='US- Tech Build Out'!N23 -> 0 | I19: ='US- Tech Build Out'!O23 -> 0 | J19: ='US- Tech Build Out'!P23 -> 0 | K19: ='US- Tech Build Out'!Q23 -> 0 | ... O19: ='US- Tech Build Out'!U23 -> 0
A20: US | B20: Engineering | C20: =SUM(D20:O20) -> 288854 | D20: ='US- Tech Build Out'!J46 -> 37152.667 | E20: ='US- Tech Build Out'!K46 -> 24685.667 | F20: ='US- Tech Build Out'!L46 -> 25525.667 | G20: ='US- Tech Build Out'!M46 -> 22182.667 | H20: ='US- Tech Build Out'!N46 -> 22758.667 | I20: ='US- Tech Build Out'!O46 -> 21745.667 | J20: ='US- Tech Build Out'!P46 -> 24333.667 | K20: ='US- Tech Build Out'!Q46 -> 21855.667 | ... O20: ='US- Tech Build Out'!U46 -> 21770.667
C21: =C3+C7+C10+C13+C16+C18 -> 2182266.5 | D21: =D3+D7+D10+D13+D16+D18 -> 160226.86 | E21: =E3+E7+E10+E13+E16+E18 -> 162618.11 | F21: =F3+F7+F10+F13+F16+F18 -> 192222.15 | G21: =G3+G7+G10+G13+G16+G18 -> 202430.58 | H21: =H3+H7+H10+H13+H16+H18 -> 190849.7 | I21: =I3+I7+I10+I13+I16+I18 -> 186137.21 | J21: =J3+J7+J10+J13+J16+J18 -> 183599.45 | ... O21: =O3+O7+O10+O13+O16+O18 -> 178122.09
B22: Check | C22: =C21-'Digital Product Summary by COA'!E49 -> 0 | D22: =D21-'Digital Product Summary by COA'!F49 -> 0 | E22: =E21-'Digital Product Summary by COA'!G49 -> 0 | F22: =F21-'Digital Product Summary by COA'!H49 -> 0 | G22: =G21-'Digital Product Summary by COA'!I49 -> 0 | H22: =H21-'Digital Product Summary by COA'!J49 -> 0 | I22: =I21-'Digital Product Summary by COA'!K49 -> 0 | J22: =J21-'Digital Product Summary by COA'!L49 -> 0 | ... O22: =O21-'Digital Product Summary by COA'!Q49 -> 0
A31: INR | B31: 87
A32: IDR | B32: 16000
A33: BDT | B33: 120
A34: NPR | B34: 135
A35: US | B35: 1

Sheet Digital Product Summary by COA
A1: Country | B1: Parent account | C1: GL Description | D1: Ledger Code | E1: Total CY-2026 | F1: 46023 | G1: 46054 | H1: 46082 | I1: 46113 | J1: 46143 | K1: 46174 | L1: 46204 | M1: 46235 | N1: 46266 | O1: 46296 | P1: 46327 | Q1: 46357
E2: Budgets | F2: Budgets | G2: Budgets | H2: Budgets | I2: Budgets | J2: Budgets | K2: Budgets | L2: Budgets | M2: Budgets | N2: Budgets | O2: Budgets | P2: Budgets | Q2: Budgets
A3: Digital product | B3: Salaries and Wages | C3: Salaries and Wages | D3: 91101-91107 | E3: =SUM(F3:Q3) -> 1229549.1 | F3: =SUMIFS(F$53:F$318,$A$53:$A$318,"India",$C$53:$C$318,$C3)/'Shared Summary by Dept_US$'!$B$31+SUMIFS(F$53:F$318,$A$53:$A$318,"INDO",$C$53:$C$318,$C3)/'Shared Summary by Dept_US$'!$B$32+SUMIFS(F$53:F$318,$A$53:$A$318,"BD",$C$53:$C$318,$C3)/'Shared Summary by Dept_US$'!$B$33+SUMIFS(F$53:F$318,$A$53:$A$318,"Nepal",$C$53:$C$318,$C3)/'Shared Summary by Dept_US$'!$B$34+SUMIFS(F$53:F$318,$A$53:$A$318,"US",$C$53:$C$318,$C3)/'Shared Summary by Dept_US$'!$B$35 -> 76195.929 | G3: =SUMIFS(G$53:G$318,$A$53:$A$318,"India",$C$53:$C$318,$C3)/'Shared Summary by Dept_US$'!$B$31+SUMIFS(G$53:G$318,$A$53:$A$318,"INDO",$C$53:$C$318,$C3)/'Shared Summary by Dept_US$'!$B$32+SUMIFS(G$53:G$318,$A$53:$A$318,"BD",$C$53:$C$318,$C3)/'Shared Summary by Dept_US$'!$B$33+SUMIFS(G$53:G$318,$A$53:$A$318,"Nepal",$C$53:$C$318,$C3)/'Shared Summary by Dept_US$'!$B$34+SUMIFS(G$53:G$318,$A$53:$A$318,"US",$C$53:$C$318,$C3)/'Shared Summary by Dept_US$'!$B$35 -> 80973.188 | H3: =SUMIFS(H$53:H$318,$A$53:$A$318,"India",$C$53:$C$318,$C3)/'Shared Summary by Dept_US$'!$B$31+SUMIFS(H$53:H$318,$A$53:$A$318,"INDO",$C$53:$C$318,$C3)/'Shared Summary by Dept_US$'!$B$32+SUMIFS(H$53:H$318,$A$53:$A$318,"BD",$C$53:$C$318,$C3)/'Shared Summary by Dept_US$'!$B$33+SUMIFS(H$53:H$318,$A$53:$A$318,"Nepal",$C$53:$C$318,$C3)/'Shared Summary by Dept_US$'!$B$34+SUMIFS(H$53:H$318,$A$53:$A$318,"US",$C$53:$C$318,$C3)/'Shared Summary by Dept_US$'!$B$35 -> 81308.244 | I3: =SUMIFS(I$53:I$318,$A$53:$A$318,"India",$C$53:$C$318,$C3)/'Shared Summary by Dept_US$'!$B$31+SUMIFS(I$53:I$318,$A$53:$A$318,"INDO",$C$53:$C$318,$C3)/'Shared Summary by Dept_US$'!$B$32+SUMIFS(I$53:I$318,$A$53:$A$318,"BD",$C$53:$C$318,$C3)/'Shared Summary by Dept_US$'!$B$33+SUMIFS(I$53:I$318,$A$53:$A$318,"Nepal",$C$53:$C$318,$C3)/'Shared Summary by Dept_US$'!$B$34+SUMIFS(I$53:I$318,$A$53:$A$318,"US",$C$53:$C$318,$C3)/'Shared Summary by Dept_US$'!$B$35 -> 104534.12 | J3: =SUMIFS(J$53:J$318,$A$53:$A$318,"India",$C$53:$C$318,$C3)/'Shared Summary by Dept_US$'!$B$31+SUMIFS(J$53:J$318,$A$53:$A$318,"INDO",$C$53:$C$318,$C3)/'Shared Summary by Dept_US$'!$B$32+SUMIFS(J$53:J$318,$A$53:$A$318,"BD",$C$53:$C$318,$C3)/'Shared Summary by Dept_US$'!$B$33+SUMIFS(J$53:J$318,$A$53:$A$318,"Nepal",$C$53:$C$318,$C3)/'Shared Summary by Dept_US$'!$B$34+SUMIFS(J$53:J$318,$A$53:$A$318,"US",$C$53:$C$318,$C3)/'Shared Summary by Dept_US$'!$B$35 -> 112902.96 | K3: =SUMIFS(K$53:K$318,$A$53:$A$318,"India",$C$53:$C$318,$C3)/'Shared Summary by Dept_US$'!$B$31+SUMIFS(K$53:K$318,$A$53:$A$318,"INDO",$C$53:$C$318,$C3)/'Shared Summary by Dept_US$'!$B$32+SUMIFS(K$53:K$318,$A$53:$A$318,"BD",$C$53:$C$318,$C3)/'Shared Summary by Dept_US$'!$B$33+SUMIFS(K$53:K$318,$A$53:$A$318,"Nepal",$C$53:$C$318,$C3)/'Shared Summary by Dept_US$'!$B$34+SUMIFS(K$53:K$318,$A$53:$A$318,"US",$C$53:$C$318,$C3)/'Shared Summary by Dept_US$'!$B$35 -> 112657.08 | L3: =SUMIFS(L$53:L$318,$A$53:$A$318,"India",$C$53:$C$318,$C3)/'Shared Summary by Dept_US$'!$B$31+SUMIFS(L$53:L$318,$A$53:$A$318,"INDO",$C$53:$C$318,$C3)/'Shared Summary by Dept_US$'!$B$32+SUMIFS(L$53:L$318,$A$53:$A$318,"BD",$C$53:$C$318,$C3)/'Shared Summary by Dept_US$'!$B$33+SUMIFS(L$53:L$318,$A$53:$A$318,"Nepal",$C$53:$C$318,$C3)/'Shared Summary by Dept_US$'!$B$34+SUMIFS(L$53:L$318,$A$53:$A$318,"US",$C$53:$C$318,$C3)/'Shared Summary by Dept_US$'!$B$35 -> 110162.93 | M3: =SUMIFS(M$53:M$318,$A$53:$A$318,"India",$C$53:$C$318,$C3)/'Shared Summary by Dept_US$'!$B$31+SUMIFS(M$53:M$318,$A$53:$A$318,"INDO",$C$53:$C$318,$C3)/'Shared Summary by Dept_US$'!$B$32+SUMIFS(M$53:M$318,$A$53:$A$318,"BD",$C$53:$C$318,$C3)/'Shared Summary by Dept_US$'!$B$33+SUMIFS(M$53:M$318,$A$53:$A$318,"Nepal",$C$53:$C$318,$C3)/'Shared Summary by Dept_US$'!$B$34+SUMIFS(M$53:M$318,$A$53:$A$318,"US",$C$53:$C$318,$C3)/'Shared Summary by Dept_US$'!$B$35 -> 110162.93 | ... Q3: =SUMIFS(Q$53:Q$318,$A$53:$A$318,"India",$C$53:$C$318,$C3)/'Shared Summary by Dept_US$'!$B$31+SUMIFS(Q$53:Q$318,$A$53:$A$318,"INDO",$C$53:$C$318,$C3)/'Shared Summary by Dept_US$'!$B$32+SUMIFS(Q$53:Q$318,$A$53:$A$318,"BD",$C$53:$C$318,$C3)/'Shared Summary by Dept_US$'!$B$33+SUMIFS(Q$53:Q$318,$A$53:$A$318,"Nepal",$C$53:$C$318,$C3)/'Shared Summary by Dept_US$'!$B$34+SUMIFS(Q$53:Q$318,$A$53:$A$318,"US",$C$53:$C$318,$C3)/'Shared Summary by Dept_US$'!$B$35 -> 110162.93
A4: Digital product | B4: Health and Retirement Benefits | C4: Gratuity & Bonus | D4: 91201-91207 | E4: =SUM(F4:Q4) -> 21501.757 | F4: =SUMIFS(F$53:F$318,$A$53:$A$318,"India",$C$53:$C$318,$C4)/'Shared Summary by Dept_US$'!$B$31+SUMIFS(F$53:F$318,$A$53:$A$318,"INDO",$C$53:$C$318,$C4)/'Shared Summary by Dept_US$'!$B$32+SUMIFS(F$53:F$318,$A$53:$A$318,"BD",$C$53:$C$318,$C4)/'Shared Summary by Dept_US$'!$B$33+SUMIFS(F$53:F$318,$A$53:$A$318,"Nepal",$C$53:$C$318,$C4)/'Shared Summary by Dept_US$'!$B$34+SUMIFS(F$53:F$318,$A$53:$A$318,"US",$C$53:$C$318,$C4)/'Shared Summary by Dept_US$'!$B$35 -> 1491.1494 | G4: =SUMIFS(G$53:G$318,$A$53:$A$318,"India",$C$53:$C$318,$C4)/'Shared Summary by Dept_US$'!$B$31+SUMIFS(G$53:G$318,$A$53:$A$318,"INDO",$C$53:$C$318,$C4)/'Shared Summary by Dept_US$'!$B$32+SUMIFS(G$53:G$318,$A$53:$A$318,"BD",$C$53:$C$318,$C4)/'Shared Summary by Dept_US$'!$B$33+SUMIFS(G$53:G$318,$A$53:$A$318,"Nepal",$C$53:$C$318,$C4)/'Shared Summary by Dept_US$'!$B$34+SUMIFS(G$53:G$318,$A$53:$A$318,"US",$C$53:$C$318,$C4)/'Shared Summary by Dept_US$'!$B$35 -> 837.2 | H4: =SUMIFS(H$53:H$318,$A$53:$A$318,"India",$C$53:$C$318,$C4)/'Shared Summary by Dept_US$'!$B$31+SUMIFS(H$53:H$318,$A$53:$A$318,"INDO",$C$53:$C$318,$C4)/'Shared Summary by Dept_US$'!$B$32+SUMIFS(H$53:H$318,$A$53:$A$318,"BD",$C$53:$C$318,$C4)/'Shared Summary by Dept_US$'!$B$33+SUMIFS(H$53:H$318,$A$53:$A$318,"Nepal",$C$53:$C$318,$C4)/'Shared Summary by Dept_US$'!$B$34+SUMIFS(H$53:H$318,$A$53:$A$318,"US",$C$53:$C$318,$C4)/'Shared Summary by Dept_US$'!$B$35 -> 15204.598 | I4: =SUMIFS(I$53:I$318,$A$53:$A$318,"India",$C$53:$C$318,$C4)/'Shared Summary by Dept_US$'!$B$31+SUMIFS(I$53:I$318,$A$53:$A$318,"INDO",$C$53:$C$318,$C4)/'Shared Summary by Dept_US$'!$B$32+SUMIFS(I$53:I$318,$A$53:$A$318,"BD",$C$53:$C$318,$C4)/'Shared Summary by Dept_US$'!$B$33+SUMIFS(I$53:I$318,$A$53:$A$318,"Nepal",$C$53:$C$318,$C4)/'Shared Summary by Dept_US$'!$B$34+SUMIFS(I$53:I$318,$A$53:$A$318,"US",$C$53:$C$318,$C4)/'Shared Summary by Dept_US$'!$B$35 -> 0 | J4: =SUMIFS(J$53:J$318,$A$53:$A$318,"India",$C$53:$C$318,$C4)/'Shared Summary by Dept_US$'!$B$31+SUMIFS(J$53:J$318,$A$53:$A$318,"INDO",$C$53:$C$318,$C4)/'Shared Summary by Dept_US$'!$B$32+SUMIFS(J$53:J$318,$A$53:$A$318,"BD",$C$53:$C$318,$C4)/'Shared Summary by Dept_US$'!$B$33+SUMIFS(J$53:J$318,$A$53:$A$318,"Nepal",$C$53:$C$318,$C4)/'Shared Summary by Dept_US$'!$B$34+SUMIFS(J$53:J$318,$A$53:$A$318,"US",$C$53:$C$318,$C4)/'Shared Summary by Dept_US$'!$B$35 -> 0 | K4: =SUMIFS(K$53:K$318,$A$53:$A$318,"India",$C$53:$C$318,$C4)/'Shared Summary by Dept_US$'!$B$31+SUMIFS(K$53:K$318,$A$53:$A$318,"INDO",$C$53:$C$318,$C4)/'Shared Summary by Dept_US$'!$B$32+SUMIFS(K$53:K$318,$A$53:$A$318,"BD",$C$53:$C$318,$C4)/'Shared Summary by Dept_US$'!$B$33+SUMIFS(K$53:K$318,$A$53:$A$318,"Nepal",$C$53:$C$318,$C4)/'Shared Summary by Dept_US$'!$B$34+SUMIFS(K$53:K$318,$A$53:$A$318,"US",$C$53:$C$318,$C4)/'Shared Summary by Dept_US$'!$B$35 -> 3190.3381 | L4: =SUMIFS(L$53:L$318,$A$53:$A$318,"India",$C$53:$C$318,$C4)/'Shared Summary by Dept_US$'!$B$31+SUMIFS(L$53:L$318,$A$53:$A$318,"INDO",$C$53:$C$318,$C4)/'Shared Summary by Dept_US$'!$B$32+SUMIFS(L$53:L$318,$A$53:$A$318,"BD",$C$53:$C$318,$C4)/'Shared Summary by Dept_US$'!$B$33+SUMIFS(L$53:L$318,$A$53:$A$318,"Nepal",$C$53:$C$318,$C4)/'Shared Summary by Dept_US$'!$B$34+SUMIFS(L$53:L$318,$A$53:$A$318,"US",$C$53:$C$318,$C4)/'Shared Summary by Dept_US$'!$B$35 -> 0 | M4: =SUMIFS(M$53:M$318,$A$53:$A$318,"India",$C$53:$C$318,$C4)/'Shared Summary by Dept_US$'!$B$31+SUMIFS(M$53:M$318,$A$53:$A$318,"INDO",$C$53:$C$318,$C4)/'Shared Summary by Dept_US$'!$B$32+SUMIFS(M$53:M$318,$A$53:$A$318,"BD",$C$53:$C$318,$C4)/'Shared Summary by Dept_US$'!$B$33+SUMIFS(M$53:M$318,$A$53:$A$318,"Nepal",$C$53:$C$318,$C4)/'Shared Summary by Dept_US$'!$B$34+SUMIFS(M$53:M$318,$A$53:$A$318,"US",$C$53:$C$318,$C4)/'Shared Summary by Dept_US$'!$B$35 -> 0 | ... Q4: =SUMIFS(Q$53:Q$318,$A$53:$A$318,"India",$C$53:$C$318,$C4)/'Shared Summary by Dept_US$'!$B$31+SUMIFS(Q$53:Q$318,$A$53:$A$318,"INDO",$C$53:$C$318,$C4)/'Shared Summary by Dept_US$'!$B$32+SUMIFS(Q$53:Q$318,$A$53:$A$318,"BD",$C$53:$C$318,$C4)/'Shared Summary by Dept_US$'!$B$33+SUMIFS(Q$53:Q$318,$A$53:$A$318,"Nepal",$C$53:$C$318,$C4)/'Shared Summary by Dept_US$'!$B$34+SUMIFS(Q$53:Q$318,$A$53:$A$318,"US",$C$53:$C$318,$C4)/'Shared Summary by Dept_US$'!$B$35 -> 0
A5: Digital product | B5: Health and Retirement Benefits | C5: Staff Insurance | D5: 91207 | E5: =SUM(F5:Q5) -> 0 | F5: =SUMIFS(F$53:F$318,$A$53:$A$318,"India",$C$53:$C$318,$C5)/'Shared Summary by Dept_US$'!$B$31+SUMIFS(F$53:F$318,$A$53:$A$318,"INDO",$C$53:$C$318,$C5)/'Shared Summary by Dept_US$'!$B$32+SUMIFS(F$53:F$318,$A$53:$A$318,"BD",$C$53:$C$318,$C5)/'Shared Summary by Dept_US$'!$B$33+SUMIFS(F$53:F$318,$A$53:$A$318,"Nepal",$C$53:$C$318,$C5)/'Shared Summary by Dept_US$'!$B$34+SUMIFS(F$53:F$318,$A$53:$A$318,"US",$C$53:$C$318,$C5)/'Shared Summary by Dept_US$'!$B$35 -> 0 | G5: =SUMIFS(G$53:G$318,$A$53:$A$318,"India",$C$53:$C$318,$C5)/'Shared Summary by Dept_US$'!$B$31+SUMIFS(G$53:G$318,$A$53:$A$318,"INDO",$C$53:$C$318,$C5)/'Shared Summary by Dept_US$'!$B$32+SUMIFS(G$53:G$318,$A$53:$A$318,"BD",$C$53:$C$318,$C5)/'Shared Summary by Dept_US$'!$B$33+SUMIFS(G$53:G$318,$A$53:$A$318,"Nepal",$C$53:$C$318,$C5)/'Shared Summary by Dept_US$'!$B$34+SUMIFS(G$53:G$318,$A$53:$A$318,"US",$C$53:$C$318,$C5)/'Shared Summary by Dept_US$'!$B$35 -> 0 | H5: =SUMIFS(H$53:H$318,$A$53:$A$318,"India",$C$53:$C$318,$C5)/'Shared Summary by Dept_US$'!$B$31+SUMIFS(H$53:H$318,$A$53:$A$318,"INDO",$C$53:$C$318,$C5)/'Shared Summary by Dept_US$'!$B$32+SUMIFS(H$53:H$318,$A$53:$A$318,"BD",$C$53:$C$318,$C5)/'Shared Summary by Dept_US$'!$B$33+SUMIFS(H$53:H$318,$A$53:$A$318,"Nepal",$C$53:$C$318,$C5)/'Shared Summary by Dept_US$'!$B$34+SUMIFS(H$53:H$318,$A$53:$A$318,"US",$C$53:$C$318,$C5)/'Shared Summary by Dept_US$'!$B$35 -> 0 | I5: =SUMIFS(I$53:I$318,$A$53:$A$318,"India",$C$53:$C$318,$C5)/'Shared Summary by Dept_US$'!$B$31+SUMIFS(I$53:I$318,$A$53:$A$318,"INDO",$C$53:$C$318,$C5)/'Shared Summary by Dept_US$'!$B$32+SUMIFS(I$53:I$318,$A$53:$A$318,"BD",$C$53:$C$318,$C5)/'Shared Summary by Dept_US$'!$B$33+SUMIFS(I$53:I$318,$A$53:$A$318,"Nepal",$C$53:$C$318,$C5)/'Shared Summary by Dept_US$'!$B$34+SUMIFS(I$53:I$318,$A$53:$A$318,"US",$C$53:$C$318,$C5)/'Shared Summary by Dept_US$'!$B$35 -> 0 | J5: =SUMIFS(J$53:J$318,$A$53:$A$318,"India",$C$53:$C$318,$C5)/'Shared Summary by Dept_US$'!$B$31+SUMIFS(J$53:J$318,$A$53:$A$318,"INDO",$C$53:$C$318,$C5)/'Shared Summary by Dept_US$'!$B$32+SUMIFS(J$53:J$318,$A$53:$A$318,"BD",$C$53:$C$318,$C5)/'Shared Summary by Dept_US$'!$B$33+SUMIFS(J$53:J$318,$A$53:$A$318,"Nepal",$C$53:$C$318,$C5)/'Shared Summary by Dept_US$'!$B$34+SUMIFS(J$53:J$318,$A$53:$A$318,"US",$C$53:$C$318,$C5)/'Shared Summary by Dept_US$'!$B$35 -> 0 | K5: =SUMIFS(K$53:K$318,$A$53:$A$318,"India",$C$53:$C$318,$C5)/'Shared Summary by Dept_US$'!$B$31+SUMIFS(K$53:K$318,$A$53:$A$318,"INDO",$C$53:$C$318,$C5)/'Shared Summary by Dept_US$'!$B$32+SUMIFS(K$53:K$318,$A$53:$A$318,"BD",$C$53:$C$318,$C5)/'Shared Summary by Dept_US$'!$B$33+SUMIFS(K$53:K$318,$A$53:$A$318,"Nepal",$C$53:$C$318,$C5)/'Shared Summary by Dept_US$'!$B$34+SUMIFS(K$53:K$318,$A$53:$A$318,"US",$C$53:$C$318,$C5)/'Shared Summary by Dept_US$'!$B$35 -> 0 | L5: =SUMIFS(L$53:L$318,$A$53:$A$318,"India",$C$53:$C$318,$C5)/'Shared Summary by Dept_US$'!$B$31+SUMIFS(L$53:L$318,$A$53:$A$318,"INDO",$C$53:$C$318,$C5)/'Shared Summary by Dept_US$'!$B$32+SUMIFS(L$53:L$318,$A$53:$A$318,"BD",$C$53:$C$318,$C5)/'Shared Summary by Dept_US$'!$B$33+SUMIFS(L$53:L$318,$A$53:$A$318,"Nepal",$C$53:$C$318,$C5)/'Shared Summary by Dept_US$'!$B$34+SUMIFS(L$53:L$318,$A$53:$A$318,"US",$C$53:$C$318,$C5)/'Shared Summary by Dept_US$'!$B$35 -> 0 | M5: =SUMIFS(M$53:M$318,$A$53:$A$318,"India",$C$53:$C$318,$C5)/'Shared Summary by Dept_US$'!$B$31+SUMIFS(M$53:M$318,$A$53:$A$318,"INDO",$C$53:$C$318,$C5)/'Shared Summary by Dept_US$'!$B$32+SUMIFS(M$53:M$318,$A$53:$A$318,"BD",$C$53:$C$318,$C5)/'Shared Summary by Dept_US$'!$B$33+SUMIFS(M$53:M$318,$A$53:$A$318,"Nepal",$C$53:$C$318,$C5)/'Shared Summary by Dept_US$'!$B$34+SUMIFS(M$53:M$318,$A$53:$A$318,"US",$C$53:$C$318,$C5)/'Shared Summary by Dept_US$'!$B$35 -> 0 | ... Q5: =SUMIFS(Q$53:Q$318,$A$53:$A$318,"India",$C$53:$C$318,$C5)/'Shared Summary by Dept_US$'!$B$31+SUMIFS(Q$53:Q$318,$A$53:$A$318,"INDO",$C$53:$C$318,$C5)/'Shared Summary by Dept_US$'!$B$32+SUMIFS(Q$53:Q$318,$A$53:$A$318,"BD",$C$53:$C$318,$C5)/'Shared Summary by Dept_US$'!$B$33+SUMIFS(Q$53:Q$318,$A$53:$A$318,"Nepal",$C$53:$C$318,$C5)/'Shared Summary by Dept_US$'!$B$34+SUMIFS(Q$53:Q$318,$A$53:$A$318,"US",$C$53:$C$318,$C5)/'Shared Summary by Dept_US$'!$B$35 -> 0
A6: Digital product | B6: Other Staff Expenses | C6: Internal meetings | D6: 91301 | E6: =SUM(F6:Q6) -> 0 | F6: =SUMIFS(F$53:F$318,$A$53:$A$318,"India",$C$53:$C$318,$C6)/'Shared Summary by Dept_US$'!$B$31+SUMIFS(F$53:F$318,$A$53:$A$318,"INDO",$C$53:$C$318,$C6)/'Shared Summary by Dept_US$'!$B$32+SUMIFS(F$53:F$318,$A$53:$A$318,"BD",$C$53:$C$318,$C6)/'Shared Summary by Dept_US$'!$B$33+SUMIFS(F$53:F$318,$A$53:$A$318,"Nepal",$C$53:$C$318,$C6)/'Shared Summary by Dept_US$'!$B$34+SUMIFS(F$53:F$318,$A$53:$A$318,"US",$C$53:$C$318,$C6)/'Shared Summary by Dept_US$'!$B$35 -> 0 | G6: =SUMIFS(G$53:G$318,$A$53:$A$318,"India",$C$53:$C$318,$C6)/'Shared Summary by Dept_US$'!$B$31+SUMIFS(G$53:G$318,$A$53:$A$318,"INDO",$C$53:$C$318,$C6)/'Shared Summary by Dept_US$'!$B$32+SUMIFS(G$53:G$318,$A$53:$A$318,"BD",$C$53:$C$318,$C6)/'Shared Summary by Dept_US$'!$B$33+SUMIFS(G$53:G$318,$A$53:$A$318,"Nepal",$C$53:$C$318,$C6)/'Shared Summary by Dept_US$'!$B$34+SUMIFS(G$53:G$318,$A$53:$A$318,"US",$C$53:$C$318,$C6)/'Shared Summary by Dept_US$'!$B$35 -> 0 | H6: =SUMIFS(H$53:H$318,$A$53:$A$318,"India",$C$53:$C$318,$C6)/'Shared Summary by Dept_US$'!$B$31+SUMIFS(H$53:H$318,$A$53:$A$318,"INDO",$C$53:$C$318,$C6)/'Shared Summary by Dept_US$'!$B$32+SUMIFS(H$53:H$318,$A$53:$A$318,"BD",$C$53:$C$318,$C6)/'Shared Summary by Dept_US$'!$B$33+SUMIFS(H$53:H$318,$A$53:$A$318,"Nepal",$C$53:$C$318,$C6)/'Shared Summary by Dept_US$'!$B$34+SUMIFS(H$53:H$318,$A$53:$A$318,"US",$C$53:$C$318,$C6)/'Shared Summary by Dept_US$'!$B$35 -> 0 | I6: =SUMIFS(I$53:I$318,$A$53:$A$318,"India",$C$53:$C$318,$C6)/'Shared Summary by Dept_US$'!$B$31+SUMIFS(I$53:I$318,$A$53:$A$318,"INDO",$C$53:$C$318,$C6)/'Shared Summary by Dept_US$'!$B$32+SUMIFS(I$53:I$318,$A$53:$A$318,"BD",$C$53:$C$318,$C6)/'Shared Summary by Dept_US$'!$B$33+SUMIFS(I$53:I$318,$A$53:$A$318,"Nepal",$C$53:$C$318,$C6)/'Shared Summary by Dept_US$'!$B$34+SUMIFS(I$53:I$318,$A$53:$A$318,"US",$C$53:$C$318,$C6)/'Shared Summary by Dept_US$'!$B$35 -> 0 | J6: =SUMIFS(J$53:J$318,$A$53:$A$318,"India",$C$53:$C$318,$C6)/'Shared Summary by Dept_US$'!$B$31+SUMIFS(J$53:J$318,$A$53:$A$318,"INDO",$C$53:$C$318,$C6)/'Shared Summary by Dept_US$'!$B$32+SUMIFS(J$53:J$318,$A$53:$A$318,"BD",$C$53:$C$318,$C6)/'Shared Summary by Dept_US$'!$B$33+SUMIFS(J$53:J$318,$A$53:$A$318,"Nepal",$C$53:$C$318,$C6)/'Shared Summary by Dept_US$'!$B$34+SUMIFS(J$53:J$318,$A$53:$A$318,"US",$C$53:$C$318,$C6)/'Shared Summary by Dept_US$'!$B$35 -> 0 | K6: =SUMIFS(K$53:K$318,$A$53:$A$318,"India",$C$53:$C$318,$C6)/'Shared Summary by Dept_US$'!$B$31+SUMIFS(K$53:K$318,$A$53:$A$318,"INDO",$C$53:$C$318,$C6)/'Shared Summary by Dept_US$'!$B$32+SUMIFS(K$53:K$318,$A$53:$A$318,"BD",$C$53:$C$318,$C6)/'Shared Summary by Dept_US$'!$B$33+SUMIFS(K$53:K$318,$A$53:$A$318,"Nepal",$C$53:$C$318,$C6)/'Shared Summary by Dept_US$'!$B$34+SUMIFS(K$53:K$318,$A$53:$A$318,"US",$C$53:$C$318,$C6)/'Shared Summary by Dept_US$'!$B$35 -> 0 | L6: =SUMIFS(L$53:L$318,$A$53:$A$318,"India",$C$53:$C$318,$C6)/'Shared Summary by Dept_US$'!$B$31+SUMIFS(L$53:L$318,$A$53:$A$318,"INDO",$C$53:$C$318,$C6)/'Shared Summary by Dept_US$'!$B$32+SUMIFS(L$53:L$318,$A$53:$A$318,"BD",$C$53:$C$318,$C6)/'Shared Summary by Dept_US$'!$B$33+SUMIFS(L$53:L$318,$A$53:$A$318,"Nepal",$C$53:$C$318,$C6)/'Shared Summary by Dept_US$'!$B$34+SUMIFS(L$53:L$318,$A$53:$A$318,"US",$C$53:$C$318,$C6)/'Shared Summary by Dept_US$'!$B$35 -> 0 | M6: =SUMIFS(M$53:M$318,$A$53:$A$318,"India",$C$53:$C$318,$C6)/'Shared Summary by Dept_US$'!$B$31+SUMIFS(M$53:M$318,$A$53:$A$318,"INDO",$C$53:$C$318,$C6)/'Shared Summary by Dept_US$'!$B$32+SUMIFS(M$53:M$318,$A$53:$A$318,"BD",$C$53:$C$318,$C6)/'Shared Summary by Dept_US$'!$B$33+SUMIFS(M$53:M$318,$A$53:$A$318,"Nepal",$C$53:$C$318,$C6)/'Shared Summary by Dept_US$'!$B$34+SUMIFS(M$53:M$318,$A$53:$A$318,"US",$C$53:$C$318,$C6)/'Shared Summary by Dept_US$'!$B$35 -> 0 | ... Q6: =SUMIFS(Q$53:Q$318,$A$53:$A$318,"India",$C$53:$C$318,$C6)/'Shared Summary by Dept_US$'!$B$31+SUMIFS(Q$53:Q$318,$A$53:$A$318,"INDO",$C$53:$C$318,$C6)/'Shared Summary by Dept_US$'!$B$32+SUMIFS(Q$53:Q$318,$A$53:$A$318,"BD",$C$53:$C$318,$C6)/'Shared Summary by Dept_US$'!$B$33+SUMIFS(Q$53:Q$318,$A$53:$A$318,"Nepal",$C$53:$C$318,$C6)/'Shared Summary by Dept_US$'!$B$34+SUMIFS(Q$53:Q$318,$A$53:$A$318,"US",$C$53:$C$318,$C6)/'Shared Summary by Dept_US$'!$B$35 -> 0
A7: Digital product | B7: Other Staff Expenses | C7: Staff Training, Learning & Development Exp | D7: 91302 | E7: =SUM(F7:Q7) -> 0 | F7: =SUMIFS(F$53:F$318,$A$53:$A$318,"India",$C$53:$C$318,$C7)/'Shared Summary by Dept_US$'!$B$31+SUMIFS(F$53:F$318,$A$53:$A$318,"INDO",$C$53:$C$318,$C7)/'Shared Summary by Dept_US$'!$B$32+SUMIFS(F$53:F$318,$A$53:$A$318,"BD",$C$53:$C$318,$C7)/'Shared Summary by Dept_US$'!$B$33+SUMIFS(F$53:F$318,$A$53:$A$318,"Nepal",$C$53:$C$318,$C7)/'Shared Summary by Dept_US$'!$B$34+SUMIFS(F$53:F$318,$A$53:$A$318,"US",$C$53:$C$318,$C7)/'Shared Summary by Dept_US$'!$B$35 -> 0 | G7: =SUMIFS(G$53:G$318,$A$53:$A$318,"India",$C$53:$C$318,$C7)/'Shared Summary by Dept_US$'!$B$31+SUMIFS(G$53:G$318,$A$53:$A$318,"INDO",$C$53:$C$318,$C7)/'Shared Summary by Dept_US$'!$B$32+SUMIFS(G$53:G$318,$A$53:$A$318,"BD",$C$53:$C$318,$C7)/'Shared Summary by Dept_US$'!$B$33+SUMIFS(G$53:G$318,$A$53:$A$318,"Nepal",$C$53:$C$318,$C7)/'Shared Summary by Dept_US$'!$B$34+SUMIFS(G$53:G$318,$A$53:$A$318,"US",$C$53:$C$318,$C7)/'Shared Summary by Dept_US$'!$B$35 -> 0 | H7: =SUMIFS(H$53:H$318,$A$53:$A$318,"India",$C$53:$C$318,$C7)/'Shared Summary by Dept_US$'!$B$31+SUMIFS(H$53:H$318,$A$53:$A$318,"INDO",$C$53:$C$318,$C7)/'Shared Summary by Dept_US$'!$B$32+SUMIFS(H$53:H$318,$A$53:$A$318,"BD",$C$53:$C$318,$C7)/'Shared Summary by Dept_US$'!$B$33+SUMIFS(H$53:H$318,$A$53:$A$318,"Nepal",$C$53:$C$318,$C7)/'Shared Summary by Dept_US$'!$B$34+SUMIFS(H$53:H$318,$A$53:$A$318,"US",$C$53:$C$318,$C7)/'Shared Summary by Dept_US$'!$B$35 -> 0 | I7: =SUMIFS(I$53:I$318,$A$53:$A$318,"India",$C$53:$C$318,$C7)/'Shared Summary by Dept_US$'!$B$31+SUMIFS(I$53:I$318,$A$53:$A$318,"INDO",$C$53:$C$318,$C7)/'Shared Summary by Dept_US$'!$B$32+SUMIFS(I$53:I$318,$A$53:$A$318,"BD",$C$53:$C$318,$C7)/'Shared Summary by Dept_US$'!$B$33+SUMIFS(I$53:I$318,$A$53:$A$318,"Nepal",$C$53:$C$318,$C7)/'Shared Summary by Dept_US$'!$B$34+SUMIFS(I$53:I$318,$A$53:$A$318,"US",$C$53:$C$318,$C7)/'Shared Summary by Dept_US$'!$B$35 -> 0 | J7: =SUMIFS(J$53:J$318,$A$53:$A$318,"India",$C$53:$C$318,$C7)/'Shared Summary by Dept_US$'!$B$31+SUMIFS(J$53:J$318,$A$53:$A$318,"INDO",$C$53:$C$318,$C7)/'Shared Summary by Dept_US$'!$B$32+SUMIFS(J$53:J$318,$A$53:$A$318,"BD",$C$53:$C$318,$C7)/'Shared Summary by Dept_US$'!$B$33+SUMIFS(J$53:J$318,$A$53:$A$318,"Nepal",$C$53:$C$318,$C7)/'Shared Summary by Dept_US$'!$B$34+SUMIFS(J$53:J$318,$A$53:$A$318,"US",$C$53:$C$318,$C7)/'Shared Summary by Dept_US$'!$B$35 -> 0 | K7: =SUMIFS(K$53:K$318,$A$53:$A$318,"India",$C$53:$C$318,$C7)/'Shared Summary by Dept_US$'!$B$31+SUMIFS(K$53:K$318,$A$53:$A$318,"INDO",$C$53:$C$318,$C7)/'Shared Summary by Dept_US$'!$B$32+SUMIFS(K$53:K$318,$A$53:$A$318,"BD",$C$53:$C$318,$C7)/'Shared Summary by Dept_US$'!$B$33+SUMIFS(K$53:K$318,$A$53:$A$318,"Nepal",$C$53:$C$318,$C7)/'Shared Summary by Dept_US$'!$B$34+SUMIFS(K$53:K$318,$A$53:$A$318,"US",$C$53:$C$318,$C7)/'Shared Summary by Dept_US$'!$B$35 -> 0 | L7: =SUMIFS(L$53:L$318,$A$53:$A$318,"India",$C$53:$C$318,$C7)/'Shared Summary by Dept_US$'!$B$31+SUMIFS(L$53:L$318,$A$53:$A$318,"INDO",$C$53:$C$318,$C7)/'Shared Summary by Dept_US$'!$B$32+SUMIFS(L$53:L$318,$A$53:$A$318,"BD",$C$53:$C$318,$C7)/'Shared Summary by Dept_US$'!$B$33+SUMIFS(L$53:L$318,$A$53:$A$318,"Nepal",$C$53:$C$318,$C7)/'Shared Summary by Dept_US$'!$B$34+SUMIFS(L$53:L$318,$A$53:$A$318,"US",$C$53:$C$318,$C7)/'Shared Summary by Dept_US$'!$B$35 -> 0 | M7: =SUMIFS(M$53:M$318,$A$53:$A$318,"India",$C$53:$C$318,$C7)/'Shared Summary by Dept_US$'!$B$31+SUMIFS(M$53:M$318,$A$53:$A$318,"INDO",$C$53:$C$318,$C7)/'Shared Summary by Dept_US$'!$B$32+SUMIFS(M$53:M$318,$A$53:$A$318,"BD",$C$53:$C$318,$C7)/'Shared Summary by Dept_US$'!$B$33+SUMIFS(M$53:M$318,$A$53:$A$318,"Nepal",$C$53:$C$318,$C7)/'Shared Summary by Dept_US$'!$B$34+SUMIFS(M$53:M$318,$A$53:$A$318,"US",$C$53:$C$318,$C7)/'Shared Summary by Dept_US$'!$B$35 -> 0 | ... Q7: =SUMIFS(Q$53:Q$318,$A$53:$A$318,"India",$C$53:$C$318,$C7)/'Shared Summary by Dept_US$'!$B$31+SUMIFS(Q$53:Q$318,$A$53:$A$318,"INDO",$C$53:$C$318,$C7)/'Shared Summary by Dept_US$'!$B$32+SUMIFS(Q$53:Q$318,$A$53:$A$318,"BD",$C$53:$C$318,$C7)/'Shared Summary by Dept_US$'!$B$33+SUMIFS(Q$53:Q$318,$A$53:$A$318,"Nepal",$C$53:$C$318,$C7)/'Shared Summary by Dept_US$'!$B$34+SUMIFS(Q$53:Q$318,$A$53:$A$318,"US",$C$53:$C$318,$C7)/'Shared Summary by Dept_US$'!$B$35 -> 0
A8: Digital product | B8: Other Staff Expenses | C8: Recruitment Expenses | D8: 91303 | E8: =SUM(F8:Q8) -> 0 | F8: =SUMIFS(F$53:F$318,$A$53:$A$318,"India",$C$53:$C$318,$C8)/'Shared Summary by Dept_US$'!$B$31+SUMIFS(F$53:F$318,$A$53:$A$318,"INDO",$C$53:$C$318,$C8)/'Shared Summary by Dept_US$'!$B$32+SUMIFS(F$53:F$318,$A$53:$A$318,"BD",$C$53:$C$318,$C8)/'Shared Summary by Dept_US$'!$B$33+SUMIFS(F$53:F$318,$A$53:$A$318,"Nepal",$C$53:$C$318,$C8)/'Shared Summary by Dept_US$'!$B$34+SUMIFS(F$53:F$318,$A$53:$A$318,"US",$C$53:$C$318,$C8)/'Shared Summary by Dept_US$'!$B$35 -> 0 | G8: =SUMIFS(G$53:G$318,$A$53:$A$318,"India",$C$53:$C$318,$C8)/'Shared Summary by Dept_US$'!$B$31+SUMIFS(G$53:G$318,$A$53:$A$318,"INDO",$C$53:$C$318,$C8)/'Shared Summary by Dept_US$'!$B$32+SUMIFS(G$53:G$318,$A$53:$A$318,"BD",$C$53:$C$318,$C8)/'Shared Summary by Dept_US$'!$B$33+SUMIFS(G$53:G$318,$A$53:$A$318,"Nepal",$C$53:$C$318,$C8)/'Shared Summary by Dept_US$'!$B$34+SUMIFS(G$53:G$318,$A$53:$A$318,"US",$C$53:$C$318,$C8)/'Shared Summary by Dept_US$'!$B$35 -> 0 | H8: =SUMIFS(H$53:H$318,$A$53:$A$318,"India",$C$53:$C$318,$C8)/'Shared Summary by Dept_US$'!$B$31+SUMIFS(H$53:H$318,$A$53:$A$318,"INDO",$C$53:$C$318,$C8)/'Shared Summary by Dept_US$'!$B$32+SUMIFS(H$53:H$318,$A$53:$A$318,"BD",$C$53:$C$318,$C8)/'Shared Summary by Dept_US$'!$B$33+SUMIFS(H$53:H$318,$A$53:$A$318,"Nepal",$C$53:$C$318,$C8)/'Shared Summary by Dept_US$'!$B$34+SUMIFS(H$53:H$318,$A$53:$A$318,"US",$C$53:$C$318,$C8)/'Shared Summary by Dept_US$'!$B$35 -> 0 | I8: =SUMIFS(I$53:I$318,$A$53:$A$318,"India",$C$53:$C$318,$C8)/'Shared Summary by Dept_US$'!$B$31+SUMIFS(I$53:I$318,$A$53:$A$318,"INDO",$C$53:$C$318,$C8)/'Shared Summary by Dept_US$'!$B$32+SUMIFS(I$53:I$318,$A$53:$A$318,"BD",$C$53:$C$318,$C8)/'Shared Summary by Dept_US$'!$B$33+SUMIFS(I$53:I$318,$A$53:$A$318,"Nepal",$C$53:$C$318,$C8)/'Shared Summary by Dept_US$'!$B$34+SUMIFS(I$53:I$318,$A$53:$A$318,"US",$C$53:$C$318,$C8)/'Shared Summary by Dept_US$'!$B$35 -> 0 | J8: =SUMIFS(J$53:J$318,$A$53:$A$318,"India",$C$53:$C$318,$C8)/'Shared Summary by Dept_US$'!$B$31+SUMIFS(J$53:J$318,$A$53:$A$318,"INDO",$C$53:$C$318,$C8)/'Shared Summary by Dept_US$'!$B$32+SUMIFS(J$53:J$318,$A$53:$A$318,"BD",$C$53:$C$318,$C8)/'Shared Summary by Dept_US$'!$B$33+SUMIFS(J$53:J$318,$A$53:$A$318,"Nepal",$C$53:$C$318,$C8)/'Shared Summary by Dept_US$'!$B$34+SUMIFS(J$53:J$318,$A$53:$A$318,"US",$C$53:$C$318,$C8)/'Shared Summary by Dept_US$'!$B$35 -> 0 | K8: =SUMIFS(K$53:K$318,$A$53:$A$318,"India",$C$53:$C$318,$C8)/'Shared Summary by Dept_US$'!$B$31+SUMIFS(K$53:K$318,$A$53:$A$318,"INDO",$C$53:$C$318,$C8)/'Shared Summary by Dept_US$'!$B$32+SUMIFS(K$53:K$318,$A$53:$A$318,"BD",$C$53:$C$318,$C8)/'Shared Summary by Dept_US$'!$B$33+SUMIFS(K$53:K$318,$A$53:$A$318,"Nepal",$C$53:$C$318,$C8)/'Shared Summary by Dept_US$'!$B$34+SUMIFS(K$53:K$318,$A$53:$A$318,"US",$C$53:$C$318,$C8)/'Shared Summary by Dept_US$'!$B$35 -> 0 | L8: =SUMIFS(L$53:L$318,$A$53:$A$318,"India",$C$53:$C$318,$C8)/'Shared Summary by Dept_US$'!$B$31+SUMIFS(L$53:L$318,$A$53:$A$318,"INDO",$C$53:$C$318,$C8)/'Shared Summary by Dept_US$'!$B$32+SUMIFS(L$53:L$318,$A$53:$A$318,"BD",$C$53:$C$318,$C8)/'Shared Summary by Dept_US$'!$B$33+SUMIFS(L$53:L$318,$A$53:$A$318,"Nepal",$C$53:$C$318,$C8)/'Shared Summary by Dept_US$'!$B$34+SUMIFS(L$53:L$318,$A$53:$A$318,"US",$C$53:$C$318,$C8)/'Shared Summary by Dept_US$'!$B$35 -> 0 | M8: =SUMIFS(M$53:M$318,$A$53:$A$318,"India",$C$53:$C$318,$C8)/'Shared Summary by Dept_US$'!$B$31+SUMIFS(M$53:M$318,$A$53:$A$318,"INDO",$C$53:$C$318,$C8)/'Shared Summary by Dept_US$'!$B$32+SUMIFS(M$53:M$318,$A$53:$A$318,"BD",$C$53:$C$318,$C8)/'Shared Summary by Dept_US$'!$B$33+SUMIFS(M$53:M$318,$A$53:$A$318,"Nepal",$C$53:$C$318,$C8)/'Shared Summary by Dept_US$'!$B$34+SUMIFS(M$53:M$318,$A$53:$A$318,"US",$C$53:$C$318,$C8)/'Shared Summary by Dept_US$'!$B$35 -> 0 | ... Q8: =SUMIFS(Q$53:Q$318,$A$53:$A$318,"India",$C$53:$C$318,$C8)/'Shared Summary by Dept_US$'!$B$31+SUMIFS(Q$53:Q$318,$A$53:$A$318,"INDO",$C$53:$C$318,$C8)/'Shared Summary by Dept_US$'!$B$32+SUMIFS(Q$53:Q$318,$A$53:$A$318,"BD",$C$53:$C$318,$C8)/'Shared Summary by Dept_US$'!$B$33+SUMIFS(Q$53:Q$318,$A$53:$A$318,"Nepal",$C$53:$C$318,$C8)/'Shared Summary by Dept_US$'!$B$34+SUMIFS(Q$53:Q$318,$A$53:$A$318,"US",$C$53:$C$318,$C8)/'Shared Summary by Dept_US$'!$B$35 -> 0
A9: Digital product | B9: Resource Persons | C9: Program Resource Consultant (EHA) | D9: 92101 | E9: =SUM(F9:Q9) -> 439613.03 | F9: =SUMIFS(F$53:F$318,$A$53:$A$318,"India",$C$53:$C$318,$C9)/'Shared Summary by Dept_US$'!$B$31+SUMIFS(F$53:F$318,$A$53:$A$318,"INDO",$C$53:$C$318,$C9)/'Shared Summary by Dept_US$'!$B$32+SUMIFS(F$53:F$318,$A$53:$A$318,"BD",$C$53:$C$318,$C9)/'Shared Summary by Dept_US$'!$B$33+SUMIFS(F$53:F$318,$A$53:$A$318,"Nepal",$C$53:$C$318,$C9)/'Shared Summary by Dept_US$'!$B$34+SUMIFS(F$53:F$318,$A$53:$A$318,"US",$C$53:$C$318,$C9)/'Shared Summary by Dept_US$'!$B$35 -> 39300.549 | G9: =SUMIFS(G$53:G$318,$A$53:$A$318,"India",$C$53:$C$318,$C9)/'Shared Summary by Dept_US$'!$B$31+SUMIFS(G$53:G$318,$A$53:$A$318,"INDO",$C$53:$C$318,$C9)/'Shared Summary by Dept_US$'!$B$32+SUMIFS(G$53:G$318,$A$53:$A$318,"BD",$C$53:$C$318,$C9)/'Shared Summary by Dept_US$'!$B$33+SUMIFS(G$53:G$318,$A$53:$A$318,"Nepal",$C$53:$C$318,$C9)/'Shared Summary by Dept_US$'!$B$34+SUMIFS(G$53:G$318,$A$53:$A$318,"US",$C$53:$C$318,$C9)/'Shared Summary by Dept_US$'!$B$35 -> 37729.916 | H9: =SUMIFS(H$53:H$318,$A$53:$A$318,"India",$C$53:$C$318,$C9)/'Shared Summary by Dept_US$'!$B$31+SUMIFS(H$53:H$318,$A$53:$A$318,"INDO",$C$53:$C$318,$C9)/'Shared Summary by Dept_US$'!$B$32+SUMIFS(H$53:H$318,$A$53:$A$318,"BD",$C$53:$C$318,$C9)/'Shared Summary by Dept_US$'!$B$33+SUMIFS(H$53:H$318,$A$53:$A$318,"Nepal",$C$53:$C$318,$C9)/'Shared Summary by Dept_US$'!$B$34+SUMIFS(H$53:H$318,$A$53:$A$318,"US",$C$53:$C$318,$C9)/'Shared Summary by Dept_US$'!$B$35 -> 36849.49 | I9: =SUMIFS(I$53:I$318,$A$53:$A$318,"India",$C$53:$C$318,$C9)/'Shared Summary by Dept_US$'!$B$31+SUMIFS(I$53:I$318,$A$53:$A$318,"INDO",$C$53:$C$318,$C9)/'Shared Summary by Dept_US$'!$B$32+SUMIFS(I$53:I$318,$A$53:$A$318,"BD",$C$53:$C$318,$C9)/'Shared Summary by Dept_US$'!$B$33+SUMIFS(I$53:I$318,$A$53:$A$318,"Nepal",$C$53:$C$318,$C9)/'Shared Summary by Dept_US$'!$B$34+SUMIFS(I$53:I$318,$A$53:$A$318,"US",$C$53:$C$318,$C9)/'Shared Summary by Dept_US$'!$B$35 -> 34516.168 | J9: =SUMIFS(J$53:J$318,$A$53:$A$318,"India",$C$53:$C$318,$C9)/'Shared Summary by Dept_US$'!$B$31+SUMIFS(J$53:J$318,$A$53:$A$318,"INDO",$C$53:$C$318,$C9)/'Shared Summary by Dept_US$'!$B$32+SUMIFS(J$53:J$318,$A$53:$A$318,"BD",$C$53:$C$318,$C9)/'Shared Summary by Dept_US$'!$B$33+SUMIFS(J$53:J$318,$A$53:$A$318,"Nepal",$C$53:$C$318,$C9)/'Shared Summary by Dept_US$'!$B$34+SUMIFS(J$53:J$318,$A$53:$A$318,"US",$C$53:$C$318,$C9)/'Shared Summary by Dept_US$'!$B$35 -> 36897.48 | K9: =SUMIFS(K$53:K$318,$A$53:$A$318,"India",$C$53:$C$318,$C9)/'Shared Summary by Dept_US$'!$B$31+SUMIFS(K$53:K$318,$A$53:$A$318,"INDO",$C$53:$C$318,$C9)/'Shared Summary by Dept_US$'!$B$32+SUMIFS(K$53:K$318,$A$53:$A$318,"BD",$C$53:$C$318,$C9)/'Shared Summary by Dept_US$'!$B$33+SUMIFS(K$53:K$318,$A$53:$A$318,"Nepal",$C$53:$C$318,$C9)/'Shared Summary by Dept_US$'!$B$34+SUMIFS(K$53:K$318,$A$53:$A$318,"US",$C$53:$C$318,$C9)/'Shared Summary by Dept_US$'!$B$35 -> 35766.168 | L9: =SUMIFS(L$53:L$318,$A$53:$A$318,"India",$C$53:$C$318,$C9)/'Shared Summary by Dept_US$'!$B$31+SUMIFS(L$53:L$318,$A$53:$A$318,"INDO",$C$53:$C$318,$C9)/'Shared Summary by Dept_US$'!$B$32+SUMIFS(L$53:L$318,$A$53:$A$318,"BD",$C$53:$C$318,$C9)/'Shared Summary by Dept_US$'!$B$33+SUMIFS(L$53:L$318,$A$53:$A$318,"Nepal",$C$53:$C$318,$C9)/'Shared Summary by Dept_US$'!$B$34+SUMIFS(L$53:L$318,$A$53:$A$318,"US",$C$53:$C$318,$C9)/'Shared Summary by Dept_US$'!$B$35 -> 35825.543 | M9: =SUMIFS(M$53:M$318,$A$53:$A$318,"India",$C$53:$C$318,$C9)/'Shared Summary by Dept_US$'!$B$31+SUMIFS(M$53:M$318,$A$53:$A$318,"INDO",$C$53:$C$318,$C9)/'Shared Summary by Dept_US$'!$B$32+SUMIFS(M$53:M$318,$A$53:$A$318,"BD",$C$53:$C$318,$C9)/'Shared Summary by Dept_US$'!$B$33+SUMIFS(M$53:M$318,$A$53:$A$318,"Nepal",$C$53:$C$318,$C9)/'Shared Summary by Dept_US$'!$B$34+SUMIFS(M$53:M$318,$A$53:$A$318,"US",$C$53:$C$318,$C9)/'Shared Summary by Dept_US$'!$B$35 -> 36450.543 | ... Q9: =SUMIFS(Q$53:Q$318,$A$53:$A$318,"India",$C$53:$C$318,$C9)/'Shared Summary by Dept_US$'!$B$31+SUMIFS(Q$53:Q$318,$A$53:$A$318,"INDO",$C$53:$C$318,$C9)/'Shared Summary by Dept_US$'!$B$32+SUMIFS(Q$53:Q$318,$A$53:$A$318,"BD",$C$53:$C$318,$C9)/'Shared Summary by Dept_US$'!$B$33+SUMIFS(Q$53:Q$318,$A$53:$A$318,"Nepal",$C$53:$C$318,$C9)/'Shared Summary by Dept_US$'!$B$34+SUMIFS(Q$53:Q$318,$A$53:$A$318,"US",$C$53:$C$318,$C9)/'Shared Summary by Dept_US$'!$B$35 -> 36569.293
A10: Digital product | B10: Travel & Lodging Expenses | C10: Hotel Accomodation | D10: 93101 | E10: =SUM(F10:Q10) -> 15450.467 | F10: =SUMIFS(F$53:F$318,$A$53:$A$318,"India",$C$53:$C$318,$C10)/'Shared Summary by Dept_US$'!$B$31+SUMIFS(F$53:F$318,$A$53:$A$318,"INDO",$C$53:$C$318,$C10)/'Shared Summary by Dept_US$'!$B$32+SUMIFS(F$53:F$318,$A$53:$A$318,"BD",$C$53:$C$318,$C10)/'Shared Summary by Dept_US$'!$B$33+SUMIFS(F$53:F$318,$A$53:$A$318,"Nepal",$C$53:$C$318,$C10)/'Shared Summary by Dept_US$'!$B$34+SUMIFS(F$53:F$318,$A$53:$A$318,"US",$C$53:$C$318,$C10)/'Shared Summary by Dept_US$'!$B$35 -> 325 | G10: =SUMIFS(G$53:G$318,$A$53:$A$318,"India",$C$53:$C$318,$C10)/'Shared Summary by Dept_US$'!$B$31+SUMIFS(G$53:G$318,$A$53:$A$318,"INDO",$C$53:$C$318,$C10)/'Shared Summary by Dept_US$'!$B$32+SUMIFS(G$53:G$318,$A$53:$A$318,"BD",$C$53:$C$318,$C10)/'Shared Summary by Dept_US$'!$B$33+SUMIFS(G$53:G$318,$A$53:$A$318,"Nepal",$C$53:$C$318,$C10)/'Shared Summary by Dept_US$'!$B$34+SUMIFS(G$53:G$318,$A$53:$A$318,"US",$C$53:$C$318,$C10)/'Shared Summary by Dept_US$'!$B$35 -> 700.75431 | H10: =SUMIFS(H$53:H$318,$A$53:$A$318,"India",$C$53:$C$318,$C10)/'Shared Summary by Dept_US$'!$B$31+SUMIFS(H$53:H$318,$A$53:$A$318,"INDO",$C$53:$C$318,$C10)/'Shared Summary by Dept_US$'!$B$32+SUMIFS(H$53:H$318,$A$53:$A$318,"BD",$C$53:$C$318,$C10)/'Shared Summary by Dept_US$'!$B$33+SUMIFS(H$53:H$318,$A$53:$A$318,"Nepal",$C$53:$C$318,$C10)/'Shared Summary by Dept_US$'!$B$34+SUMIFS(H$53:H$318,$A$53:$A$318,"US",$C$53:$C$318,$C10)/'Shared Summary by Dept_US$'!$B$35 -> 1733.4052 | I10: =SUMIFS(I$53:I$318,$A$53:$A$318,"India",$C$53:$C$318,$C10)/'Shared Summary by Dept_US$'!$B$31+SUMIFS(I$53:I$318,$A$53:$A$318,"INDO",$C$53:$C$318,$C10)/'Shared Summary by Dept_US$'!$B$32+SUMIFS(I$53:I$318,$A$53:$A$318,"BD",$C$53:$C$318,$C10)/'Shared Summary by Dept_US$'!$B$33+SUMIFS(I$53:I$318,$A$53:$A$318,"Nepal",$C$53:$C$318,$C10)/'Shared Summary by Dept_US$'!$B$34+SUMIFS(I$53:I$318,$A$53:$A$318,"US",$C$53:$C$318,$C10)/'Shared Summary by Dept_US$'!$B$35 -> 2432.9023 | J10: =SUMIFS(J$53:J$318,$A$53:$A$318,"India",$C$53:$C$318,$C10)/'Shared Summary by Dept_US$'!$B$31+SUMIFS(J$53:J$318,$A$53:$A$318,"INDO",$C$53:$C$318,$C10)/'Shared Summary by Dept_US$'!$B$32+SUMIFS(J$53:J$318,$A$53:$A$318,"BD",$C$53:$C$318,$C10)/'Shared Summary by Dept_US$'!$B$33+SUMIFS(J$53:J$318,$A$53:$A$318,"Nepal",$C$53:$C$318,$C10)/'Shared Summary by Dept_US$'!$B$34+SUMIFS(J$53:J$318,$A$53:$A$318,"US",$C$53:$C$318,$C10)/'Shared Summary by Dept_US$'!$B$35 -> 2699.569 | K10: =SUMIFS(K$53:K$318,$A$53:$A$318,"India",$C$53:$C$318,$C10)/'Shared Summary by Dept_US$'!$B$31+SUMIFS(K$53:K$318,$A$53:$A$318,"INDO",$C$53:$C$318,$C10)/'Shared Summary by Dept_US$'!$B$32+SUMIFS(K$53:K$318,$A$53:$A$318,"BD",$C$53:$C$318,$C10)/'Shared Summary by Dept_US$'!$B$33+SUMIFS(K$53:K$318,$A$53:$A$318,"Nepal",$C$53:$C$318,$C10)/'Shared Summary by Dept_US$'!$B$34+SUMIFS(K$53:K$318,$A$53:$A$318,"US",$C$53:$C$318,$C10)/'Shared Summary by Dept_US$'!$B$35 -> 1425 | L10: =SUMIFS(L$53:L$318,$A$53:$A$318,"India",$C$53:$C$318,$C10)/'Shared Summary by Dept_US$'!$B$31+SUMIFS(L$53:L$318,$A$53:$A$318,"INDO",$C$53:$C$318,$C10)/'Shared Summary by Dept_US$'!$B$32+SUMIFS(L$53:L$318,$A$53:$A$318,"BD",$C$53:$C$318,$C10)/'Shared Summary by Dept_US$'!$B$33+SUMIFS(L$53:L$318,$A$53:$A$318,"Nepal",$C$53:$C$318,$C10)/'Shared Summary by Dept_US$'!$B$34+SUMIFS(L$53:L$318,$A$53:$A$318,"US",$C$53:$C$318,$C10)/'Shared Summary by Dept_US$'!$B$35 -> 1580.6753 | M10: =SUMIFS(M$53:M$318,$A$53:$A$318,"India",$C$53:$C$318,$C10)/'Shared Summary by Dept_US$'!$B$31+SUMIFS(M$53:M$318,$A$53:$A$318,"INDO",$C$53:$C$318,$C10)/'Shared Summary by Dept_US$'!$B$32+SUMIFS(M$53:M$318,$A$53:$A$318,"BD",$C$53:$C$318,$C10)/'Shared Summary by Dept_US$'!$B$33+SUMIFS(M$53:M$318,$A$53:$A$318,"Nepal",$C$53:$C$318,$C10)/'Shared Summary by Dept_US$'!$B$34+SUMIFS(M$53:M$318,$A$53:$A$318,"US",$C$53:$C$318,$C10)/'Shared Summary by Dept_US$'!$B$35 -> 1033.7644 | ... Q10: =SUMIFS(Q$53:Q$318,$A$53:$A$318,"India",$C$53:$C$318,$C10)/'Shared Summary by Dept_US$'!$B$31+SUMIFS(Q$53:Q$318,$A$53:$A$318,"INDO",$C$53:$C$318,$C10)/'Shared Summary by Dept_US$'!$B$32+SUMIFS(Q$53:Q$318,$A$53:$A$318,"BD",$C$53:$C$318,$C10)/'Shared Summary by Dept_US$'!$B$33+SUMIFS(Q$53:Q$318,$A$53:$A$318,"Nepal",$C$53:$C$318,$C10)/'Shared Summary by Dept_US$'!$B$34+SUMIFS(Q$53:Q$318,$A$53:$A$318,"US",$C$53:$C$318,$C10)/'Shared Summary by Dept_US$'!$B$35 -> 487.5
A11: Digital product | B11: Travel & Lodging Expenses | C11: Food Expenses | D11: 93102 | E11: =SUM(F11:Q11) -> 8600.7328 | F11: =SUMIFS(F$53:F$318,$A$53:$A$318,"India",$C$53:$C$318,$C11)/'Shared Summary by Dept_US$'!$B$31+SUMIFS(F$53:F$318,$A$53:$A$318,"INDO",$C$53:$C$318,$C11)/'Shared Summary by Dept_US$'!$B$32+SUMIFS(F$53:F$318,$A$53:$A$318,"BD",$C$53:$C$318,$C11)/'Shared Summary by Dept_US$'!$B$33+SUMIFS(F$53:F$318,$A$53:$A$318,"Nepal",$C$53:$C$318,$C11)/'Shared Summary by Dept_US$'!$B$34+SUMIFS(F$53:F$318,$A$53:$A$318,"US",$C$53:$C$318,$C11)/'Shared Summary by Dept_US$'!$B$35 -> 267.5 | G11: =SUMIFS(G$53:G$318,$A$53:$A$318,"India",$C$53:$C$318,$C11)/'Shared Summary by Dept_US$'!$B$31+SUMIFS(G$53:G$318,$A$53:$A$318,"INDO",$C$53:$C$318,$C11)/'Shared Summary by Dept_US$'!$B$32+SUMIFS(G$53:G$318,$A$53:$A$318,"BD",$C$53:$C$318,$C11)/'Shared Summary by Dept_US$'!$B$33+SUMIFS(G$53:G$318,$A$53:$A$318,"Nepal",$C$53:$C$318,$C11)/'Shared Summary by Dept_US$'!$B$34+SUMIFS(G$53:G$318,$A$53:$A$318,"US",$C$53:$C$318,$C11)/'Shared Summary by Dept_US$'!$B$35 -> 374.69828 | H11: =SUMIFS(H$53:H$318,$A$53:$A$318,"India",$C$53:$C$318,$C11)/'Shared Summary by Dept_US$'!$B$31+SUMIFS(H$53:H$318,$A$53:$A$318,"INDO",$C$53:$C$318,$C11)/'Shared Summary by Dept_US$'!$B$32+SUMIFS(H$53:H$318,$A$53:$A$318,"BD",$C$53:$C$318,$C11)/'Shared Summary by Dept_US$'!$B$33+SUMIFS(H$53:H$318,$A$53:$A$318,"Nepal",$C$53:$C$318,$C11)/'Shared Summary by Dept_US$'!$B$34+SUMIFS(H$53:H$318,$A$53:$A$318,"US",$C$53:$C$318,$C11)/'Shared Summary by Dept_US$'!$B$35 -> 2502.0402 | I11: =SUMIFS(I$53:I$318,$A$53:$A$318,"India",$C$53:$C$318,$C11)/'Shared Summary by Dept_US$'!$B$31+SUMIFS(I$53:I$318,$A$53:$A$318,"INDO",$C$53:$C$318,$C11)/'Shared Summary by Dept_US$'!$B$32+SUMIFS(I$53:I$318,$A$53:$A$318,"BD",$C$53:$C$318,$C11)/'Shared Summary by Dept_US$'!$B$33+SUMIFS(I$53:I$318,$A$53:$A$318,"Nepal",$C$53:$C$318,$C11)/'Shared Summary by Dept_US$'!$B$34+SUMIFS(I$53:I$318,$A$53:$A$318,"US",$C$53:$C$318,$C11)/'Shared Summary by Dept_US$'!$B$35 -> 850.91954 | J11: =SUMIFS(J$53:J$318,$A$53:$A$318,"India",$C$53:$C$318,$C11)/'Shared Summary by Dept_US$'!$B$31+SUMIFS(J$53:J$318,$A$53:$A$318,"INDO",$C$53:$C$318,$C11)/'Shared Summary by Dept_US$'!$B$32+SUMIFS(J$53:J$318,$A$53:$A$318,"BD",$C$53:$C$318,$C11)/'Shared Summary by Dept_US$'!$B$33+SUMIFS(J$53:J$318,$A$53:$A$318,"Nepal",$C$53:$C$318,$C11)/'Shared Summary by Dept_US$'!$B$34+SUMIFS(J$53:J$318,$A$53:$A$318,"US",$C$53:$C$318,$C11)/'Shared Summary by Dept_US$'!$B$35 -> 1057.0977 | K11: =SUMIFS(K$53:K$318,$A$53:$A$318,"India",$C$53:$C$318,$C11)/'Shared Summary by Dept_US$'!$B$31+SUMIFS(K$53:K$318,$A$53:$A$318,"INDO",$C$53:$C$318,$C11)/'Shared Summary by Dept_US$'!$B$32+SUMIFS(K$53:K$318,$A$53:$A$318,"BD",$C$53:$C$318,$C11)/'Shared Summary by Dept_US$'!$B$33+SUMIFS(K$53:K$318,$A$53:$A$318,"Nepal",$C$53:$C$318,$C11)/'Shared Summary by Dept_US$'!$B$34+SUMIFS(K$53:K$318,$A$53:$A$318,"US",$C$53:$C$318,$C11)/'Shared Summary by Dept_US$'!$B$35 -> 566.83908 | L11: =SUMIFS(L$53:L$318,$A$53:$A$318,"India",$C$53:$C$318,$C11)/'Shared Summary by Dept_US$'!$B$31+SUMIFS(L$53:L$318,$A$53:$A$318,"INDO",$C$53:$C$318,$C11)/'Shared Summary by Dept_US$'!$B$32+SUMIFS(L$53:L$318,$A$53:$A$318,"BD",$C$53:$C$318,$C11)/'Shared Summary by Dept_US$'!$B$33+SUMIFS(L$53:L$318,$A$53:$A$318,"Nepal",$C$53:$C$318,$C11)/'Shared Summary by Dept_US$'!$B$34+SUMIFS(L$53:L$318,$A$53:$A$318,"US",$C$53:$C$318,$C11)/'Shared Summary by Dept_US$'!$B$35 -> 995.43103 | M11: =SUMIFS(M$53:M$318,$A$53:$A$318,"India",$C$53:$C$318,$C11)/'Shared Summary by Dept_US$'!$B$31+SUMIFS(M$53:M$318,$A$53:$A$318,"INDO",$C$53:$C$318,$C11)/'Shared Summary by Dept_US$'!$B$32+SUMIFS(M$53:M$318,$A$53:$A$318,"BD",$C$53:$C$318,$C11)/'Shared Summary by Dept_US$'!$B$33+SUMIFS(M$53:M$318,$A$53:$A$318,"Nepal",$C$53:$C$318,$C11)/'Shared Summary by Dept_US$'!$B$34+SUMIFS(M$53:M$318,$A$53:$A$318,"US",$C$53:$C$318,$C11)/'Shared Summary by Dept_US$'!$B$35 -> 441.89655 | ... Q11: =SUMIFS(Q$53:Q$318,$A$53:$A$318,"India",$C$53:$C$318,$C11)/'Shared Summary by Dept_US$'!$B$31+SUMIFS(Q$53:Q$318,$A$53:$A$318,"INDO",$C$53:$C$318,$C11)/'Shared Summary by Dept_US$'!$B$32+SUMIFS(Q$53:Q$318,$A$53:$A$318,"BD",$C$53:$C$318,$C11)/'Shared Summary by Dept_US$'!$B$33+SUMIFS(Q$53:Q$318,$A$53:$A$318,"Nepal",$C$53:$C$318,$C11)/'Shared Summary by Dept_US$'!$B$34+SUMIFS(Q$53:Q$318,$A$53:$A$318,"US",$C$53:$C$318,$C11)/'Shared Summary by Dept_US$'!$B$35 -> 225
A12: Digital product | B12: Travel & Lodging Expenses | C12: Air fare | D12: 93103 | E12: =SUM(F12:Q12) -> 22907.007 | F12: =SUMIFS(F$53:F$318,$A$53:$A$318,"India",$C$53:$C$318,$C12)/'Shared Summary by Dept_US$'!$B$31+SUMIFS(F$53:F$318,$A$53:$A$318,"INDO",$C$53:$C$318,$C12)/'Shared Summary by Dept_US$'!$B$32+SUMIFS(F$53:F$318,$A$53:$A$318,"BD",$C$53:$C$318,$C12)/'Shared Summary by Dept_US$'!$B$33+SUMIFS(F$53:F$318,$A$53:$A$318,"Nepal",$C$53:$C$318,$C12)/'Shared Summary by Dept_US$'!$B$34+SUMIFS(F$53:F$318,$A$53:$A$318,"US",$C$53:$C$318,$C12)/'Shared Summary by Dept_US$'!$B$35 -> 433.41787 | G12: =SUMIFS(G$53:G$318,$A$53:$A$318,"India",$C$53:$C$318,$C12)/'Shared Summary by Dept_US$'!$B$31+SUMIFS(G$53:G$318,$A$53:$A$318,"INDO",$C$53:$C$318,$C12)/'Shared Summary by Dept_US$'!$B$32+SUMIFS(G$53:G$318,$A$53:$A$318,"BD",$C$53:$C$318,$C12)/'Shared Summary by Dept_US$'!$B$33+SUMIFS(G$53:G$318,$A$53:$A$318,"Nepal",$C$53:$C$318,$C12)/'Shared Summary by Dept_US$'!$B$34+SUMIFS(G$53:G$318,$A$53:$A$318,"US",$C$53:$C$318,$C12)/'Shared Summary by Dept_US$'!$B$35 -> 1122.211 | H12: =SUMIFS(H$53:H$318,$A$53:$A$318,"India",$C$53:$C$318,$C12)/'Shared Summary by Dept_US$'!$B$31+SUMIFS(H$53:H$318,$A$53:$A$318,"INDO",$C$53:$C$318,$C12)/'Shared Summary by Dept_US$'!$B$32+SUMIFS(H$53:H$318,$A$53:$A$318,"BD",$C$53:$C$318,$C12)/'Shared Summary by Dept_US$'!$B$33+SUMIFS(H$53:H$318,$A$53:$A$318,"Nepal",$C$53:$C$318,$C12)/'Shared Summary by Dept_US$'!$B$34+SUMIFS(H$53:H$318,$A$53:$A$318,"US",$C$53:$C$318,$C12)/'Shared Summary by Dept_US$'!$B$35 -> 2320.977 | I12: =SUMIFS(I$53:I$318,$A$53:$A$318,"India",$C$53:$C$318,$C12)/'Shared Summary by Dept_US$'!$B$31+SUMIFS(I$53:I$318,$A$53:$A$318,"INDO",$C$53:$C$318,$C12)/'Shared Summary by Dept_US$'!$B$32+SUMIFS(I$53:I$318,$A$53:$A$318,"BD",$C$53:$C$318,$C12)/'Shared Summary by Dept_US$'!$B$33+SUMIFS(I$53:I$318,$A$53:$A$318,"Nepal",$C$53:$C$318,$C12)/'Shared Summary by Dept_US$'!$B$34+SUMIFS(I$53:I$318,$A$53:$A$318,"US",$C$53:$C$318,$C12)/'Shared Summary by Dept_US$'!$B$35 -> 4550.5747 | J12: =SUMIFS(J$53:J$318,$A$53:$A$318,"India",$C$53:$C$318,$C12)/'Shared Summary by Dept_US$'!$B$31+SUMIFS(J$53:J$318,$A$53:$A$318,"INDO",$C$53:$C$318,$C12)/'Shared Summary by Dept_US$'!$B$32+SUMIFS(J$53:J$318,$A$53:$A$318,"BD",$C$53:$C$318,$C12)/'Shared Summary by Dept_US$'!$B$33+SUMIFS(J$53:J$318,$A$53:$A$318,"Nepal",$C$53:$C$318,$C12)/'Shared Summary by Dept_US$'!$B$34+SUMIFS(J$53:J$318,$A$53:$A$318,"US",$C$53:$C$318,$C12)/'Shared Summary by Dept_US$'!$B$35 -> 3939.9848 | K12: =SUMIFS(K$53:K$318,$A$53:$A$318,"India",$C$53:$C$318,$C12)/'Shared Summary by Dept_US$'!$B$31+SUMIFS(K$53:K$318,$A$53:$A$318,"INDO",$C$53:$C$318,$C12)/'Shared Summary by Dept_US$'!$B$32+SUMIFS(K$53:K$318,$A$53:$A$318,"BD",$C$53:$C$318,$C12)/'Shared Summary by Dept_US$'!$B$33+SUMIFS(K$53:K$318,$A$53:$A$318,"Nepal",$C$53:$C$318,$C12)/'Shared Summary by Dept_US$'!$B$34+SUMIFS(K$53:K$318,$A$53:$A$318,"US",$C$53:$C$318,$C12)/'Shared Summary by Dept_US$'!$B$35 -> 2330.7894 | L12: =SUMIFS(L$53:L$318,$A$53:$A$318,"India",$C$53:$C$318,$C12)/'Shared Summary by Dept_US$'!$B$31+SUMIFS(L$53:L$318,$A$53:$A$318,"INDO",$C$53:$C$318,$C12)/'Shared Summary by Dept_US$'!$B$32+SUMIFS(L$53:L$318,$A$53:$A$318,"BD",$C$53:$C$318,$C12)/'Shared Summary by Dept_US$'!$B$33+SUMIFS(L$53:L$318,$A$53:$A$318,"Nepal",$C$53:$C$318,$C12)/'Shared Summary by Dept_US$'!$B$34+SUMIFS(L$53:L$318,$A$53:$A$318,"US",$C$53:$C$318,$C12)/'Shared Summary by Dept_US$'!$B$35 -> 1122.211 | M12: =SUMIFS(M$53:M$318,$A$53:$A$318,"India",$C$53:$C$318,$C12)/'Shared Summary by Dept_US$'!$B$31+SUMIFS(M$53:M$318,$A$53:$A$318,"INDO",$C$53:$C$318,$C12)/'Shared Summary by Dept_US$'!$B$32+SUMIFS(M$53:M$318,$A$53:$A$318,"BD",$C$53:$C$318,$C12)/'Shared Summary by Dept_US$'!$B$33+SUMIFS(M$53:M$318,$A$53:$A$318,"Nepal",$C$53:$C$318,$C12)/'Shared Summary by Dept_US$'!$B$34+SUMIFS(M$53:M$318,$A$53:$A$318,"US",$C$53:$C$318,$C12)/'Shared Summary by Dept_US$'!$B$35 -> 1617.8584 | ... Q12: =SUMIFS(Q$53:Q$318,$A$53:$A$318,"India",$C$53:$C$318,$C12)/'Shared Summary by Dept_US$'!$B$31+SUMIFS(Q$53:Q$318,$A$53:$A$318,"INDO",$C$53:$C$318,$C12)/'Shared Summary by Dept_US$'!$B$32+SUMIFS(Q$53:Q$318,$A$53:$A$318,"BD",$C$53:$C$318,$C12)/'Shared Summary by Dept_US$'!$B$33+SUMIFS(Q$53:Q$318,$A$53:$A$318,"Nepal",$C$53:$C$318,$C12)/'Shared Summary by Dept_US$'!$B$34+SUMIFS(Q$53:Q$318,$A$53:$A$318,"US",$C$53:$C$318,$C12)/'Shared Summary by Dept_US$'!$B$35 -> 866.83575
A13: Digital product | B13: Travel & Lodging Expenses | C13: Cab/Auto | D13: 93104 | E13: =SUM(F13:Q13) -> 13490.036 | F13: =SUMIFS(F$53:F$318,$A$53:$A$318,"India",$C$53:$C$318,$C13)/'Shared Summary by Dept_US$'!$B$31+SUMIFS(F$53:F$318,$A$53:$A$318,"INDO",$C$53:$C$318,$C13)/'Shared Summary by Dept_US$'!$B$32+SUMIFS(F$53:F$318,$A$53:$A$318,"BD",$C$53:$C$318,$C13)/'Shared Summary by Dept_US$'!$B$33+SUMIFS(F$53:F$318,$A$53:$A$318,"Nepal",$C$53:$C$318,$C13)/'Shared Summary by Dept_US$'!$B$34+SUMIFS(F$53:F$318,$A$53:$A$318,"US",$C$53:$C$318,$C13)/'Shared Summary by Dept_US$'!$B$35 -> 281.25 | G13: =SUMIFS(G$53:G$318,$A$53:$A$318,"India",$C$53:$C$318,$C13)/'Shared Summary by Dept_US$'!$B$31+SUMIFS(G$53:G$318,$A$53:$A$318,"INDO",$C$53:$C$318,$C13)/'Shared Summary by Dept_US$'!$B$32+SUMIFS(G$53:G$318,$A$53:$A$318,"BD",$C$53:$C$318,$C13)/'Shared Summary by Dept_US$'!$B$33+SUMIFS(G$53:G$318,$A$53:$A$318,"Nepal",$C$53:$C$318,$C13)/'Shared Summary by Dept_US$'!$B$34+SUMIFS(G$53:G$318,$A$53:$A$318,"US",$C$53:$C$318,$C13)/'Shared Summary by Dept_US$'!$B$35 -> 784.86351 | H13: =SUMIFS(H$53:H$318,$A$53:$A$318,"India",$C$53:$C$318,$C13)/'Shared Summary by Dept_US$'!$B$31+SUMIFS(H$53:H$318,$A$53:$A$318,"INDO",$C$53:$C$318,$C13)/'Shared Summary by Dept_US$'!$B$32+SUMIFS(H$53:H$318,$A$53:$A$318,"BD",$C$53:$C$318,$C13)/'Shared Summary by Dept_US$'!$B$33+SUMIFS(H$53:H$318,$A$53:$A$318,"Nepal",$C$53:$C$318,$C13)/'Shared Summary by Dept_US$'!$B$34+SUMIFS(H$53:H$318,$A$53:$A$318,"US",$C$53:$C$318,$C13)/'Shared Summary by Dept_US$'!$B$35 -> 2549.296 | I13: =SUMIFS(I$53:I$318,$A$53:$A$318,"India",$C$53:$C$318,$C13)/'Shared Summary by Dept_US$'!$B$31+SUMIFS(I$53:I$318,$A$53:$A$318,"INDO",$C$53:$C$318,$C13)/'Shared Summary by Dept_US$'!$B$32+SUMIFS(I$53:I$318,$A$53:$A$318,"BD",$C$53:$C$318,$C13)/'Shared Summary by Dept_US$'!$B$33+SUMIFS(I$53:I$318,$A$53:$A$318,"Nepal",$C$53:$C$318,$C13)/'Shared Summary by Dept_US$'!$B$34+SUMIFS(I$53:I$318,$A$53:$A$318,"US",$C$53:$C$318,$C13)/'Shared Summary by Dept_US$'!$B$35 -> 2169.1667 | J13: =SUMIFS(J$53:J$318,$A$53:$A$318,"India",$C$53:$C$318,$C13)/'Shared Summary by Dept_US$'!$B$31+SUMIFS(J$53:J$318,$A$53:$A$318,"INDO",$C$53:$C$318,$C13)/'Shared Summary by Dept_US$'!$B$32+SUMIFS(J$53:J$318,$A$53:$A$318,"BD",$C$53:$C$318,$C13)/'Shared Summary by Dept_US$'!$B$33+SUMIFS(J$53:J$318,$A$53:$A$318,"Nepal",$C$53:$C$318,$C13)/'Shared Summary by Dept_US$'!$B$34+SUMIFS(J$53:J$318,$A$53:$A$318,"US",$C$53:$C$318,$C13)/'Shared Summary by Dept_US$'!$B$35 -> 1600.4167 | K13: =SUMIFS(K$53:K$318,$A$53:$A$318,"India",$C$53:$C$318,$C13)/'Shared Summary by Dept_US$'!$B$31+SUMIFS(K$53:K$318,$A$53:$A$318,"INDO",$C$53:$C$318,$C13)/'Shared Summary by Dept_US$'!$B$32+SUMIFS(K$53:K$318,$A$53:$A$318,"BD",$C$53:$C$318,$C13)/'Shared Summary by Dept_US$'!$B$33+SUMIFS(K$53:K$318,$A$53:$A$318,"Nepal",$C$53:$C$318,$C13)/'Shared Summary by Dept_US$'!$B$34+SUMIFS(K$53:K$318,$A$53:$A$318,"US",$C$53:$C$318,$C13)/'Shared Summary by Dept_US$'!$B$35 -> 1169.1954 | L13: =SUMIFS(L$53:L$318,$A$53:$A$318,"India",$C$53:$C$318,$C13)/'Shared Summary by Dept_US$'!$B$31+SUMIFS(L$53:L$318,$A$53:$A$318,"INDO",$C$53:$C$318,$C13)/'Shared Summary by Dept_US$'!$B$32+SUMIFS(L$53:L$318,$A$53:$A$318,"BD",$C$53:$C$318,$C13)/'Shared Summary by Dept_US$'!$B$33+SUMIFS(L$53:L$318,$A$53:$A$318,"Nepal",$C$53:$C$318,$C13)/'Shared Summary by Dept_US$'!$B$34+SUMIFS(L$53:L$318,$A$53:$A$318,"US",$C$53:$C$318,$C13)/'Shared Summary by Dept_US$'!$B$35 -> 1052.4569 | M13: =SUMIFS(M$53:M$318,$A$53:$A$318,"India",$C$53:$C$318,$C13)/'Shared Summary by Dept_US$'!$B$31+SUMIFS(M$53:M$318,$A$53:$A$318,"INDO",$C$53:$C$318,$C13)/'Shared Summary by Dept_US$'!$B$32+SUMIFS(M$53:M$318,$A$53:$A$318,"BD",$C$53:$C$318,$C13)/'Shared Summary by Dept_US$'!$B$33+SUMIFS(M$53:M$318,$A$53:$A$318,"Nepal",$C$53:$C$318,$C13)/'Shared Summary by Dept_US$'!$B$34+SUMIFS(M$53:M$318,$A$53:$A$318,"US",$C$53:$C$318,$C13)/'Shared Summary by Dept_US$'!$B$35 -> 921.00575 | ... Q13: =SUMIFS(Q$53:Q$318,$A$53:$A$318,"India",$C$53:$C$318,$C13)/'Shared Summary by Dept_US$'!$B$31+SUMIFS(Q$53:Q$318,$A$53:$A$318,"INDO",$C$53:$C$318,$C13)/'Shared Summary by Dept_US$'!$B$32+SUMIFS(Q$53:Q$318,$A$53:$A$318,"BD",$C$53:$C$318,$C13)/'Shared Summary by Dept_US$'!$B$33+SUMIFS(Q$53:Q$318,$A$53:$A$318,"Nepal",$C$53:$C$318,$C13)/'Shared Summary by Dept_US$'!$B$34+SUMIFS(Q$53:Q$318,$A$53:$A$318,"US",$C$53:$C$318,$C13)/'Shared Summary by Dept_US$'!$B$35 -> 337.5
A14: Digital product | B14: Travel & Lodging Expenses | C14: Bus/Train | D14: 93105 | E14: =SUM(F14:Q14) -> 842.75862 | F14: =SUMIFS(F$53:F$318,$A$53:$A$318,"India",$C$53:$C$318,$C14)/'Shared Summary by Dept_US$'!$B$31+SUMIFS(F$53:F$318,$A$53:$A$318,"INDO",$C$53:$C$318,$C14)/'Shared Summary by Dept_US$'!$B$32+SUMIFS(F$53:F$318,$A$53:$A$318,"BD",$C$53:$C$318,$C14)/'Shared Summary by Dept_US$'!$B$33+SUMIFS(F$53:F$318,$A$53:$A$318,"Nepal",$C$53:$C$318,$C14)/'Shared Summary by Dept_US$'!$B$34+SUMIFS(F$53:F$318,$A$53:$A$318,"US",$C$53:$C$318,$C14)/'Shared Summary by Dept_US$'!$B$35 -> 0 | G14: =SUMIFS(G$53:G$318,$A$53:$A$318,"India",$C$53:$C$318,$C14)/'Shared Summary by Dept_US$'!$B$31+SUMIFS(G$53:G$318,$A$53:$A$318,"INDO",$C$53:$C$318,$C14)/'Shared Summary by Dept_US$'!$B$32+SUMIFS(G$53:G$318,$A$53:$A$318,"BD",$C$53:$C$318,$C14)/'Shared Summary by Dept_US$'!$B$33+SUMIFS(G$53:G$318,$A$53:$A$318,"Nepal",$C$53:$C$318,$C14)/'Shared Summary by Dept_US$'!$B$34+SUMIFS(G$53:G$318,$A$53:$A$318,"US",$C$53:$C$318,$C14)/'Shared Summary by Dept_US$'!$B$35 -> 54.482759 | H14: =SUMIFS(H$53:H$318,$A$53:$A$318,"India",$C$53:$C$318,$C14)/'Shared Summary by Dept_US$'!$B$31+SUMIFS(H$53:H$318,$A$53:$A$318,"INDO",$C$53:$C$318,$C14)/'Shared Summary by Dept_US$'!$B$32+SUMIFS(H$53:H$318,$A$53:$A$318,"BD",$C$53:$C$318,$C14)/'Shared Summary by Dept_US$'!$B$33+SUMIFS(H$53:H$318,$A$53:$A$318,"Nepal",$C$53:$C$318,$C14)/'Shared Summary by Dept_US$'!$B$34+SUMIFS(H$53:H$318,$A$53:$A$318,"US",$C$53:$C$318,$C14)/'Shared Summary by Dept_US$'!$B$35 -> 106.2069 | I14: =SUMIFS(I$53:I$318,$A$53:$A$318,"India",$C$53:$C$318,$C14)/'Shared Summary by Dept_US$'!$B$31+SUMIFS(I$53:I$318,$A$53:$A$318,"INDO",$C$53:$C$318,$C14)/'Shared Summary by Dept_US$'!$B$32+SUMIFS(I$53:I$318,$A$53:$A$318,"BD",$C$53:$C$318,$C14)/'Shared Summary by Dept_US$'!$B$33+SUMIFS(I$53:I$318,$A$53:$A$318,"Nepal",$C$53:$C$318,$C14)/'Shared Summary by Dept_US$'!$B$34+SUMIFS(I$53:I$318,$A$53:$A$318,"US",$C$53:$C$318,$C14)/'Shared Summary by Dept_US$'!$B$35 -> 78.390805 | J14: =SUMIFS(J$53:J$318,$A$53:$A$318,"India",$C$53:$C$318,$C14)/'Shared Summary by Dept_US$'!$B$31+SUMIFS(J$53:J$318,$A$53:$A$318,"INDO",$C$53:$C$318,$C14)/'Shared Summary by Dept_US$'!$B$32+SUMIFS(J$53:J$318,$A$53:$A$318,"BD",$C$53:$C$318,$C14)/'Shared Summary by Dept_US$'!$B$33+SUMIFS(J$53:J$318,$A$53:$A$318,"Nepal",$C$53:$C$318,$C14)/'Shared Summary by Dept_US$'!$B$34+SUMIFS(J$53:J$318,$A$53:$A$318,"US",$C$53:$C$318,$C14)/'Shared Summary by Dept_US$'!$B$35 -> 71.724138 | K14: =SUMIFS(K$53:K$318,$A$53:$A$318,"India",$C$53:$C$318,$C14)/'Shared Summary by Dept_US$'!$B$31+SUMIFS(K$53:K$318,$A$53:$A$318,"INDO",$C$53:$C$318,$C14)/'Shared Summary by Dept_US$'!$B$32+SUMIFS(K$53:K$318,$A$53:$A$318,"BD",$C$53:$C$318,$C14)/'Shared Summary by Dept_US$'!$B$33+SUMIFS(K$53:K$318,$A$53:$A$318,"Nepal",$C$53:$C$318,$C14)/'Shared Summary by Dept_US$'!$B$34+SUMIFS(K$53:K$318,$A$53:$A$318,"US",$C$53:$C$318,$C14)/'Shared Summary by Dept_US$'!$B$35 -> 88.965517 | L14: =SUMIFS(L$53:L$318,$A$53:$A$318,"India",$C$53:$C$318,$C14)/'Shared Summary by Dept_US$'!$B$31+SUMIFS(L$53:L$318,$A$53:$A$318,"INDO",$C$53:$C$318,$C14)/'Shared Summary by Dept_US$'!$B$32+SUMIFS(L$53:L$318,$A$53:$A$318,"BD",$C$53:$C$318,$C14)/'Shared Summary by Dept_US$'!$B$33+SUMIFS(L$53:L$318,$A$53:$A$318,"Nepal",$C$53:$C$318,$C14)/'Shared Summary by Dept_US$'!$B$34+SUMIFS(L$53:L$318,$A$53:$A$318,"US",$C$53:$C$318,$C14)/'Shared Summary by Dept_US$'!$B$35 -> 221.14943 | M14: =SUMIFS(M$53:M$318,$A$53:$A$318,"India",$C$53:$C$318,$C14)/'Shared Summary by Dept_US$'!$B$31+SUMIFS(M$53:M$318,$A$53:$A$318,"INDO",$C$53:$C$318,$C14)/'Shared Summary by Dept_US$'!$B$32+SUMIFS(M$53:M$318,$A$53:$A$318,"BD",$C$53:$C$318,$C14)/'Shared Summary by Dept_US$'!$B$33+SUMIFS(M$53:M$318,$A$53:$A$318,"Nepal",$C$53:$C$318,$C14)/'Shared Summary by Dept_US$'!$B$34+SUMIFS(M$53:M$318,$A$53:$A$318,"US",$C$53:$C$318,$C14)/'Shared Summary by Dept_US$'!$B$35 -> 78.390805 | ... Q14: =SUMIFS(Q$53:Q$318,$A$53:$A$318,"India",$C$53:$C$318,$C14)/'Shared Summary by Dept_US$'!$B$31+SUMIFS(Q$53:Q$318,$A$53:$A$318,"INDO",$C$53:$C$318,$C14)/'Shared Summary by Dept_US$'!$B$32+SUMIFS(Q$53:Q$318,$A$53:$A$318,"BD",$C$53:$C$318,$C14)/'Shared Summary by Dept_US$'!$B$33+SUMIFS(Q$53:Q$318,$A$53:$A$318,"Nepal",$C$53:$C$318,$C14)/'Shared Summary by Dept_US$'!$B$34+SUMIFS(Q$53:Q$318,$A$53:$A$318,"US",$C$53:$C$318,$C14)/'Shared Summary by Dept_US$'!$B$35 -> 0
A15: Digital product | B15: Travel & Lodging Expenses | C15: Other incidental travel costs | D15: 93106 | E15: =SUM(F15:Q15) -> 3859.5036 | F15: =SUMIFS(F$53:F$318,$A$53:$A$318,"India",$C$53:$C$318,$C15)/'Shared Summary by Dept_US$'!$B$31+SUMIFS(F$53:F$318,$A$53:$A$318,"INDO",$C$53:$C$318,$C15)/'Shared Summary by Dept_US$'!$B$32+SUMIFS(F$53:F$318,$A$53:$A$318,"BD",$C$53:$C$318,$C15)/'Shared Summary by Dept_US$'!$B$33+SUMIFS(F$53:F$318,$A$53:$A$318,"Nepal",$C$53:$C$318,$C15)/'Shared Summary by Dept_US$'!$B$34+SUMIFS(F$53:F$318,$A$53:$A$318,"US",$C$53:$C$318,$C15)/'Shared Summary by Dept_US$'!$B$35 -> 12.5 | G15: =SUMIFS(G$53:G$318,$A$53:$A$318,"India",$C$53:$C$318,$C15)/'Shared Summary by Dept_US$'!$B$31+SUMIFS(G$53:G$318,$A$53:$A$318,"INDO",$C$53:$C$318,$C15)/'Shared Summary by Dept_US$'!$B$32+SUMIFS(G$53:G$318,$A$53:$A$318,"BD",$C$53:$C$318,$C15)/'Shared Summary by Dept_US$'!$B$33+SUMIFS(G$53:G$318,$A$53:$A$318,"Nepal",$C$53:$C$318,$C15)/'Shared Summary by Dept_US$'!$B$34+SUMIFS(G$53:G$318,$A$53:$A$318,"US",$C$53:$C$318,$C15)/'Shared Summary by Dept_US$'!$B$35 -> 22.341954 | H15: =SUMIFS(H$53:H$318,$A$53:$A$318,"India",$C$53:$C$318,$C15)/'Shared Summary by Dept_US$'!$B$31+SUMIFS(H$53:H$318,$A$53:$A$318,"INDO",$C$53:$C$318,$C15)/'Shared Summary by Dept_US$'!$B$32+SUMIFS(H$53:H$318,$A$53:$A$318,"BD",$C$53:$C$318,$C15)/'Shared Summary by Dept_US$'!$B$33+SUMIFS(H$53:H$318,$A$53:$A$318,"Nepal",$C$53:$C$318,$C15)/'Shared Summary by Dept_US$'!$B$34+SUMIFS(H$53:H$318,$A$53:$A$318,"US",$C$53:$C$318,$C15)/'Shared Summary by Dept_US$'!$B$35 -> 1474.7126 | I15: =SUMIFS(I$53:I$318,$A$53:$A$318,"India",$C$53:$C$318,$C15)/'Shared Summary by Dept_US$'!$B$31+SUMIFS(I$53:I$318,$A$53:$A$318,"INDO",$C$53:$C$318,$C15)/'Shared Summary by Dept_US$'!$B$32+SUMIFS(I$53:I$318,$A$53:$A$318,"BD",$C$53:$C$318,$C15)/'Shared Summary by Dept_US$'!$B$33+SUMIFS(I$53:I$318,$A$53:$A$318,"Nepal",$C$53:$C$318,$C15)/'Shared Summary by Dept_US$'!$B$34+SUMIFS(I$53:I$318,$A$53:$A$318,"US",$C$53:$C$318,$C15)/'Shared Summary by Dept_US$'!$B$35 -> 261.43678 | J15: =SUMIFS(J$53:J$318,$A$53:$A$318,"India",$C$53:$C$318,$C15)/'Shared Summary by Dept_US$'!$B$31+SUMIFS(J$53:J$318,$A$53:$A$318,"INDO",$C$53:$C$318,$C15)/'Shared Summary by Dept_US$'!$B$32+SUMIFS(J$53:J$318,$A$53:$A$318,"BD",$C$53:$C$318,$C15)/'Shared Summary by Dept_US$'!$B$33+SUMIFS(J$53:J$318,$A$53:$A$318,"Nepal",$C$53:$C$318,$C15)/'Shared Summary by Dept_US$'!$B$34+SUMIFS(J$53:J$318,$A$53:$A$318,"US",$C$53:$C$318,$C15)/'Shared Summary by Dept_US$'!$B$35 -> 553.05316 | K15: =SUMIFS(K$53:K$318,$A$53:$A$318,"India",$C$53:$C$318,$C15)/'Shared Summary by Dept_US$'!$B$31+SUMIFS(K$53:K$318,$A$53:$A$318,"INDO",$C$53:$C$318,$C15)/'Shared Summary by Dept_US$'!$B$32+SUMIFS(K$53:K$318,$A$53:$A$318,"BD",$C$53:$C$318,$C15)/'Shared Summary by Dept_US$'!$B$33+SUMIFS(K$53:K$318,$A$53:$A$318,"Nepal",$C$53:$C$318,$C15)/'Shared Summary by Dept_US$'!$B$34+SUMIFS(K$53:K$318,$A$53:$A$318,"US",$C$53:$C$318,$C15)/'Shared Summary by Dept_US$'!$B$35 -> 69.791667 | L15: =SUMIFS(L$53:L$318,$A$53:$A$318,"India",$C$53:$C$318,$C15)/'Shared Summary by Dept_US$'!$B$31+SUMIFS(L$53:L$318,$A$53:$A$318,"INDO",$C$53:$C$318,$C15)/'Shared Summary by Dept_US$'!$B$32+SUMIFS(L$53:L$318,$A$53:$A$318,"BD",$C$53:$C$318,$C15)/'Shared Summary by Dept_US$'!$B$33+SUMIFS(L$53:L$318,$A$53:$A$318,"Nepal",$C$53:$C$318,$C15)/'Shared Summary by Dept_US$'!$B$34+SUMIFS(L$53:L$318,$A$53:$A$318,"US",$C$53:$C$318,$C15)/'Shared Summary by Dept_US$'!$B$35 -> 28.591954 | M15: =SUMIFS(M$53:M$318,$A$53:$A$318,"India",$C$53:$C$318,$C15)/'Shared Summary by Dept_US$'!$B$31+SUMIFS(M$53:M$318,$A$53:$A$318,"INDO",$C$53:$C$318,$C15)/'Shared Summary by Dept_US$'!$B$32+SUMIFS(M$53:M$318,$A$53:$A$318,"BD",$C$53:$C$318,$C15)/'Shared Summary by Dept_US$'!$B$33+SUMIFS(M$53:M$318,$A$53:$A$318,"Nepal",$C$53:$C$318,$C15)/'Shared Summary by Dept_US$'!$B$34+SUMIFS(M$53:M$318,$A$53:$A$318,"US",$C$53:$C$318,$C15)/'Shared Summary by Dept_US$'!$B$35 -> 295.59626 | ... Q15: =SUMIFS(Q$53:Q$318,$A$53:$A$318,"India",$C$53:$C$318,$C15)/'Shared Summary by Dept_US$'!$B$31+SUMIFS(Q$53:Q$318,$A$53:$A$318,"INDO",$C$53:$C$318,$C15)/'Shared Summary by Dept_US$'!$B$32+SUMIFS(Q$53:Q$318,$A$53:$A$318,"BD",$C$53:$C$318,$C15)/'Shared Summary by Dept_US$'!$B$33+SUMIFS(Q$53:Q$318,$A$53:$A$318,"Nepal",$C$53:$C$318,$C15)/'Shared Summary by Dept_US$'!$B$34+SUMIFS(Q$53:Q$318,$A$53:$A$318,"US",$C$53:$C$318,$C15)/'Shared Summary by Dept_US$'!$B$35 -> 262.5
A16: Digital product | B16: Supplies & Printing Costs | C16: Other Direct Expenses | D16: 93201 | E16: =SUM(F16:Q16) -> 5747.1264 | F16: =SUMIFS(F$53:F$318,$A$53:$A$318,"India",$C$53:$C$318,$C16)/'Shared Summary by Dept_US$'!$B$31+SUMIFS(F$53:F$318,$A$53:$A$318,"INDO",$C$53:$C$318,$C16)/'Shared Summary by Dept_US$'!$B$32+SUMIFS(F$53:F$318,$A$53:$A$318,"BD",$C$53:$C$318,$C16)/'Shared Summary by Dept_US$'!$B$33+SUMIFS(F$53:F$318,$A$53:$A$318,"Nepal",$C$53:$C$318,$C16)/'Shared Summary by Dept_US$'!$B$34+SUMIFS(F$53:F$318,$A$53:$A$318,"US",$C$53:$C$318,$C16)/'Shared Summary by Dept_US$'!$B$35 -> 0 | G16: =SUMIFS(G$53:G$318,$A$53:$A$318,"India",$C$53:$C$318,$C16)/'Shared Summary by Dept_US$'!$B$31+SUMIFS(G$53:G$318,$A$53:$A$318,"INDO",$C$53:$C$318,$C16)/'Shared Summary by Dept_US$'!$B$32+SUMIFS(G$53:G$318,$A$53:$A$318,"BD",$C$53:$C$318,$C16)/'Shared Summary by Dept_US$'!$B$33+SUMIFS(G$53:G$318,$A$53:$A$318,"Nepal",$C$53:$C$318,$C16)/'Shared Summary by Dept_US$'!$B$34+SUMIFS(G$53:G$318,$A$53:$A$318,"US",$C$53:$C$318,$C16)/'Shared Summary by Dept_US$'!$B$35 -> 0 | H16: =SUMIFS(H$53:H$318,$A$53:$A$318,"India",$C$53:$C$318,$C16)/'Shared Summary by Dept_US$'!$B$31+SUMIFS(H$53:H$318,$A$53:$A$318,"INDO",$C$53:$C$318,$C16)/'Shared Summary by Dept_US$'!$B$32+SUMIFS(H$53:H$318,$A$53:$A$318,"BD",$C$53:$C$318,$C16)/'Shared Summary by Dept_US$'!$B$33+SUMIFS(H$53:H$318,$A$53:$A$318,"Nepal",$C$53:$C$318,$C16)/'Shared Summary by Dept_US$'!$B$34+SUMIFS(H$53:H$318,$A$53:$A$318,"US",$C$53:$C$318,$C16)/'Shared Summary by Dept_US$'!$B$35 -> 2298.8506 | I16: =SUMIFS(I$53:I$318,$A$53:$A$318,"India",$C$53:$C$318,$C16)/'Shared Summary by Dept_US$'!$B$31+SUMIFS(I$53:I$318,$A$53:$A$318,"INDO",$C$53:$C$318,$C16)/'Shared Summary by Dept_US$'!$B$32+SUMIFS(I$53:I$318,$A$53:$A$318,"BD",$C$53:$C$318,$C16)/'Shared Summary by Dept_US$'!$B$33+SUMIFS(I$53:I$318,$A$53:$A$318,"Nepal",$C$53:$C$318,$C16)/'Shared Summary by Dept_US$'!$B$34+SUMIFS(I$53:I$318,$A$53:$A$318,"US",$C$53:$C$318,$C16)/'Shared Summary by Dept_US$'!$B$35 -> 0 | J16: =SUMIFS(J$53:J$318,$A$53:$A$318,"India",$C$53:$C$318,$C16)/'Shared Summary by Dept_US$'!$B$31+SUMIFS(J$53:J$318,$A$53:$A$318,"INDO",$C$53:$C$318,$C16)/'Shared Summary by Dept_US$'!$B$32+SUMIFS(J$53:J$318,$A$53:$A$318,"BD",$C$53:$C$318,$C16)/'Shared Summary by Dept_US$'!$B$33+SUMIFS(J$53:J$318,$A$53:$A$318,"Nepal",$C$53:$C$318,$C16)/'Shared Summary by Dept_US$'!$B$34+SUMIFS(J$53:J$318,$A$53:$A$318,"US",$C$53:$C$318,$C16)/'Shared Summary by Dept_US$'!$B$35 -> 1149.4253 | K16: =SUMIFS(K$53:K$318,$A$53:$A$318,"India",$C$53:$C$318,$C16)/'Shared Summary by Dept_US$'!$B$31+SUMIFS(K$53:K$318,$A$53:$A$318,"INDO",$C$53:$C$318,$C16)/'Shared Summary by Dept_US$'!$B$32+SUMIFS(K$53:K$318,$A$53:$A$318,"BD",$C$53:$C$318,$C16)/'Shared Summary by Dept_US$'!$B$33+SUMIFS(K$53:K$318,$A$53:$A$318,"Nepal",$C$53:$C$318,$C16)/'Shared Summary by Dept_US$'!$B$34+SUMIFS(K$53:K$318,$A$53:$A$318,"US",$C$53:$C$318,$C16)/'Shared Summary by Dept_US$'!$B$35 -> 0 | L16: =SUMIFS(L$53:L$318,$A$53:$A$318,"India",$C$53:$C$318,$C16)/'Shared Summary by Dept_US$'!$B$31+SUMIFS(L$53:L$318,$A$53:$A$318,"INDO",$C$53:$C$318,$C16)/'Shared Summary by Dept_US$'!$B$32+SUMIFS(L$53:L$318,$A$53:$A$318,"BD",$C$53:$C$318,$C16)/'Shared Summary by Dept_US$'!$B$33+SUMIFS(L$53:L$318,$A$53:$A$318,"Nepal",$C$53:$C$318,$C16)/'Shared Summary by Dept_US$'!$B$34+SUMIFS(L$53:L$318,$A$53:$A$318,"US",$C$53:$C$318,$C16)/'Shared Summary by Dept_US$'!$B$35 -> 1149.4253 | M16: =SUMIFS(M$53:M$318,$A$53:$A$318,"India",$C$53:$C$318,$C16)/'Shared Summary by Dept_US$'!$B$31+SUMIFS(M$53:M$318,$A$53:$A$318,"INDO",$C$53:$C$318,$C16)/'Shared Summary by Dept_US$'!$B$32+SUMIFS(M$53:M$318,$A$53:$A$318,"BD",$C$53:$C$318,$C16)/'Shared Summary by Dept_US$'!$B$33+SUMIFS(M$53:M$318,$A$53:$A$318,"Nepal",$C$53:$C$318,$C16)/'Shared Summary by Dept_US$'!$B$34+SUMIFS(M$53:M$318,$A$53:$A$318,"US",$C$53:$C$318,$C16)/'Shared Summary by Dept_US$'!$B$35 -> 0 | ... Q16: =SUMIFS(Q$53:Q$318,$A$53:$A$318,"India",$C$53:$C$318,$C16)/'Shared Summary by Dept_US$'!$B$31+SUMIFS(Q$53:Q$318,$A$53:$A$318,"INDO",$C$53:$C$318,$C16)/'Shared Summary by Dept_US$'!$B$32+SUMIFS(Q$53:Q$318,$A$53:$A$318,"BD",$C$53:$C$318,$C16)/'Shared Summary by Dept_US$'!$B$33+SUMIFS(Q$53:Q$318,$A$53:$A$318,"Nepal",$C$53:$C$318,$C16)/'Shared Summary by Dept_US$'!$B$34+SUMIFS(Q$53:Q$318,$A$53:$A$318,"US",$C$53:$C$318,$C16)/'Shared Summary by Dept_US$'!$B$35 -> 0
... A40: Digital product | B40: Health and Retirement Benefits | C40: Staff Insurance (Employee Medical Insurance) | D40: 91207 | E40: =SUM(F40:Q40) -> 0 | F40: =SUMIFS(F$53:F$318,$A$53:$A$318,"India",$C$53:$C$318,$C40)/'Shared Summary by Dept_US$'!$B$31+SUMIFS(F$53:F$318,$A$53:$A$318,"INDO",$C$53:$C$318,$C40)/'Shared Summary by Dept_US$'!$B$32+SUMIFS(F$53:F$318,$A$53:$A$318,"BD",$C$53:$C$318,$C40)/'Shared Summary by Dept_US$'!$B$33+SUMIFS(F$53:F$318,$A$53:$A$318,"Nepal",$C$53:$C$318,$C40)/'Shared Summary by Dept_US$'!$B$34+SUMIFS(F$53:F$318,$A$53:$A$318,"US",$C$53:$C$318,$C40)/'Shared Summary by Dept_US$'!$B$35 -> 0 | G40: =SUMIFS(G$53:G$318,$A$53:$A$318,"India",$C$53:$C$318,$C40)/'Shared Summary by Dept_US$'!$B$31+SUMIFS(G$53:G$318,$A$53:$A$318,"INDO",$C$53:$C$318,$C40)/'Shared Summary by Dept_US$'!$B$32+SUMIFS(G$53:G$318,$A$53:$A$318,"BD",$C$53:$C$318,$C40)/'Shared Summary by Dept_US$'!$B$33+SUMIFS(G$53:G$318,$A$53:$A$318,"Nepal",$C$53:$C$318,$C40)/'Shared Summary by Dept_US$'!$B$34+SUMIFS(G$53:G$318,$A$53:$A$318,"US",$C$53:$C$318,$C40)/'Shared Summary by Dept_US$'!$B$35 -> 0 | H40: =SUMIFS(H$53:H$318,$A$53:$A$318,"India",$C$53:$C$318,$C40)/'Shared Summary by Dept_US$'!$B$31+SUMIFS(H$53:H$318,$A$53:$A$318,"INDO",$C$53:$C$318,$C40)/'Shared Summary by Dept_US$'!$B$32+SUMIFS(H$53:H$318,$A$53:$A$318,"BD",$C$53:$C$318,$C40)/'Shared Summary by Dept_US$'!$B$33+SUMIFS(H$53:H$318,$A$53:$A$318,"Nepal",$C$53:$C$318,$C40)/'Shared Summary by Dept_US$'!$B$34+SUMIFS(H$53:H$318,$A$53:$A$318,"US",$C$53:$C$318,$C40)/'Shared Summary by Dept_US$'!$B$35 -> 0 | I40: =SUMIFS(I$53:I$318,$A$53:$A$318,"India",$C$53:$C$318,$C40)/'Shared Summary by Dept_US$'!$B$31+SUMIFS(I$53:I$318,$A$53:$A$318,"INDO",$C$53:$C$318,$C40)/'Shared Summary by Dept_US$'!$B$32+SUMIFS(I$53:I$318,$A$53:$A$318,"BD",$C$53:$C$318,$C40)/'Shared Summary by Dept_US$'!$B$33+SUMIFS(I$53:I$318,$A$53:$A$318,"Nepal",$C$53:$C$318,$C40)/'Shared Summary by Dept_US$'!$B$34+SUMIFS(I$53:I$318,$A$53:$A$318,"US",$C$53:$C$318,$C40)/'Shared Summary by Dept_US$'!$B$35 -> 0 | J40: =SUMIFS(J$53:J$318,$A$53:$A$318,"India",$C$53:$C$318,$C40)/'Shared Summary by Dept_US$'!$B$31+SUMIFS(J$53:J$318,$A$53:$A$318,"INDO",$C$53:$C$318,$C40)/'Shared Summary by Dept_US$'!$B$32+SUMIFS(J$53:J$318,$A$53:$A$318,"BD",$C$53:$C$318,$C40)/'Shared Summary by Dept_US$'!$B$33+SUMIFS(J$53:J$318,$A$53:$A$318,"Nepal",$C$53:$C$318,$C40)/'Shared Summary by Dept_US$'!$B$34+SUMIFS(J$53:J$318,$A$53:$A$318,"US",$C$53:$C$318,$C40)/'Shared Summary by Dept_US$'!$B$35 -> 0 | K40: =SUMIFS(K$53:K$318,$A$53:$A$318,"India",$C$53:$C$318,$C40)/'Shared Summary by Dept_US$'!$B$31+SUMIFS(K$53:K$318,$A$53:$A$318,"INDO",$C$53:$C$318,$C40)/'Shared Summary by Dept_US$'!$B$32+SUMIFS(K$53:K$318,$A$53:$A$318,"BD",$C$53:$C$318,$C40)/'Shared Summary by Dept_US$'!$B$33+SUMIFS(K$53:K$318,$A$53:$A$318,"Nepal",$C$53:$C$318,$C40)/'Shared Summary by Dept_US$'!$B$34+SUMIFS(K$53:K$318,$A$53:$A$318,"US",$C$53:$C$318,$C40)/'Shared Summary by Dept_US$'!$B$35 -> 0 | L40: =SUMIFS(L$53:L$318,$A$53:$A$318,"India",$C$53:$C$318,$C40)/'Shared Summary by Dept_US$'!$B$31+SUMIFS(L$53:L$318,$A$53:$A$318,"INDO",$C$53:$C$318,$C40)/'Shared Summary by Dept_US$'!$B$32+SUMIFS(L$53:L$318,$A$53:$A$318,"BD",$C$53:$C$318,$C40)/'Shared Summary by Dept_US$'!$B$33+SUMIFS(L$53:L$318,$A$53:$A$318,"Nepal",$C$53:$C$318,$C40)/'Shared Summary by Dept_US$'!$B$34+SUMIFS(L$53:L$318,$A$53:$A$318,"US",$C$53:$C$318,$C40)/'Shared Summary by Dept_US$'!$B$35 -> 0 | M40: =SUMIFS(M$53:M$318,$A$53:$A$318,"India",$C$53:$C$318,$C40)/'Shared Summary by Dept_US$'!$B$31+SUMIFS(M$53:M$318,$A$53:$A$318,"INDO",$C$53:$C$318,$C40)/'Shared Summary by Dept_US$'!$B$32+SUMIFS(M$53:M$318,$A$53:$A$318,"BD",$C$53:$C$318,$C40)/'Shared Summary by Dept_US$'!$B$33+SUMIFS(M$53:M$318,$A$53:$A$318,"Nepal",$C$53:$C$318,$C40)/'Shared Summary by Dept_US$'!$B$34+SUMIFS(M$53:M$318,$A$53:$A$318,"US",$C$53:$C$318,$C40)/'Shared Summary by Dept_US$'!$B$35 -> 0 | ... Q40: =SUMIFS(Q$53:Q$318,$A$53:$A$318,"India",$C$53:$C$318,$C40)/'Shared Summary by Dept_US$'!$B$31+SUMIFS(Q$53:Q$318,$A$53:$A$318,"INDO",$C$53:$C$318,$C40)/'Shared Summary by Dept_US$'!$B$32+SUMIFS(Q$53:Q$318,$A$53:$A$318,"BD",$C$53:$C$318,$C40)/'Shared Summary by Dept_US$'!$B$33+SUMIFS(Q$53:Q$318,$A$53:$A$318,"Nepal",$C$53:$C$318,$C40)/'Shared Summary by Dept_US$'!$B$34+SUMIFS(Q$53:Q$318,$A$53:$A$318,"US",$C$53:$C$318,$C40)/'Shared Summary by Dept_US$'!$B$35 -> 0
A41: Digital product | B41: Office Expenses | C41: Leasehold Improvements (Ground floor) | E41: =SUM(F41:Q41) -> 0 | F41: =SUMIFS(F$53:F$318,$A$53:$A$318,"India",$C$53:$C$318,$C41)/'Shared Summary by Dept_US$'!$B$31+SUMIFS(F$53:F$318,$A$53:$A$318,"INDO",$C$53:$C$318,$C41)/'Shared Summary by Dept_US$'!$B$32+SUMIFS(F$53:F$318,$A$53:$A$318,"BD",$C$53:$C$318,$C41)/'Shared Summary by Dept_US$'!$B$33+SUMIFS(F$53:F$318,$A$53:$A$318,"Nepal",$C$53:$C$318,$C41)/'Shared Summary by Dept_US$'!$B$34+SUMIFS(F$53:F$318,$A$53:$A$318,"US",$C$53:$C$318,$C41)/'Shared Summary by Dept_US$'!$B$35 -> 0 | G41: =SUMIFS(G$53:G$318,$A$53:$A$318,"India",$C$53:$C$318,$C41)/'Shared Summary by Dept_US$'!$B$31+SUMIFS(G$53:G$318,$A$53:$A$318,"INDO",$C$53:$C$318,$C41)/'Shared Summary by Dept_US$'!$B$32+SUMIFS(G$53:G$318,$A$53:$A$318,"BD",$C$53:$C$318,$C41)/'Shared Summary by Dept_US$'!$B$33+SUMIFS(G$53:G$318,$A$53:$A$318,"Nepal",$C$53:$C$318,$C41)/'Shared Summary by Dept_US$'!$B$34+SUMIFS(G$53:G$318,$A$53:$A$318,"US",$C$53:$C$318,$C41)/'Shared Summary by Dept_US$'!$B$35 -> 0 | H41: =SUMIFS(H$53:H$318,$A$53:$A$318,"India",$C$53:$C$318,$C41)/'Shared Summary by Dept_US$'!$B$31+SUMIFS(H$53:H$318,$A$53:$A$318,"INDO",$C$53:$C$318,$C41)/'Shared Summary by Dept_US$'!$B$32+SUMIFS(H$53:H$318,$A$53:$A$318,"BD",$C$53:$C$318,$C41)/'Shared Summary by Dept_US$'!$B$33+SUMIFS(H$53:H$318,$A$53:$A$318,"Nepal",$C$53:$C$318,$C41)/'Shared Summary by Dept_US$'!$B$34+SUMIFS(H$53:H$318,$A$53:$A$318,"US",$C$53:$C$318,$C41)/'Shared Summary by Dept_US$'!$B$35 -> 0 | I41: =SUMIFS(I$53:I$318,$A$53:$A$318,"India",$C$53:$C$318,$C41)/'Shared Summary by Dept_US$'!$B$31+SUMIFS(I$53:I$318,$A$53:$A$318,"INDO",$C$53:$C$318,$C41)/'Shared Summary by Dept_US$'!$B$32+SUMIFS(I$53:I$318,$A$53:$A$318,"BD",$C$53:$C$318,$C41)/'Shared Summary by Dept_US$'!$B$33+SUMIFS(I$53:I$318,$A$53:$A$318,"Nepal",$C$53:$C$318,$C41)/'Shared Summary by Dept_US$'!$B$34+SUMIFS(I$53:I$318,$A$53:$A$318,"US",$C$53:$C$318,$C41)/'Shared Summary by Dept_US$'!$B$35 -> 0 | J41: =SUMIFS(J$53:J$318,$A$53:$A$318,"India",$C$53:$C$318,$C41)/'Shared Summary by Dept_US$'!$B$31+SUMIFS(J$53:J$318,$A$53:$A$318,"INDO",$C$53:$C$318,$C41)/'Shared Summary by Dept_US$'!$B$32+SUMIFS(J$53:J$318,$A$53:$A$318,"BD",$C$53:$C$318,$C41)/'Shared Summary by Dept_US$'!$B$33+SUMIFS(J$53:J$318,$A$53:$A$318,"Nepal",$C$53:$C$318,$C41)/'Shared Summary by Dept_US$'!$B$34+SUMIFS(J$53:J$318,$A$53:$A$318,"US",$C$53:$C$318,$C41)/'Shared Summary by Dept_US$'!$B$35 -> 0 | K41: =SUMIFS(K$53:K$318,$A$53:$A$318,"India",$C$53:$C$318,$C41)/'Shared Summary by Dept_US$'!$B$31+SUMIFS(K$53:K$318,$A$53:$A$318,"INDO",$C$53:$C$318,$C41)/'Shared Summary by Dept_US$'!$B$32+SUMIFS(K$53:K$318,$A$53:$A$318,"BD",$C$53:$C$318,$C41)/'Shared Summary by Dept_US$'!$B$33+SUMIFS(K$53:K$318,$A$53:$A$318,"Nepal",$C$53:$C$318,$C41)/'Shared Summary by Dept_US$'!$B$34+SUMIFS(K$53:K$318,$A$53:$A$318,"US",$C$53:$C$318,$C41)/'Shared Summary by Dept_US$'!$B$35 -> 0 | L41: =SUMIFS(L$53:L$318,$A$53:$A$318,"India",$C$53:$C$318,$C41)/'Shared Summary by Dept_US$'!$B$31+SUMIFS(L$53:L$318,$A$53:$A$318,"INDO",$C$53:$C$318,$C41)/'Shared Summary by Dept_US$'!$B$32+SUMIFS(L$53:L$318,$A$53:$A$318,"BD",$C$53:$C$318,$C41)/'Shared Summary by Dept_US$'!$B$33+SUMIFS(L$53:L$318,$A$53:$A$318,"Nepal",$C$53:$C$318,$C41)/'Shared Summary by Dept_US$'!$B$34+SUMIFS(L$53:L$318,$A$53:$A$318,"US",$C$53:$C$318,$C41)/'Shared Summary by Dept_US$'!$B$35 -> 0 | M41: =SUMIFS(M$53:M$318,$A$53:$A$318,"India",$C$53:$C$318,$C41)/'Shared Summary by Dept_US$'!$B$31+SUMIFS(M$53:M$318,$A$53:$A$318,"INDO",$C$53:$C$318,$C41)/'Shared Summary by Dept_US$'!$B$32+SUMIFS(M$53:M$318,$A$53:$A$318,"BD",$C$53:$C$318,$C41)/'Shared Summary by Dept_US$'!$B$33+SUMIFS(M$53:M$318,$A$53:$A$318,"Nepal",$C$53:$C$318,$C41)/'Shared Summary by Dept_US$'!$B$34+SUMIFS(M$53:M$318,$A$53:$A$318,"US",$C$53:$C$318,$C41)/'Shared Summary by Dept_US$'!$B$35 -> 0 | ... Q41: =SUMIFS(Q$53:Q$318,$A$53:$A$318,"India",$C$53:$C$318,$C41)/'Shared Summary by Dept_US$'!$B$31+SUMIFS(Q$53:Q$318,$A$53:$A$318,"INDO",$C$53:$C$318,$C41)/'Shared Summary by Dept_US$'!$B$32+SUMIFS(Q$53:Q$318,$A$53:$A$318,"BD",$C$53:$C$318,$C41)/'Shared Summary by Dept_US$'!$B$33+SUMIFS(Q$53:Q$318,$A$53:$A$318,"Nepal",$C$53:$C$318,$C41)/'Shared Summary by Dept_US$'!$B$34+SUMIFS(Q$53:Q$318,$A$53:$A$318,"US",$C$53:$C$318,$C41)/'Shared Summary by Dept_US$'!$B$35 -> 0
A42: Digital product | B42: Professional & Consultancy Charges | C42: Audit Fees & Expenses | D42: 93701 | E42: =SUM(F42:Q42) -> 0 | F42: =SUMIFS(F$53:F$318,$A$53:$A$318,"India",$C$53:$C$318,$C42)/'Shared Summary by Dept_US$'!$B$31+SUMIFS(F$53:F$318,$A$53:$A$318,"INDO",$C$53:$C$318,$C42)/'Shared Summary by Dept_US$'!$B$32+SUMIFS(F$53:F$318,$A$53:$A$318,"BD",$C$53:$C$318,$C42)/'Shared Summary by Dept_US$'!$B$33+SUMIFS(F$53:F$318,$A$53:$A$318,"Nepal",$C$53:$C$318,$C42)/'Shared Summary by Dept_US$'!$B$34+SUMIFS(F$53:F$318,$A$53:$A$318,"US",$C$53:$C$318,$C42)/'Shared Summary by Dept_US$'!$B$35 -> 0 | G42: =SUMIFS(G$53:G$318,$A$53:$A$318,"India",$C$53:$C$318,$C42)/'Shared Summary by Dept_US$'!$B$31+SUMIFS(G$53:G$318,$A$53:$A$318,"INDO",$C$53:$C$318,$C42)/'Shared Summary by Dept_US$'!$B$32+SUMIFS(G$53:G$318,$A$53:$A$318,"BD",$C$53:$C$318,$C42)/'Shared Summary by Dept_US$'!$B$33+SUMIFS(G$53:G$318,$A$53:$A$318,"Nepal",$C$53:$C$318,$C42)/'Shared Summary by Dept_US$'!$B$34+SUMIFS(G$53:G$318,$A$53:$A$318,"US",$C$53:$C$318,$C42)/'Shared Summary by Dept_US$'!$B$35 -> 0 | H42: =SUMIFS(H$53:H$318,$A$53:$A$318,"India",$C$53:$C$318,$C42)/'Shared Summary by Dept_US$'!$B$31+SUMIFS(H$53:H$318,$A$53:$A$318,"INDO",$C$53:$C$318,$C42)/'Shared Summary by Dept_US$'!$B$32+SUMIFS(H$53:H$318,$A$53:$A$318,"BD",$C$53:$C$318,$C42)/'Shared Summary by Dept_US$'!$B$33+SUMIFS(H$53:H$318,$A$53:$A$318,"Nepal",$C$53:$C$318,$C42)/'Shared Summary by Dept_US$'!$B$34+SUMIFS(H$53:H$318,$A$53:$A$318,"US",$C$53:$C$318,$C42)/'Shared Summary by Dept_US$'!$B$35 -> 0 | I42: =SUMIFS(I$53:I$318,$A$53:$A$318,"India",$C$53:$C$318,$C42)/'Shared Summary by Dept_US$'!$B$31+SUMIFS(I$53:I$318,$A$53:$A$318,"INDO",$C$53:$C$318,$C42)/'Shared Summary by Dept_US$'!$B$32+SUMIFS(I$53:I$318,$A$53:$A$318,"BD",$C$53:$C$318,$C42)/'Shared Summary by Dept_US$'!$B$33+SUMIFS(I$53:I$318,$A$53:$A$318,"Nepal",$C$53:$C$318,$C42)/'Shared Summary by Dept_US$'!$B$34+SUMIFS(I$53:I$318,$A$53:$A$318,"US",$C$53:$C$318,$C42)/'Shared Summary by Dept_US$'!$B$35 -> 0 | J42: =SUMIFS(J$53:J$318,$A$53:$A$318,"India",$C$53:$C$318,$C42)/'Shared Summary by Dept_US$'!$B$31+SUMIFS(J$53:J$318,$A$53:$A$318,"INDO",$C$53:$C$318,$C42)/'Shared Summary by Dept_US$'!$B$32+SUMIFS(J$53:J$318,$A$53:$A$318,"BD",$C$53:$C$318,$C42)/'Shared Summary by Dept_US$'!$B$33+SUMIFS(J$53:J$318,$A$53:$A$318,"Nepal",$C$53:$C$318,$C42)/'Shared Summary by Dept_US$'!$B$34+SUMIFS(J$53:J$318,$A$53:$A$318,"US",$C$53:$C$318,$C42)/'Shared Summary by Dept_US$'!$B$35 -> 0 | K42: =SUMIFS(K$53:K$318,$A$53:$A$318,"India",$C$53:$C$318,$C42)/'Shared Summary by Dept_US$'!$B$31+SUMIFS(K$53:K$318,$A$53:$A$318,"INDO",$C$53:$C$318,$C42)/'Shared Summary by Dept_US$'!$B$32+SUMIFS(K$53:K$318,$A$53:$A$318,"BD",$C$53:$C$318,$C42)/'Shared Summary by Dept_US$'!$B$33+SUMIFS(K$53:K$318,$A$53:$A$318,"Nepal",$C$53:$C$318,$C42)/'Shared Summary by Dept_US$'!$B$34+SUMIFS(K$53:K$318,$A$53:$A$318,"US",$C$53:$C$318,$C42)/'Shared Summary by Dept_US$'!$B$35 -> 0 | L42: =SUMIFS(L$53:L$318,$A$53:$A$318,"India",$C$53:$C$318,$C42)/'Shared Summary by Dept_US$'!$B$31+SUMIFS(L$53:L$318,$A$53:$A$318,"INDO",$C$53:$C$318,$C42)/'Shared Summary by Dept_US$'!$B$32+SUMIFS(L$53:L$318,$A$53:$A$318,"BD",$C$53:$C$318,$C42)/'Shared Summary by Dept_US$'!$B$33+SUMIFS(L$53:L$318,$A$53:$A$318,"Nepal",$C$53:$C$318,$C42)/'Shared Summary by Dept_US$'!$B$34+SUMIFS(L$53:L$318,$A$53:$A$318,"US",$C$53:$C$318,$C42)/'Shared Summary by Dept_US$'!$B$35 -> 0 | M42: =SUMIFS(M$53:M$318,$A$53:$A$318,"India",$C$53:$C$318,$C42)/'Shared Summary by Dept_US$'!$B$31+SUMIFS(M$53:M$318,$A$53:$A$318,"INDO",$C$53:$C$318,$C42)/'Shared Summary by Dept_US$'!$B$32+SUMIFS(M$53:M$318,$A$53:$A$318,"BD",$C$53:$C$318,$C42)/'Shared Summary by Dept_US$'!$B$33+SUMIFS(M$53:M$318,$A$53:$A$318,"Nepal",$C$53:$C$318,$C42)/'Shared Summary by Dept_US$'!$B$34+SUMIFS(M$53:M$318,$A$53:$A$318,"US",$C$53:$C$318,$C42)/'Shared Summary by Dept_US$'!$B$35 -> 0 | ... Q42: =SUMIFS(Q$53:Q$318,$A$53:$A$318,"India",$C$53:$C$318,$C42)/'Shared Summary by Dept_US$'!$B$31+SUMIFS(Q$53:Q$318,$A$53:$A$318,"INDO",$C$53:$C$318,$C42)/'Shared Summary by Dept_US$'!$B$32+SUMIFS(Q$53:Q$318,$A$53:$A$318,"BD",$C$53:$C$318,$C42)/'Shared Summary by Dept_US$'!$B$33+SUMIFS(Q$53:Q$318,$A$53:$A$318,"Nepal",$C$53:$C$318,$C42)/'Shared Summary by Dept_US$'!$B$34+SUMIFS(Q$53:Q$318,$A$53:$A$318,"US",$C$53:$C$318,$C42)/'Shared Summary by Dept_US$'!$B$35 -> 0
A43: Digital product | B43: Professional & Consultancy Charges | C43: Legal Expenses | D43: 93702 | E43: =SUM(F43:Q43) -> 0 | F43: =SUMIFS(F$53:F$318,$A$53:$A$318,"India",$C$53:$C$318,$C43)/'Shared Summary by Dept_US$'!$B$31+SUMIFS(F$53:F$318,$A$53:$A$318,"INDO",$C$53:$C$318,$C43)/'Shared Summary by Dept_US$'!$B$32+SUMIFS(F$53:F$318,$A$53:$A$318,"BD",$C$53:$C$318,$C43)/'Shared Summary by Dept_US$'!$B$33+SUMIFS(F$53:F$318,$A$53:$A$318,"Nepal",$C$53:$C$318,$C43)/'Shared Summary by Dept_US$'!$B$34+SUMIFS(F$53:F$318,$A$53:$A$318,"US",$C$53:$C$318,$C43)/'Shared Summary by Dept_US$'!$B$35 -> 0 | G43: =SUMIFS(G$53:G$318,$A$53:$A$318,"India",$C$53:$C$318,$C43)/'Shared Summary by Dept_US$'!$B$31+SUMIFS(G$53:G$318,$A$53:$A$318,"INDO",$C$53:$C$318,$C43)/'Shared Summary by Dept_US$'!$B$32+SUMIFS(G$53:G$318,$A$53:$A$318,"BD",$C$53:$C$318,$C43)/'Shared Summary by Dept_US$'!$B$33+SUMIFS(G$53:G$318,$A$53:$A$318,"Nepal",$C$53:$C$318,$C43)/'Shared Summary by Dept_US$'!$B$34+SUMIFS(G$53:G$318,$A$53:$A$318,"US",$C$53:$C$318,$C43)/'Shared Summary by Dept_US$'!$B$35 -> 0 | H43: =SUMIFS(H$53:H$318,$A$53:$A$318,"India",$C$53:$C$318,$C43)/'Shared Summary by Dept_US$'!$B$31+SUMIFS(H$53:H$318,$A$53:$A$318,"INDO",$C$53:$C$318,$C43)/'Shared Summary by Dept_US$'!$B$32+SUMIFS(H$53:H$318,$A$53:$A$318,"BD",$C$53:$C$318,$C43)/'Shared Summary by Dept_US$'!$B$33+SUMIFS(H$53:H$318,$A$53:$A$318,"Nepal",$C$53:$C$318,$C43)/'Shared Summary by Dept_US$'!$B$34+SUMIFS(H$53:H$318,$A$53:$A$318,"US",$C$53:$C$318,$C43)/'Shared Summary by Dept_US$'!$B$35 -> 0 | I43: =SUMIFS(I$53:I$318,$A$53:$A$318,"India",$C$53:$C$318,$C43)/'Shared Summary by Dept_US$'!$B$31+SUMIFS(I$53:I$318,$A$53:$A$318,"INDO",$C$53:$C$318,$C43)/'Shared Summary by Dept_US$'!$B$32+SUMIFS(I$53:I$318,$A$53:$A$318,"BD",$C$53:$C$318,$C43)/'Shared Summary by Dept_US$'!$B$33+SUMIFS(I$53:I$318,$A$53:$A$318,"Nepal",$C$53:$C$318,$C43)/'Shared Summary by Dept_US$'!$B$34+SUMIFS(I$53:I$318,$A$53:$A$318,"US",$C$53:$C$318,$C43)/'Shared Summary by Dept_US$'!$B$35 -> 0 | J43: =SUMIFS(J$53:J$318,$A$53:$A$318,"India",$C$53:$C$318,$C43)/'Shared Summary by Dept_US$'!$B$31+SUMIFS(J$53:J$318,$A$53:$A$318,"INDO",$C$53:$C$318,$C43)/'Shared Summary by Dept_US$'!$B$32+SUMIFS(J$53:J$318,$A$53:$A$318,"BD",$C$53:$C$318,$C43)/'Shared Summary by Dept_US$'!$B$33+SUMIFS(J$53:J$318,$A$53:$A$318,"Nepal",$C$53:$C$318,$C43)/'Shared Summary by Dept_US$'!$B$34+SUMIFS(J$53:J$318,$A$53:$A$318,"US",$C$53:$C$318,$C43)/'Shared Summary by Dept_US$'!$B$35 -> 0 | K43: =SUMIFS(K$53:K$318,$A$53:$A$318,"India",$C$53:$C$318,$C43)/'Shared Summary by Dept_US$'!$B$31+SUMIFS(K$53:K$318,$A$53:$A$318,"INDO",$C$53:$C$318,$C43)/'Shared Summary by Dept_US$'!$B$32+SUMIFS(K$53:K$318,$A$53:$A$318,"BD",$C$53:$C$318,$C43)/'Shared Summary by Dept_US$'!$B$33+SUMIFS(K$53:K$318,$A$53:$A$318,"Nepal",$C$53:$C$318,$C43)/'Shared Summary by Dept_US$'!$B$34+SUMIFS(K$53:K$318,$A$53:$A$318,"US",$C$53:$C$318,$C43)/'Shared Summary by Dept_US$'!$B$35 -> 0 | L43: =SUMIFS(L$53:L$318,$A$53:$A$318,"India",$C$53:$C$318,$C43)/'Shared Summary by Dept_US$'!$B$31+SUMIFS(L$53:L$318,$A$53:$A$318,"INDO",$C$53:$C$318,$C43)/'Shared Summary by Dept_US$'!$B$32+SUMIFS(L$53:L$318,$A$53:$A$318,"BD",$C$53:$C$318,$C43)/'Shared Summary by Dept_US$'!$B$33+SUMIFS(L$53:L$318,$A$53:$A$318,"Nepal",$C$53:$C$318,$C43)/'Shared Summary by Dept_US$'!$B$34+SUMIFS(L$53:L$318,$A$53:$A$318,"US",$C$53:$C$318,$C43)/'Shared Summary by Dept_US$'!$B$35 -> 0 | M43: =SUMIFS(M$53:M$318,$A$53:$A$318,"India",$C$53:$C$318,$C43)/'Shared Summary by Dept_US$'!$B$31+SUMIFS(M$53:M$318,$A$53:$A$318,"INDO",$C$53:$C$318,$C43)/'Shared Summary by Dept_US$'!$B$32+SUMIFS(M$53:M$318,$A$53:$A$318,"BD",$C$53:$C$318,$C43)/'Shared Summary by Dept_US$'!$B$33+SUMIFS(M$53:M$318,$A$53:$A$318,"Nepal",$C$53:$C$318,$C43)/'Shared Summary by Dept_US$'!$B$34+SUMIFS(M$53:M$318,$A$53:$A$318,"US",$C$53:$C$318,$C43)/'Shared Summary by Dept_US$'!$B$35 -> 0 | ... Q43: =SUMIFS(Q$53:Q$318,$A$53:$A$318,"India",$C$53:$C$318,$C43)/'Shared Summary by Dept_US$'!$B$31+SUMIFS(Q$53:Q$318,$A$53:$A$318,"INDO",$C$53:$C$318,$C43)/'Shared Summary by Dept_US$'!$B$32+SUMIFS(Q$53:Q$318,$A$53:$A$318,"BD",$C$53:$C$318,$C43)/'Shared Summary by Dept_US$'!$B$33+SUMIFS(Q$53:Q$318,$A$53:$A$318,"Nepal",$C$53:$C$318,$C43)/'Shared Summary by Dept_US$'!$B$34+SUMIFS(Q$53:Q$318,$A$53:$A$318,"US",$C$53:$C$318,$C43)/'Shared Summary by Dept_US$'!$B$35 -> 0
A44: Digital product | B44: Professional & Consultancy Charges | C44: Admin Consultants | D44: 93703 | E44: =SUM(F44:Q44) -> 36041.207 | F44: =SUMIFS(F$53:F$318,$A$53:$A$318,"India",$C$53:$C$318,$C44)/'Shared Summary by Dept_US$'!$B$31+SUMIFS(F$53:F$318,$A$53:$A$318,"INDO",$C$53:$C$318,$C44)/'Shared Summary by Dept_US$'!$B$32+SUMIFS(F$53:F$318,$A$53:$A$318,"BD",$C$53:$C$318,$C44)/'Shared Summary by Dept_US$'!$B$33+SUMIFS(F$53:F$318,$A$53:$A$318,"Nepal",$C$53:$C$318,$C44)/'Shared Summary by Dept_US$'!$B$34+SUMIFS(F$53:F$318,$A$53:$A$318,"US",$C$53:$C$318,$C44)/'Shared Summary by Dept_US$'!$B$35 -> 8253.8506 | G44: =SUMIFS(G$53:G$318,$A$53:$A$318,"India",$C$53:$C$318,$C44)/'Shared Summary by Dept_US$'!$B$31+SUMIFS(G$53:G$318,$A$53:$A$318,"INDO",$C$53:$C$318,$C44)/'Shared Summary by Dept_US$'!$B$32+SUMIFS(G$53:G$318,$A$53:$A$318,"BD",$C$53:$C$318,$C44)/'Shared Summary by Dept_US$'!$B$33+SUMIFS(G$53:G$318,$A$53:$A$318,"Nepal",$C$53:$C$318,$C44)/'Shared Summary by Dept_US$'!$B$34+SUMIFS(G$53:G$318,$A$53:$A$318,"US",$C$53:$C$318,$C44)/'Shared Summary by Dept_US$'!$B$35 -> 2298.8506 | H44: =SUMIFS(H$53:H$318,$A$53:$A$318,"India",$C$53:$C$318,$C44)/'Shared Summary by Dept_US$'!$B$31+SUMIFS(H$53:H$318,$A$53:$A$318,"INDO",$C$53:$C$318,$C44)/'Shared Summary by Dept_US$'!$B$32+SUMIFS(H$53:H$318,$A$53:$A$318,"BD",$C$53:$C$318,$C44)/'Shared Summary by Dept_US$'!$B$33+SUMIFS(H$53:H$318,$A$53:$A$318,"Nepal",$C$53:$C$318,$C44)/'Shared Summary by Dept_US$'!$B$34+SUMIFS(H$53:H$318,$A$53:$A$318,"US",$C$53:$C$318,$C44)/'Shared Summary by Dept_US$'!$B$35 -> 2298.8506 | I44: =SUMIFS(I$53:I$318,$A$53:$A$318,"India",$C$53:$C$318,$C44)/'Shared Summary by Dept_US$'!$B$31+SUMIFS(I$53:I$318,$A$53:$A$318,"INDO",$C$53:$C$318,$C44)/'Shared Summary by Dept_US$'!$B$32+SUMIFS(I$53:I$318,$A$53:$A$318,"BD",$C$53:$C$318,$C44)/'Shared Summary by Dept_US$'!$B$33+SUMIFS(I$53:I$318,$A$53:$A$318,"Nepal",$C$53:$C$318,$C44)/'Shared Summary by Dept_US$'!$B$34+SUMIFS(I$53:I$318,$A$53:$A$318,"US",$C$53:$C$318,$C44)/'Shared Summary by Dept_US$'!$B$35 -> 2298.8506 | J44: =SUMIFS(J$53:J$318,$A$53:$A$318,"India",$C$53:$C$318,$C44)/'Shared Summary by Dept_US$'!$B$31+SUMIFS(J$53:J$318,$A$53:$A$318,"INDO",$C$53:$C$318,$C44)/'Shared Summary by Dept_US$'!$B$32+SUMIFS(J$53:J$318,$A$53:$A$318,"BD",$C$53:$C$318,$C44)/'Shared Summary by Dept_US$'!$B$33+SUMIFS(J$53:J$318,$A$53:$A$318,"Nepal",$C$53:$C$318,$C44)/'Shared Summary by Dept_US$'!$B$34+SUMIFS(J$53:J$318,$A$53:$A$318,"US",$C$53:$C$318,$C44)/'Shared Summary by Dept_US$'!$B$35 -> 2298.8506 | K44: =SUMIFS(K$53:K$318,$A$53:$A$318,"India",$C$53:$C$318,$C44)/'Shared Summary by Dept_US$'!$B$31+SUMIFS(K$53:K$318,$A$53:$A$318,"INDO",$C$53:$C$318,$C44)/'Shared Summary by Dept_US$'!$B$32+SUMIFS(K$53:K$318,$A$53:$A$318,"BD",$C$53:$C$318,$C44)/'Shared Summary by Dept_US$'!$B$33+SUMIFS(K$53:K$318,$A$53:$A$318,"Nepal",$C$53:$C$318,$C44)/'Shared Summary by Dept_US$'!$B$34+SUMIFS(K$53:K$318,$A$53:$A$318,"US",$C$53:$C$318,$C44)/'Shared Summary by Dept_US$'!$B$35 -> 2298.8506 | L44: =SUMIFS(L$53:L$318,$A$53:$A$318,"India",$C$53:$C$318,$C44)/'Shared Summary by Dept_US$'!$B$31+SUMIFS(L$53:L$318,$A$53:$A$318,"INDO",$C$53:$C$318,$C44)/'Shared Summary by Dept_US$'!$B$32+SUMIFS(L$53:L$318,$A$53:$A$318,"BD",$C$53:$C$318,$C44)/'Shared Summary by Dept_US$'!$B$33+SUMIFS(L$53:L$318,$A$53:$A$318,"Nepal",$C$53:$C$318,$C44)/'Shared Summary by Dept_US$'!$B$34+SUMIFS(L$53:L$318,$A$53:$A$318,"US",$C$53:$C$318,$C44)/'Shared Summary by Dept_US$'!$B$35 -> 2298.8506 | M44: =SUMIFS(M$53:M$318,$A$53:$A$318,"India",$C$53:$C$318,$C44)/'Shared Summary by Dept_US$'!$B$31+SUMIFS(M$53:M$318,$A$53:$A$318,"INDO",$C$53:$C$318,$C44)/'Shared Summary by Dept_US$'!$B$32+SUMIFS(M$53:M$318,$A$53:$A$318,"BD",$C$53:$C$318,$C44)/'Shared Summary by Dept_US$'!$B$33+SUMIFS(M$53:M$318,$A$53:$A$318,"Nepal",$C$53:$C$318,$C44)/'Shared Summary by Dept_US$'!$B$34+SUMIFS(M$53:M$318,$A$53:$A$318,"US",$C$53:$C$318,$C44)/'Shared Summary by Dept_US$'!$B$35 -> 2298.8506 | ... Q44: =SUMIFS(Q$53:Q$318,$A$53:$A$318,"India",$C$53:$C$318,$C44)/'Shared Summary by Dept_US$'!$B$31+SUMIFS(Q$53:Q$318,$A$53:$A$318,"INDO",$C$53:$C$318,$C44)/'Shared Summary by Dept_US$'!$B$32+SUMIFS(Q$53:Q$318,$A$53:$A$318,"BD",$C$53:$C$318,$C44)/'Shared Summary by Dept_US$'!$B$33+SUMIFS(Q$53:Q$318,$A$53:$A$318,"Nepal",$C$53:$C$318,$C44)/'Shared Summary by Dept_US$'!$B$34+SUMIFS(Q$53:Q$318,$A$53:$A$318,"US",$C$53:$C$318,$C44)/'Shared Summary by Dept_US$'!$B$35 -> 2298.8506
A45: Digital product | B45: Fixed Assets | C45: Laptop/ Printer | D45: 11301 | E45: =SUM(F45:Q45) -> 45886.494 | F45: =SUMIFS(F$53:F$318,$A$53:$A$318,"India",$C$53:$C$318,$C45)/'Shared Summary by Dept_US$'!$B$31+SUMIFS(F$53:F$318,$A$53:$A$318,"INDO",$C$53:$C$318,$C45)/'Shared Summary by Dept_US$'!$B$32+SUMIFS(F$53:F$318,$A$53:$A$318,"BD",$C$53:$C$318,$C45)/'Shared Summary by Dept_US$'!$B$33+SUMIFS(F$53:F$318,$A$53:$A$318,"Nepal",$C$53:$C$318,$C45)/'Shared Summary by Dept_US$'!$B$34+SUMIFS(F$53:F$318,$A$53:$A$318,"US",$C$53:$C$318,$C45)/'Shared Summary by Dept_US$'!$B$35 -> 0 | G45: =SUMIFS(G$53:G$318,$A$53:$A$318,"India",$C$53:$C$318,$C45)/'Shared Summary by Dept_US$'!$B$31+SUMIFS(G$53:G$318,$A$53:$A$318,"INDO",$C$53:$C$318,$C45)/'Shared Summary by Dept_US$'!$B$32+SUMIFS(G$53:G$318,$A$53:$A$318,"BD",$C$53:$C$318,$C45)/'Shared Summary by Dept_US$'!$B$33+SUMIFS(G$53:G$318,$A$53:$A$318,"Nepal",$C$53:$C$318,$C45)/'Shared Summary by Dept_US$'!$B$34+SUMIFS(G$53:G$318,$A$53:$A$318,"US",$C$53:$C$318,$C45)/'Shared Summary by Dept_US$'!$B$35 -> 11166.667 | H45: =SUMIFS(H$53:H$318,$A$53:$A$318,"India",$C$53:$C$318,$C45)/'Shared Summary by Dept_US$'!$B$31+SUMIFS(H$53:H$318,$A$53:$A$318,"INDO",$C$53:$C$318,$C45)/'Shared Summary by Dept_US$'!$B$32+SUMIFS(H$53:H$318,$A$53:$A$318,"BD",$C$53:$C$318,$C45)/'Shared Summary by Dept_US$'!$B$33+SUMIFS(H$53:H$318,$A$53:$A$318,"Nepal",$C$53:$C$318,$C45)/'Shared Summary by Dept_US$'!$B$34+SUMIFS(H$53:H$318,$A$53:$A$318,"US",$C$53:$C$318,$C45)/'Shared Summary by Dept_US$'!$B$35 -> 14080.46 | I45: =SUMIFS(I$53:I$318,$A$53:$A$318,"India",$C$53:$C$318,$C45)/'Shared Summary by Dept_US$'!$B$31+SUMIFS(I$53:I$318,$A$53:$A$318,"INDO",$C$53:$C$318,$C45)/'Shared Summary by Dept_US$'!$B$32+SUMIFS(I$53:I$318,$A$53:$A$318,"BD",$C$53:$C$318,$C45)/'Shared Summary by Dept_US$'!$B$33+SUMIFS(I$53:I$318,$A$53:$A$318,"Nepal",$C$53:$C$318,$C45)/'Shared Summary by Dept_US$'!$B$34+SUMIFS(I$53:I$318,$A$53:$A$318,"US",$C$53:$C$318,$C45)/'Shared Summary by Dept_US$'!$B$35 -> 20639.368 | J45: =SUMIFS(J$53:J$318,$A$53:$A$318,"India",$C$53:$C$318,$C45)/'Shared Summary by Dept_US$'!$B$31+SUMIFS(J$53:J$318,$A$53:$A$318,"INDO",$C$53:$C$318,$C45)/'Shared Summary by Dept_US$'!$B$32+SUMIFS(J$53:J$318,$A$53:$A$318,"BD",$C$53:$C$318,$C45)/'Shared Summary by Dept_US$'!$B$33+SUMIFS(J$53:J$318,$A$53:$A$318,"Nepal",$C$53:$C$318,$C45)/'Shared Summary by Dept_US$'!$B$34+SUMIFS(J$53:J$318,$A$53:$A$318,"US",$C$53:$C$318,$C45)/'Shared Summary by Dept_US$'!$B$35 -> 0 | K45: =SUMIFS(K$53:K$318,$A$53:$A$318,"India",$C$53:$C$318,$C45)/'Shared Summary by Dept_US$'!$B$31+SUMIFS(K$53:K$318,$A$53:$A$318,"INDO",$C$53:$C$318,$C45)/'Shared Summary by Dept_US$'!$B$32+SUMIFS(K$53:K$318,$A$53:$A$318,"BD",$C$53:$C$318,$C45)/'Shared Summary by Dept_US$'!$B$33+SUMIFS(K$53:K$318,$A$53:$A$318,"Nepal",$C$53:$C$318,$C45)/'Shared Summary by Dept_US$'!$B$34+SUMIFS(K$53:K$318,$A$53:$A$318,"US",$C$53:$C$318,$C45)/'Shared Summary by Dept_US$'!$B$35 -> 0 | L45: =SUMIFS(L$53:L$318,$A$53:$A$318,"India",$C$53:$C$318,$C45)/'Shared Summary by Dept_US$'!$B$31+SUMIFS(L$53:L$318,$A$53:$A$318,"INDO",$C$53:$C$318,$C45)/'Shared Summary by Dept_US$'!$B$32+SUMIFS(L$53:L$318,$A$53:$A$318,"BD",$C$53:$C$318,$C45)/'Shared Summary by Dept_US$'!$B$33+SUMIFS(L$53:L$318,$A$53:$A$318,"Nepal",$C$53:$C$318,$C45)/'Shared Summary by Dept_US$'!$B$34+SUMIFS(L$53:L$318,$A$53:$A$318,"US",$C$53:$C$318,$C45)/'Shared Summary by Dept_US$'!$B$35 -> 0 | M45: =SUMIFS(M$53:M$318,$A$53:$A$318,"India",$C$53:$C$318,$C45)/'Shared Summary by Dept_US$'!$B$31+SUMIFS(M$53:M$318,$A$53:$A$318,"INDO",$C$53:$C$318,$C45)/'Shared Summary by Dept_US$'!$B$32+SUMIFS(M$53:M$318,$A$53:$A$318,"BD",$C$53:$C$318,$C45)/'Shared Summary by Dept_US$'!$B$33+SUMIFS(M$53:M$318,$A$53:$A$318,"Nepal",$C$53:$C$318,$C45)/'Shared Summary by Dept_US$'!$B$34+SUMIFS(M$53:M$318,$A$53:$A$318,"US",$C$53:$C$318,$C45)/'Shared Summary by Dept_US$'!$B$35 -> 0 | ... Q45: =SUMIFS(Q$53:Q$318,$A$53:$A$318,"India",$C$53:$C$318,$C45)/'Shared Summary by Dept_US$'!$B$31+SUMIFS(Q$53:Q$318,$A$53:$A$318,"INDO",$C$53:$C$318,$C45)/'Shared Summary by Dept_US$'!$B$32+SUMIFS(Q$53:Q$318,$A$53:$A$318,"BD",$C$53:$C$318,$C45)/'Shared Summary by Dept_US$'!$B$33+SUMIFS(Q$53:Q$318,$A$53:$A$318,"Nepal",$C$53:$C$318,$C45)/'Shared Summary by Dept_US$'!$B$34+SUMIFS(Q$53:Q$318,$A$53:$A$318,"US",$C$53:$C$318,$C45)/'Shared Summary by Dept_US$'!$B$35 -> 0
A46: Digital product | B46: Office Expenses | C46: Noora U Session | E46: =SUM(F46:Q46) -> 0 | F46: =SUMIFS(F$53:F$318,$A$53:$A$318,"India",$C$53:$C$318,$C46)/'Shared Summary by Dept_US$'!$B$31+SUMIFS(F$53:F$318,$A$53:$A$318,"INDO",$C$53:$C$318,$C46)/'Shared Summary by Dept_US$'!$B$32+SUMIFS(F$53:F$318,$A$53:$A$318,"BD",$C$53:$C$318,$C46)/'Shared Summary by Dept_US$'!$B$33+SUMIFS(F$53:F$318,$A$53:$A$318,"Nepal",$C$53:$C$318,$C46)/'Shared Summary by Dept_US$'!$B$34+SUMIFS(F$53:F$318,$A$53:$A$318,"US",$C$53:$C$318,$C46)/'Shared Summary by Dept_US$'!$B$35 -> 0 | G46: =SUMIFS(G$53:G$318,$A$53:$A$318,"India",$C$53:$C$318,$C46)/'Shared Summary by Dept_US$'!$B$31+SUMIFS(G$53:G$318,$A$53:$A$318,"INDO",$C$53:$C$318,$C46)/'Shared Summary by Dept_US$'!$B$32+SUMIFS(G$53:G$318,$A$53:$A$318,"BD",$C$53:$C$318,$C46)/'Shared Summary by Dept_US$'!$B$33+SUMIFS(G$53:G$318,$A$53:$A$318,"Nepal",$C$53:$C$318,$C46)/'Shared Summary by Dept_US$'!$B$34+SUMIFS(G$53:G$318,$A$53:$A$318,"US",$C$53:$C$318,$C46)/'Shared Summary by Dept_US$'!$B$35 -> 0 | H46: =SUMIFS(H$53:H$318,$A$53:$A$318,"India",$C$53:$C$318,$C46)/'Shared Summary by Dept_US$'!$B$31+SUMIFS(H$53:H$318,$A$53:$A$318,"INDO",$C$53:$C$318,$C46)/'Shared Summary by Dept_US$'!$B$32+SUMIFS(H$53:H$318,$A$53:$A$318,"BD",$C$53:$C$318,$C46)/'Shared Summary by Dept_US$'!$B$33+SUMIFS(H$53:H$318,$A$53:$A$318,"Nepal",$C$53:$C$318,$C46)/'Shared Summary by Dept_US$'!$B$34+SUMIFS(H$53:H$318,$A$53:$A$318,"US",$C$53:$C$318,$C46)/'Shared Summary by Dept_US$'!$B$35 -> 0 | I46: =SUMIFS(I$53:I$318,$A$53:$A$318,"India",$C$53:$C$318,$C46)/'Shared Summary by Dept_US$'!$B$31+SUMIFS(I$53:I$318,$A$53:$A$318,"INDO",$C$53:$C$318,$C46)/'Shared Summary by Dept_US$'!$B$32+SUMIFS(I$53:I$318,$A$53:$A$318,"BD",$C$53:$C$318,$C46)/'Shared Summary by Dept_US$'!$B$33+SUMIFS(I$53:I$318,$A$53:$A$318,"Nepal",$C$53:$C$318,$C46)/'Shared Summary by Dept_US$'!$B$34+SUMIFS(I$53:I$318,$A$53:$A$318,"US",$C$53:$C$318,$C46)/'Shared Summary by Dept_US$'!$B$35 -> 0 | J46: =SUMIFS(J$53:J$318,$A$53:$A$318,"India",$C$53:$C$318,$C46)/'Shared Summary by Dept_US$'!$B$31+SUMIFS(J$53:J$318,$A$53:$A$318,"INDO",$C$53:$C$318,$C46)/'Shared Summary by Dept_US$'!$B$32+SUMIFS(J$53:J$318,$A$53:$A$318,"BD",$C$53:$C$318,$C46)/'Shared Summary by Dept_US$'!$B$33+SUMIFS(J$53:J$318,$A$53:$A$318,"Nepal",$C$53:$C$318,$C46)/'Shared Summary by Dept_US$'!$B$34+SUMIFS(J$53:J$318,$A$53:$A$318,"US",$C$53:$C$318,$C46)/'Shared Summary by Dept_US$'!$B$35 -> 0 | K46: =SUMIFS(K$53:K$318,$A$53:$A$318,"India",$C$53:$C$318,$C46)/'Shared Summary by Dept_US$'!$B$31+SUMIFS(K$53:K$318,$A$53:$A$318,"INDO",$C$53:$C$318,$C46)/'Shared Summary by Dept_US$'!$B$32+SUMIFS(K$53:K$318,$A$53:$A$318,"BD",$C$53:$C$318,$C46)/'Shared Summary by Dept_US$'!$B$33+SUMIFS(K$53:K$318,$A$53:$A$318,"Nepal",$C$53:$C$318,$C46)/'Shared Summary by Dept_US$'!$B$34+SUMIFS(K$53:K$318,$A$53:$A$318,"US",$C$53:$C$318,$C46)/'Shared Summary by Dept_US$'!$B$35 -> 0 | L46: =SUMIFS(L$53:L$318,$A$53:$A$318,"India",$C$53:$C$318,$C46)/'Shared Summary by Dept_US$'!$B$31+SUMIFS(L$53:L$318,$A$53:$A$318,"INDO",$C$53:$C$318,$C46)/'Shared Summary by Dept_US$'!$B$32+SUMIFS(L$53:L$318,$A$53:$A$318,"BD",$C$53:$C$318,$C46)/'Shared Summary by Dept_US$'!$B$33+SUMIFS(L$53:L$318,$A$53:$A$318,"Nepal",$C$53:$C$318,$C46)/'Shared Summary by Dept_US$'!$B$34+SUMIFS(L$53:L$318,$A$53:$A$318,"US",$C$53:$C$318,$C46)/'Shared Summary by Dept_US$'!$B$35 -> 0 | M46: =SUMIFS(M$53:M$318,$A$53:$A$318,"India",$C$53:$C$318,$C46)/'Shared Summary by Dept_US$'!$B$31+SUMIFS(M$53:M$318,$A$53:$A$318,"INDO",$C$53:$C$318,$C46)/'Shared Summary by Dept_US$'!$B$32+SUMIFS(M$53:M$318,$A$53:$A$318,"BD",$C$53:$C$318,$C46)/'Shared Summary by Dept_US$'!$B$33+SUMIFS(M$53:M$318,$A$53:$A$318,"Nepal",$C$53:$C$318,$C46)/'Shared Summary by Dept_US$'!$B$34+SUMIFS(M$53:M$318,$A$53:$A$318,"US",$C$53:$C$318,$C46)/'Shared Summary by Dept_US$'!$B$35 -> 0 | ... Q46: =SUMIFS(Q$53:Q$318,$A$53:$A$318,"India",$C$53:$C$318,$C46)/'Shared Summary by Dept_US$'!$B$31+SUMIFS(Q$53:Q$318,$A$53:$A$318,"INDO",$C$53:$C$318,$C46)/'Shared Summary by Dept_US$'!$B$32+SUMIFS(Q$53:Q$318,$A$53:$A$318,"BD",$C$53:$C$318,$C46)/'Shared Summary by Dept_US$'!$B$33+SUMIFS(Q$53:Q$318,$A$53:$A$318,"Nepal",$C$53:$C$318,$C46)/'Shared Summary by Dept_US$'!$B$34+SUMIFS(Q$53:Q$318,$A$53:$A$318,"US",$C$53:$C$318,$C46)/'Shared Summary by Dept_US$'!$B$35 -> 0
A47: Digital product | B47: Other Staff expenses | C47: Staff welfare | E47: =SUM(F47:Q47) -> 0 | F47: =SUMIFS(F$53:F$318,$A$53:$A$318,"India",$C$53:$C$318,$C47)/'Shared Summary by Dept_US$'!$B$31+SUMIFS(F$53:F$318,$A$53:$A$318,"INDO",$C$53:$C$318,$C47)/'Shared Summary by Dept_US$'!$B$32+SUMIFS(F$53:F$318,$A$53:$A$318,"BD",$C$53:$C$318,$C47)/'Shared Summary by Dept_US$'!$B$33+SUMIFS(F$53:F$318,$A$53:$A$318,"Nepal",$C$53:$C$318,$C47)/'Shared Summary by Dept_US$'!$B$34+SUMIFS(F$53:F$318,$A$53:$A$318,"US",$C$53:$C$318,$C47)/'Shared Summary by Dept_US$'!$B$35 -> 0 | G47: =SUMIFS(G$53:G$318,$A$53:$A$318,"India",$C$53:$C$318,$C47)/'Shared Summary by Dept_US$'!$B$31+SUMIFS(G$53:G$318,$A$53:$A$318,"INDO",$C$53:$C$318,$C47)/'Shared Summary by Dept_US$'!$B$32+SUMIFS(G$53:G$318,$A$53:$A$318,"BD",$C$53:$C$318,$C47)/'Shared Summary by Dept_US$'!$B$33+SUMIFS(G$53:G$318,$A$53:$A$318,"Nepal",$C$53:$C$318,$C47)/'Shared Summary by Dept_US$'!$B$34+SUMIFS(G$53:G$318,$A$53:$A$318,"US",$C$53:$C$318,$C47)/'Shared Summary by Dept_US$'!$B$35 -> 0 | H47: =SUMIFS(H$53:H$318,$A$53:$A$318,"India",$C$53:$C$318,$C47)/'Shared Summary by Dept_US$'!$B$31+SUMIFS(H$53:H$318,$A$53:$A$318,"INDO",$C$53:$C$318,$C47)/'Shared Summary by Dept_US$'!$B$32+SUMIFS(H$53:H$318,$A$53:$A$318,"BD",$C$53:$C$318,$C47)/'Shared Summary by Dept_US$'!$B$33+SUMIFS(H$53:H$318,$A$53:$A$318,"Nepal",$C$53:$C$318,$C47)/'Shared Summary by Dept_US$'!$B$34+SUMIFS(H$53:H$318,$A$53:$A$318,"US",$C$53:$C$318,$C47)/'Shared Summary by Dept_US$'!$B$35 -> 0 | I47: =SUMIFS(I$53:I$318,$A$53:$A$318,"India",$C$53:$C$318,$C47)/'Shared Summary by Dept_US$'!$B$31+SUMIFS(I$53:I$318,$A$53:$A$318,"INDO",$C$53:$C$318,$C47)/'Shared Summary by Dept_US$'!$B$32+SUMIFS(I$53:I$318,$A$53:$A$318,"BD",$C$53:$C$318,$C47)/'Shared Summary by Dept_US$'!$B$33+SUMIFS(I$53:I$318,$A$53:$A$318,"Nepal",$C$53:$C$318,$C47)/'Shared Summary by Dept_US$'!$B$34+SUMIFS(I$53:I$318,$A$53:$A$318,"US",$C$53:$C$318,$C47)/'Shared Summary by Dept_US$'!$B$35 -> 0 | J47: =SUMIFS(J$53:J$318,$A$53:$A$318,"India",$C$53:$C$318,$C47)/'Shared Summary by Dept_US$'!$B$31+SUMIFS(J$53:J$318,$A$53:$A$318,"INDO",$C$53:$C$318,$C47)/'Shared Summary by Dept_US$'!$B$32+SUMIFS(J$53:J$318,$A$53:$A$318,"BD",$C$53:$C$318,$C47)/'Shared Summary by Dept_US$'!$B$33+SUMIFS(J$53:J$318,$A$53:$A$318,"Nepal",$C$53:$C$318,$C47)/'Shared Summary by Dept_US$'!$B$34+SUMIFS(J$53:J$318,$A$53:$A$318,"US",$C$53:$C$318,$C47)/'Shared Summary by Dept_US$'!$B$35 -> 0 | K47: =SUMIFS(K$53:K$318,$A$53:$A$318,"India",$C$53:$C$318,$C47)/'Shared Summary by Dept_US$'!$B$31+SUMIFS(K$53:K$318,$A$53:$A$318,"INDO",$C$53:$C$318,$C47)/'Shared Summary by Dept_US$'!$B$32+SUMIFS(K$53:K$318,$A$53:$A$318,"BD",$C$53:$C$318,$C47)/'Shared Summary by Dept_US$'!$B$33+SUMIFS(K$53:K$318,$A$53:$A$318,"Nepal",$C$53:$C$318,$C47)/'Shared Summary by Dept_US$'!$B$34+SUMIFS(K$53:K$318,$A$53:$A$318,"US",$C$53:$C$318,$C47)/'Shared Summary by Dept_US$'!$B$35 -> 0 | L47: =SUMIFS(L$53:L$318,$A$53:$A$318,"India",$C$53:$C$318,$C47)/'Shared Summary by Dept_US$'!$B$31+SUMIFS(L$53:L$318,$A$53:$A$318,"INDO",$C$53:$C$318,$C47)/'Shared Summary by Dept_US$'!$B$32+SUMIFS(L$53:L$318,$A$53:$A$318,"BD",$C$53:$C$318,$C47)/'Shared Summary by Dept_US$'!$B$33+SUMIFS(L$53:L$318,$A$53:$A$318,"Nepal",$C$53:$C$318,$C47)/'Shared Summary by Dept_US$'!$B$34+SUMIFS(L$53:L$318,$A$53:$A$318,"US",$C$53:$C$318,$C47)/'Shared Summary by Dept_US$'!$B$35 -> 0 | M47: =SUMIFS(M$53:M$318,$A$53:$A$318,"India",$C$53:$C$318,$C47)/'Shared Summary by Dept_US$'!$B$31+SUMIFS(M$53:M$318,$A$53:$A$318,"INDO",$C$53:$C$318,$C47)/'Shared Summary by Dept_US$'!$B$32+SUMIFS(M$53:M$318,$A$53:$A$318,"BD",$C$53:$C$318,$C47)/'Shared Summary by Dept_US$'!$B$33+SUMIFS(M$53:M$318,$A$53:$A$318,"Nepal",$C$53:$C$318,$C47)/'Shared Summary by Dept_US$'!$B$34+SUMIFS(M$53:M$318,$A$53:$A$318,"US",$C$53:$C$318,$C47)/'Shared Summary by Dept_US$'!$B$35 -> 0 | ... Q47: =SUMIFS(Q$53:Q$318,$A$53:$A$318,"India",$C$53:$C$318,$C47)/'Shared Summary by Dept_US$'!$B$31+SUMIFS(Q$53:Q$318,$A$53:$A$318,"INDO",$C$53:$C$318,$C47)/'Shared Summary by Dept_US$'!$B$32+SUMIFS(Q$53:Q$318,$A$53:$A$318,"BD",$C$53:$C$318,$C47)/'Shared Summary by Dept_US$'!$B$33+SUMIFS(Q$53:Q$318,$A$53:$A$318,"Nepal",$C$53:$C$318,$C47)/'Shared Summary by Dept_US$'!$B$34+SUMIFS(Q$53:Q$318,$A$53:$A$318,"US",$C$53:$C$318,$C47)/'Shared Summary by Dept_US$'!$B$35 -> 0
E48: =SUM(F48:Q48) -> 0 | F48: =SUMIFS(F$53:F$318,$A$53:$A$318,"India",$C$53:$C$318,$C48)/'Shared Summary by Dept_US$'!$B$31+SUMIFS(F$53:F$318,$A$53:$A$318,"INDO",$C$53:$C$318,$C48)/'Shared Summary by Dept_US$'!$B$32+SUMIFS(F$53:F$318,$A$53:$A$318,"BD",$C$53:$C$318,$C48)/'Shared Summary by Dept_US$'!$B$33+SUMIFS(F$53:F$318,$A$53:$A$318,"Nepal",$C$53:$C$318,$C48)/'Shared Summary by Dept_US$'!$B$34+SUMIFS(F$53:F$318,$A$53:$A$318,"US",$C$53:$C$318,$C48)/'Shared Summary by Dept_US$'!$B$35 -> 0 | G48: =SUMIFS(G$53:G$318,$A$53:$A$318,"India",$C$53:$C$318,$C48)/'Shared Summary by Dept_US$'!$B$31+SUMIFS(G$53:G$318,$A$53:$A$318,"INDO",$C$53:$C$318,$C48)/'Shared Summary by Dept_US$'!$B$32+SUMIFS(G$53:G$318,$A$53:$A$318,"BD",$C$53:$C$318,$C48)/'Shared Summary by Dept_US$'!$B$33+SUMIFS(G$53:G$318,$A$53:$A$318,"Nepal",$C$53:$C$318,$C48)/'Shared Summary by Dept_US$'!$B$34+SUMIFS(G$53:G$318,$A$53:$A$318,"US",$C$53:$C$318,$C48)/'Shared Summary by Dept_US$'!$B$35 -> 0 | H48: =SUMIFS(H$53:H$318,$A$53:$A$318,"India",$C$53:$C$318,$C48)/'Shared Summary by Dept_US$'!$B$31+SUMIFS(H$53:H$318,$A$53:$A$318,"INDO",$C$53:$C$318,$C48)/'Shared Summary by Dept_US$'!$B$32+SUMIFS(H$53:H$318,$A$53:$A$318,"BD",$C$53:$C$318,$C48)/'Shared Summary by Dept_US$'!$B$33+SUMIFS(H$53:H$318,$A$53:$A$318,"Nepal",$C$53:$C$318,$C48)/'Shared Summary by Dept_US$'!$B$34+SUMIFS(H$53:H$318,$A$53:$A$318,"US",$C$53:$C$318,$C48)/'Shared Summary by Dept_US$'!$B$35 -> 0 | I48: =SUMIFS(I$53:I$318,$A$53:$A$318,"India",$C$53:$C$318,$C48)/'Shared Summary by Dept_US$'!$B$31+SUMIFS(I$53:I$318,$A$53:$A$318,"INDO",$C$53:$C$318,$C48)/'Shared Summary by Dept_US$'!$B$32+SUMIFS(I$53:I$318,$A$53:$A$318,"BD",$C$53:$C$318,$C48)/'Shared Summary by Dept_US$'!$B$33+SUMIFS(I$53:I$318,$A$53:$A$318,"Nepal",$C$53:$C$318,$C48)/'Shared Summary by Dept_US$'!$B$34+SUMIFS(I$53:I$318,$A$53:$A$318,"US",$C$53:$C$318,$C48)/'Shared Summary by Dept_US$'!$B$35 -> 0 | J48: =SUMIFS(J$53:J$318,$A$53:$A$318,"India",$C$53:$C$318,$C48)/'Shared Summary by Dept_US$'!$B$31+SUMIFS(J$53:J$318,$A$53:$A$318,"INDO",$C$53:$C$318,$C48)/'Shared Summary by Dept_US$'!$B$32+SUMIFS(J$53:J$318,$A$53:$A$318,"BD",$C$53:$C$318,$C48)/'Shared Summary by Dept_US$'!$B$33+SUMIFS(J$53:J$318,$A$53:$A$318,"Nepal",$C$53:$C$318,$C48)/'Shared Summary by Dept_US$'!$B$34+SUMIFS(J$53:J$318,$A$53:$A$318,"US",$C$53:$C$318,$C48)/'Shared Summary by Dept_US$'!$B$35 -> 0 | K48: =SUMIFS(K$53:K$318,$A$53:$A$318,"India",$C$53:$C$318,$C48)/'Shared Summary by Dept_US$'!$B$31+SUMIFS(K$53:K$318,$A$53:$A$318,"INDO",$C$53:$C$318,$C48)/'Shared Summary by Dept_US$'!$B$32+SUMIFS(K$53:K$318,$A$53:$A$318,"BD",$C$53:$C$318,$C48)/'Shared Summary by Dept_US$'!$B$33+SUMIFS(K$53:K$318,$A$53:$A$318,"Nepal",$C$53:$C$318,$C48)/'Shared Summary by Dept_US$'!$B$34+SUMIFS(K$53:K$318,$A$53:$A$318,"US",$C$53:$C$318,$C48)/'Shared Summary by Dept_US$'!$B$35 -> 0 | L48: =SUMIFS(L$53:L$318,$A$53:$A$318,"India",$C$53:$C$318,$C48)/'Shared Summary by Dept_US$'!$B$31+SUMIFS(L$53:L$318,$A$53:$A$318,"INDO",$C$53:$C$318,$C48)/'Shared Summary by Dept_US$'!$B$32+SUMIFS(L$53:L$318,$A$53:$A$318,"BD",$C$53:$C$318,$C48)/'Shared Summary by Dept_US$'!$B$33+SUMIFS(L$53:L$318,$A$53:$A$318,"Nepal",$C$53:$C$318,$C48)/'Shared Summary by Dept_US$'!$B$34+SUMIFS(L$53:L$318,$A$53:$A$318,"US",$C$53:$C$318,$C48)/'Shared Summary by Dept_US$'!$B$35 -> 0 | M48: =SUMIFS(M$53:M$318,$A$53:$A$318,"India",$C$53:$C$318,$C48)/'Shared Summary by Dept_US$'!$B$31+SUMIFS(M$53:M$318,$A$53:$A$318,"INDO",$C$53:$C$318,$C48)/'Shared Summary by Dept_US$'!$B$32+SUMIFS(M$53:M$318,$A$53:$A$318,"BD",$C$53:$C$318,$C48)/'Shared Summary by Dept_US$'!$B$33+SUMIFS(M$53:M$318,$A$53:$A$318,"Nepal",$C$53:$C$318,$C48)/'Shared Summary by Dept_US$'!$B$34+SUMIFS(M$53:M$318,$A$53:$A$318,"US",$C$53:$C$318,$C48)/'Shared Summary by Dept_US$'!$B$35 -> 0 | ... Q48: =SUMIFS(Q$53:Q$318,$A$53:$A$318,"India",$C$53:$C$318,$C48)/'Shared Summary by Dept_US$'!$B$31+SUMIFS(Q$53:Q$318,$A$53:$A$318,"INDO",$C$53:$C$318,$C48)/'Shared Summary by Dept_US$'!$B$32+SUMIFS(Q$53:Q$318,$A$53:$A$318,"BD",$C$53:$C$318,$C48)/'Shared Summary by Dept_US$'!$B$33+SUMIFS(Q$53:Q$318,$A$53:$A$318,"Nepal",$C$53:$C$318,$C48)/'Shared Summary by Dept_US$'!$B$34+SUMIFS(Q$53:Q$318,$A$53:$A$318,"US",$C$53:$C$318,$C48)/'Shared Summary by Dept_US$'!$B$35 -> 0
C49: Total | E49: =SUM(E3:E48) -> 2182266.5 | F49: =SUM(F3:F48) -> 160226.86 | G49: =SUM(G3:G48) -> 162618.11 | H49: =SUM(H3:H48) -> 192222.15 | I49: =SUM(I3:I48) -> 202430.58 | J49: =SUM(J3:J48) -> 190849.7 | K49: =SUM(K3:K48) -> 186137.21 | L49: =SUM(L3:L48) -> 183599.45 | ... Q49: =SUM(Q3:Q48) -> 178122.09
C50: Check | E50: =E49-'Shared Summary by Dept_US$'!C21 -> 0 | F50: =F49-'Shared Summary by Dept_US$'!D21 -> 0 | G50: =G49-'Shared Summary by Dept_US$'!E21 -> 0 | H50: =H49-'Shared Summary by Dept_US$'!F21 -> 0 | I50: =I49-'Shared Summary by Dept_US$'!G21 -> 0 | J50: =J49-'Shared Summary by Dept_US$'!H21 -> 0 | K50: =K49-'Shared Summary by Dept_US$'!I21 -> 0 | L50: =L49-'Shared Summary by Dept_US$'!J21 -> 0 | ... Q50: =Q49-'Shared Summary by Dept_US$'!O21 -> 0
B52: =IFERROR(__xludf.DUMMYFUNCTION("query({'India- Tech Build Out'!F1:U23;'India- Tech Build Out'!F26:U46;'India- Tech Build Out'!F49:U69;'India- Tech Build Out'!F72:U91;'India- Tech Build Out'!F95:U114;'INDO- Tech Build-Out'!F3:U22;'INDO- Tech Build-Out'!F26:U45;'BD- Tech Build-Out'!F3:U22"&";'BD- Tech Build-Out'!F26:U45;'India- Tech Build Out'!F117:U118;'Nepal- Tech Build Out'!F3:U22;'US- Tech Build Out'!F3:U22;'US- Tech Build Out'!F26:U45;'India- Tech Build Out'!F122:U141},""Select*"",1)"),"Parent account") -> Parent account | C52: =IFERROR(__xludf.DUMMYFUNCTION("""COMPUTED_VALUE"""),"GL Description") -> GL Description | D52: =IFERROR(__xludf.DUMMYFUNCTION("""COMPUTED_VALUE"""),"Ledger Code") -> Ledger Code | E52: =IFERROR(__xludf.DUMMYFUNCTION("""COMPUTED_VALUE"""),"Total CY-2026") -> Total CY-2026 | F52: =IFERROR(__xludf.DUMMYFUNCTION("""COMPUTED_VALUE"""),"Jan-2026") -> Jan-2026 | G52: =IFERROR(__xludf.DUMMYFUNCTION("""COMPUTED_VALUE"""),"Feb-2026") -> Feb-2026 | H52: =IFERROR(__xludf.DUMMYFUNCTION("""COMPUTED_VALUE"""),"Mar-2026") -> Mar-2026 | I52: =IFERROR(__xludf.DUMMYFUNCTION("""COMPUTED_VALUE"""),"Apr-2026") -> Apr-2026 | J52: =IFERROR(__xludf.DUMMYFUNCTION("""COMPUTED_VALUE"""),"May-2026") -> May-2026 | K52: =IFERROR(__xludf.DUMMYFUNCTION("""COMPUTED_VALUE"""),"Jun-2026") -> Jun-2026 | L52: =IFERROR(__xludf.DUMMYFUNCTION("""COMPUTED_VALUE"""),"Jul-2026") -> Jul-2026 | M52: =IFERROR(__xludf.DUMMYFUNCTION("""COMPUTED_VALUE"""),"Aug-2026") -> Aug-2026 | N52: =IFERROR(__xludf.DUMMYFUNCTION("""COMPUTED_VALUE"""),"Sep-2026") -> Sep-2026 | O52: =IFERROR(__xludf.DUMMYFUNCTION("""COMPUTED_VALUE"""),"Oct-2026") -> Oct-2026 | P52: =IFERROR(__xludf.DUMMYFUNCTION("""COMPUTED_VALUE"""),"Nov-2026") -> Nov-2026 | Q52: =IFERROR(__xludf.DUMMYFUNCTION("""COMPUTED_VALUE"""),"Dec-2026") -> Dec-2026 | S52: Total-US$ CY-2026
A54: India | B54: =IFERROR(__xludf.DUMMYFUNCTION("""COMPUTED_VALUE"""),"Salaries and Wages") -> Salaries and Wages | C54: =IFERROR(__xludf.DUMMYFUNCTION("""COMPUTED_VALUE"""),"Salaries and Wages") -> Salaries and Wages | E54: =IFERROR(__xludf.DUMMYFUNCTION("""COMPUTED_VALUE"""),451493.679) -> 451493.68 | F54: =IFERROR(__xludf.DUMMYFUNCTION("""COMPUTED_VALUE"""),150497.893) -> 150497.89 | G54: =IFERROR(__xludf.DUMMYFUNCTION("""COMPUTED_VALUE"""),150497.893) -> 150497.89 | H54: =IFERROR(__xludf.DUMMYFUNCTION("""COMPUTED_VALUE"""),150497.893) -> 150497.89 | I54: =IFERROR(__xludf.DUMMYFUNCTION("""COMPUTED_VALUE"""),0) -> 0 | J54: =IFERROR(__xludf.DUMMYFUNCTION("""COMPUTED_VALUE"""),0) -> 0 | K54: =IFERROR(__xludf.DUMMYFUNCTION("""COMPUTED_VALUE"""),0) -> 0 | L54: =IFERROR(__xludf.DUMMYFUNCTION("""COMPUTED_VALUE"""),0) -> 0 | M54: =IFERROR(__xludf.DUMMYFUNCTION("""COMPUTED_VALUE"""),0) -> 0 | N54: =IFERROR(__xludf.DUMMYFUNCTION("""COMPUTED_VALUE"""),0) -> 0 | O54: =IFERROR(__xludf.DUMMYFUNCTION("""COMPUTED_VALUE"""),0) -> 0 | P54: =IFERROR(__xludf.DUMMYFUNCTION("""COMPUTED_VALUE"""),0) -> 0 | Q54: =IFERROR(__xludf.DUMMYFUNCTION("""COMPUTED_VALUE"""),0) -> 0 | S54: =_xludf.ifs(A54="INDIA",E54/'Shared Summary by Dept_US$'!$B$31,A54="INDO",E54/'Shared Summary by Dept_US$'!$B$32,A54="BD",E54/'Shared Summary by Dept_US$'!$B$33,A54="Nepal",E54/'Shared Summary by Dept_US$'!$B$34,A54="US",E54/'Shared Summary by Dept_US$'!$B$35) -> #NAME? | T54: INDIA-Digital Product-Product Management
A55: India | B55: =IFERROR(__xludf.DUMMYFUNCTION("""COMPUTED_VALUE"""),"Health and Retirement Benefits") -> Health and Retirement Benefits | C55: =IFERROR(__xludf.DUMMYFUNCTION("""COMPUTED_VALUE"""),"Gratuity & Bonus") -> Gratuity & Bonus | E55: =IFERROR(__xludf.DUMMYFUNCTION("""COMPUTED_VALUE"""),0) -> 0 | F55: =IFERROR(__xludf.DUMMYFUNCTION("""COMPUTED_VALUE"""),0) -> 0 | G55: =IFERROR(__xludf.DUMMYFUNCTION("""COMPUTED_VALUE"""),0) -> 0 | H55: =IFERROR(__xludf.DUMMYFUNCTION("""COMPUTED_VALUE"""),0) -> 0 | I55: =IFERROR(__xludf.DUMMYFUNCTION("""COMPUTED_VALUE"""),0) -> 0 | J55: =IFERROR(__xludf.DUMMYFUNCTION("""COMPUTED_VALUE"""),0) -> 0 | K55: =IFERROR(__xludf.DUMMYFUNCTION("""COMPUTED_VALUE"""),0) -> 0 | L55: =IFERROR(__xludf.DUMMYFUNCTION("""COMPUTED_VALUE"""),0) -> 0 | ... Q55: =IFERROR(__xludf.DUMMYFUNCTION("""COMPUTED_VALUE"""),0) -> 0 | S55: =_xludf.ifs(A55="INDIA",E55/'Shared Summary by Dept_US$'!$B$31,A55="INDO",E55/'Shared Summary by Dept_US$'!$B$32,A55="BD",E55/'Shared Summary by Dept_US$'!$B$33,A55="Nepal",E55/'Shared Summary by Dept_US$'!$B$34,A55="US",E55/'Shared Summary by Dept_US$'!$B$35) -> #NAME? | T55: INDIA-Digital Product-Product Management
A56: India | B56: =IFERROR(__xludf.DUMMYFUNCTION("""COMPUTED_VALUE"""),"Other Staff Expenses") -> Other Staff Expenses | C56: =IFERROR(__xludf.DUMMYFUNCTION("""COMPUTED_VALUE"""),"Staff Training, Learning & Development Exp") -> Staff Training, Learning & Development Exp | D56: =IFERROR(__xludf.DUMMYFUNCTION("""COMPUTED_VALUE"""),91302) -> 91302 | E56: =IFERROR(__xludf.DUMMYFUNCTION("""COMPUTED_VALUE"""),0) -> 0 | F56: =IFERROR(__xludf.DUMMYFUNCTION("""COMPUTED_VALUE"""),0) -> 0 | G56: =IFERROR(__xludf.DUMMYFUNCTION("""COMPUTED_VALUE"""),0) -> 0 | H56: =IFERROR(__xludf.DUMMYFUNCTION("""COMPUTED_VALUE"""),0) -> 0 | I56: =IFERROR(__xludf.DUMMYFUNCTION("""COMPUTED_VALUE"""),0) -> 0 | J56: =IFERROR(__xludf.DUMMYFUNCTION("""COMPUTED_VALUE"""),0) -> 0 | K56: =IFERROR(__xludf.DUMMYFUNCTION("""COMPUTED_VALUE"""),0) -> 0 | L56: =IFERROR(__xludf.DUMMYFUNCTION("""COMPUTED_VALUE"""),0) -> 0 | ... Q56: =IFERROR(__xludf.DUMMYFUNCTION("""COMPUTED_VALUE"""),0) -> 0 | S56: =_xludf.ifs(A56="INDIA",E56/'Shared Summary by Dept_US$'!$B$31,A56="INDO",E56/'Shared Summary by Dept_US$'!$B$32,A56="BD",E56/'Shared Summary by Dept_US$'!$B$33,A56="Nepal",E56/'Shared Summary by Dept_US$'!$B$34,A56="US",E56/'Shared Summary by Dept_US$'!$B$35) -> #NAME? | T56: INDIA-Digital Product-Product Management
A57: India | B57: =IFERROR(__xludf.DUMMYFUNCTION("""COMPUTED_VALUE"""),"Resource Persons") -> Resource Persons | C57: =IFERROR(__xludf.DUMMYFUNCTION("""COMPUTED_VALUE"""),"Program Resource Consultant (EHA)") -> Program Resource Consultant (EHA) | D57: =IFERROR(__xludf.DUMMYFUNCTION("""COMPUTED_VALUE"""),92101) -> 92101 | E57: =IFERROR(__xludf.DUMMYFUNCTION("""COMPUTED_VALUE"""),0) -> 0 | F57: =IFERROR(__xludf.DUMMYFUNCTION("""COMPUTED_VALUE"""),0) -> 0 | G57: =IFERROR(__xludf.DUMMYFUNCTION("""COMPUTED_VALUE"""),0) -> 0 | H57: =IFERROR(__xludf.DUMMYFUNCTION("""COMPUTED_VALUE"""),0) -> 0 | I57: =IFERROR(__xludf.DUMMYFUNCTION("""COMPUTED_VALUE"""),0) -> 0 | J57: =IFERROR(__xludf.DUMMYFUNCTION("""COMPUTED_VALUE"""),0) -> 0 | K57: =IFERROR(__xludf.DUMMYFUNCTION("""COMPUTED_VALUE"""),0) -> 0 | L57: =IFERROR(__xludf.DUMMYFUNCTION("""COMPUTED_VALUE"""),0) -> 0 | ... Q57: =IFERROR(__xludf.DUMMYFUNCTION("""COMPUTED_VALUE"""),0) -> 0 | S57: =_xludf.ifs(A57="INDIA",E57/'Shared Summary by Dept_US$'!$B$31,A57="INDO",E57/'Shared Summary by Dept_US$'!$B$32,A57="BD",E57/'Shared Summary by Dept_US$'!$B$33,A57="Nepal",E57/'Shared Summary by Dept_US$'!$B$34,A57="US",E57/'Shared Summary by Dept_US$'!$B$35) -> #NAME? | T57: INDIA-Digital Product-Product Management
A58: India | B58: =IFERROR(__xludf.DUMMYFUNCTION("""COMPUTED_VALUE"""),"Travel & Lodging Expenses") -> Travel & Lodging Expenses | C58: =IFERROR(__xludf.DUMMYFUNCTION("""COMPUTED_VALUE"""),"Hotel Accomodation") -> Hotel Accomodation | D58: =IFERROR(__xludf.DUMMYFUNCTION("""COMPUTED_VALUE"""),93101) -> 93101 | E58: =IFERROR(__xludf.DUMMYFUNCTION("""COMPUTED_VALUE"""),0) -> 0 | F58: =IFERROR(__xludf.DUMMYFUNCTION("""COMPUTED_VALUE"""),0) -> 0 | G58: =IFERROR(__xludf.DUMMYFUNCTION("""COMPUTED_VALUE"""),0) -> 0 | H58: =IFERROR(__xludf.DUMMYFUNCTION("""COMPUTED_VALUE"""),0) -> 0 | I58: =IFERROR(__xludf.DUMMYFUNCTION("""COMPUTED_VALUE"""),0) -> 0 | J58: =IFERROR(__xludf.DUMMYFUNCTION("""COMPUTED_VALUE"""),0) -> 0 | K58: =IFERROR(__xludf.DUMMYFUNCTION("""COMPUTED_VALUE"""),0) -> 0 | L58: =IFERROR(__xludf.DUMMYFUNCTION("""COMPUTED_VALUE"""),0) -> 0 | ... Q58: =IFERROR(__xludf.DUMMYFUNCTION("""COMPUTED_VALUE"""),0) -> 0 | S58: =_xludf.ifs(A58="INDIA",E58/'Shared Summary by Dept_US$'!$B$31,A58="INDO",E58/'Shared Summary by Dept_US$'!$B$32,A58="BD",E58/'Shared Summary by Dept_US$'!$B$33,A58="Nepal",E58/'Shared Summary by Dept_US$'!$B$34,A58="US",E58/'Shared Summary by Dept_US$'!$B$35) -> #NAME? | T58: INDIA-Digital Product-Product Management
A59: India | B59: =IFERROR(__xludf.DUMMYFUNCTION("""COMPUTED_VALUE"""),"Travel & Lodging Expenses") -> Travel & Lodging Expenses | C59: =IFERROR(__xludf.DUMMYFUNCTION("""COMPUTED_VALUE"""),"Food Expenses") -> Food Expenses | D59: =IFERROR(__xludf.DUMMYFUNCTION("""COMPUTED_VALUE"""),93102) -> 93102 | E59: =IFERROR(__xludf.DUMMYFUNCTION("""COMPUTED_VALUE"""),0) -> 0 | F59: =IFERROR(__xludf.DUMMYFUNCTION("""COMPUTED_VALUE"""),0) -> 0 | G59: =IFERROR(__xludf.DUMMYFUNCTION("""COMPUTED_VALUE"""),0) -> 0 | H59: =IFERROR(__xludf.DUMMYFUNCTION("""COMPUTED_VALUE"""),0) -> 0 | I59: =IFERROR(__xludf.DUMMYFUNCTION("""COMPUTED_VALUE"""),0) -> 0 | J59: =IFERROR(__xludf.DUMMYFUNCTION("""COMPUTED_VALUE"""),0) -> 0 | K59: =IFERROR(__xludf.DUMMYFUNCTION("""COMPUTED_VALUE"""),0) -> 0 | L59: =IFERROR(__xludf.DUMMYFUNCTION("""COMPUTED_VALUE"""),0) -> 0 | ... Q59: =IFERROR(__xludf.DUMMYFUNCTION("""COMPUTED_VALUE"""),0) -> 0 | S59: =_xludf.ifs(A59="INDIA",E59/'Shared Summary by Dept_US$'!$B$31,A59="INDO",E59/'Shared Summary by Dept_US$'!$B$32,A59="BD",E59/'Shared Summary by Dept_US$'!$B$33,A59="Nepal",E59/'Shared Summary by Dept_US$'!$B$34,A59="US",E59/'Shared Summary by Dept_US$'!$B$35) -> #NAME? | T59: INDIA-Digital Product-Product Management
A60: India | B60: =IFERROR(__xludf.DUMMYFUNCTION("""COMPUTED_VALUE"""),"Travel & Lodging Expenses") -> Travel & Lodging Expenses | C60: =IFERROR(__xludf.DUMMYFUNCTION("""COMPUTED_VALUE"""),"Air fare") -> Air fare | D60: =IFERROR(__xludf.DUMMYFUNCTION("""COMPUTED_VALUE"""),93103) -> 93103 | E60: =IFERROR(__xludf.DUMMYFUNCTION("""COMPUTED_VALUE"""),0) -> 0 | F60: =IFERROR(__xludf.DUMMYFUNCTION("""COMPUTED_VALUE"""),0) -> 0 | G60: =IFERROR(__xludf.DUMMYFUNCTION("""COMPUTED_VALUE"""),0) -> 0 | H60: =IFERROR(__xludf.DUMMYFUNCTION("""COMPUTED_VALUE"""),0) -> 0 | I60: =IFERROR(__xludf.DUMMYFUNCTION("""COMPUTED_VALUE"""),0) -> 0 | J60: =IFERROR(__xludf.DUMMYFUNCTION("""COMPUTED_VALUE"""),0) -> 0 | K60: =IFERROR(__xludf.DUMMYFUNCTION("""COMPUTED_VALUE"""),0) -> 0 | L60: =IFERROR(__xludf.DUMMYFUNCTION("""COMPUTED_VALUE"""),0) -> 0 | ... Q60: =IFERROR(__xludf.DUMMYFUNCTION("""COMPUTED_VALUE"""),0) -> 0 | S60: =_xludf.ifs(A60="INDIA",E60/'Shared Summary by Dept_US$'!$B$31,A60="INDO",E60/'Shared Summary by Dept_US$'!$B$32,A60="BD",E60/'Shared Summary by Dept_US$'!$B$33,A60="Nepal",E60/'Shared Summary by Dept_US$'!$B$34,A60="US",E60/'Shared Summary by Dept_US$'!$B$35) -> #NAME? | T60: INDIA-Digital Product-Product Management
A61: India | B61: =IFERROR(__xludf.DUMMYFUNCTION("""COMPUTED_VALUE"""),"Travel & Lodging Expenses") -> Travel & Lodging Expenses | C61: =IFERROR(__xludf.DUMMYFUNCTION("""COMPUTED_VALUE"""),"Cab/Auto") -> Cab/Auto | D61: =IFERROR(__xludf.DUMMYFUNCTION("""COMPUTED_VALUE"""),93104) -> 93104 | E61: =IFERROR(__xludf.DUMMYFUNCTION("""COMPUTED_VALUE"""),0) -> 0 | F61: =IFERROR(__xludf.DUMMYFUNCTION("""COMPUTED_VALUE"""),0) -> 0 | G61: =IFERROR(__xludf.DUMMYFUNCTION("""COMPUTED_VALUE"""),0) -> 0 | H61: =IFERROR(__xludf.DUMMYFUNCTION("""COMPUTED_VALUE"""),0) -> 0 | I61: =IFERROR(__xludf.DUMMYFUNCTION("""COMPUTED_VALUE"""),0) -> 0 | J61: =IFERROR(__xludf.DUMMYFUNCTION("""COMPUTED_VALUE"""),0) -> 0 | K61: =IFERROR(__xludf.DUMMYFUNCTION("""COMPUTED_VALUE"""),0) -> 0 | L61: =IFERROR(__xludf.DUMMYFUNCTION("""COMPUTED_VALUE"""),0) -> 0 | ... Q61: =IFERROR(__xludf.DUMMYFUNCTION("""COMPUTED_VALUE"""),0) -> 0 | S61: =_xludf.ifs(A61="INDIA",E61/'Shared Summary by Dept_US$'!$B$31,A61="INDO",E61/'Shared Summary by Dept_US$'!$B$32,A61="BD",E61/'Shared Summary by Dept_US$'!$B$33,A61="Nepal",E61/'Shared Summary by Dept_US$'!$B$34,A61="US",E61/'Shared Summary by Dept_US$'!$B$35) -> #NAME? | T61: INDIA-Digital Product-Product Management
A62: India | B62: =IFERROR(__xludf.DUMMYFUNCTION("""COMPUTED_VALUE"""),"Travel & Lodging Expenses") -> Travel & Lodging Expenses | C62: =IFERROR(__xludf.DUMMYFUNCTION("""COMPUTED_VALUE"""),"Bus/Train") -> Bus/Train | D62: =IFERROR(__xludf.DUMMYFUNCTION("""COMPUTED_VALUE"""),93105) -> 93105 | E62: =IFERROR(__xludf.DUMMYFUNCTION("""COMPUTED_VALUE"""),0) -> 0 | F62: =IFERROR(__xludf.DUMMYFUNCTION("""COMPUTED_VALUE"""),0) -> 0 | G62: =IFERROR(__xludf.DUMMYFUNCTION("""COMPUTED_VALUE"""),0) -> 0 | H62: =IFERROR(__xludf.DUMMYFUNCTION("""COMPUTED_VALUE"""),0) -> 0 | I62: =IFERROR(__xludf.DUMMYFUNCTION("""COMPUTED_VALUE"""),0) -> 0 | J62: =IFERROR(__xludf.DUMMYFUNCTION("""COMPUTED_VALUE"""),0) -> 0 | K62: =IFERROR(__xludf.DUMMYFUNCTION("""COMPUTED_VALUE"""),0) -> 0 | L62: =IFERROR(__xludf.DUMMYFUNCTION("""COMPUTED_VALUE"""),0) -> 0 | ... Q62: =IFERROR(__xludf.DUMMYFUNCTION("""COMPUTED_VALUE"""),0) -> 0 | S62: =_xludf.ifs(A62="INDIA",E62/'Shared Summary by Dept_US$'!$B$31,A62="INDO",E62/'Shared Summary by Dept_US$'!$B$32,A62="BD",E62/'Shared Summary by Dept_US$'!$B$33,A62="Nepal",E62/'Shared Summary by Dept_US$'!$B$34,A62="US",E62/'Shared Summary by Dept_US$'!$B$35) -> #NAME? | T62: INDIA-Digital Product-Product Management
A63: India | B63: =IFERROR(__xludf.DUMMYFUNCTION("""COMPUTED_VALUE"""),"Travel & Lodging Expenses") -> Travel & Lodging Expenses | C63: =IFERROR(__xludf.DUMMYFUNCTION("""COMPUTED_VALUE"""),"Other incidental travel costs") -> Other incidental travel costs | D63: =IFERROR(__xludf.DUMMYFUNCTION("""COMPUTED_VALUE"""),93106) -> 93106 | E63: =IFERROR(__xludf.DUMMYFUNCTION("""COMPUTED_VALUE"""),0) -> 0 | F63: =IFERROR(__xludf.DUMMYFUNCTION("""COMPUTED_VALUE"""),0) -> 0 | G63: =IFERROR(__xludf.DUMMYFUNCTION("""COMPUTED_VALUE"""),0) -> 0 | H63: =IFERROR(__xludf.DUMMYFUNCTION("""COMPUTED_VALUE"""),0) -> 0 | I63: =IFERROR(__xludf.DUMMYFUNCTION("""COMPUTED_VALUE"""),0) -> 0 | J63: =IFERROR(__xludf.DUMMYFUNCTION("""COMPUTED_VALUE"""),0) -> 0 | K63: =IFERROR(__xludf.DUMMYFUNCTION("""COMPUTED_VALUE"""),0) -> 0 | L63: =IFERROR(__xludf.DUMMYFUNCTION("""COMPUTED_VALUE"""),0) -> 0 | ... Q63: =IFERROR(__xludf.DUMMYFUNCTION("""COMPUTED_VALUE"""),0) -> 0 | S63: =_xludf.ifs(A63="INDIA",E63/'Shared Summary by Dept_US$'!$B$31,A63="INDO",E63/'Shared Summary by Dept_US$'!$B$32,A63="BD",E63/'Shared Summary by Dept_US$'!$B$33,A63="Nepal",E63/'Shared Summary by Dept_US$'!$B$34,A63="US",E63/'Shared Summary by Dept_US$'!$B$35) -> #NAME? | T63: INDIA-Digital Product-Product Management
A64: India | B64: =IFERROR(__xludf.DUMMYFUNCTION("""COMPUTED_VALUE"""),"Supplies & Printing Costs") -> Supplies & Printing Costs | C64: =IFERROR(__xludf.DUMMYFUNCTION("""COMPUTED_VALUE"""),"Other Direct Expenses") -> Other Direct Expenses | D64: =IFERROR(__xludf.DUMMYFUNCTION("""COMPUTED_VALUE"""),93201) -> 93201 | E64: =IFERROR(__xludf.DUMMYFUNCTION("""COMPUTED_VALUE"""),0) -> 0 | S64: =_xludf.ifs(A64="INDIA",E64/'Shared Summary by Dept_US$'!$B$31,A64="INDO",E64/'Shared Summary by Dept_US$'!$B$32,A64="BD",E64/'Shared Summary by Dept_US$'!$B$33,A64="Nepal",E64/'Shared Summary by Dept_US$'!$B$34,A64="US",E64/'Shared Summary by Dept_US$'!$B$35) -> #NAME? | T64: INDIA-Digital Product-Product Management
A65: India | B65: =IFERROR(__xludf.DUMMYFUNCTION("""COMPUTED_VALUE"""),"Supplies & Printing Costs") -> Supplies & Printing Costs | C65: =IFERROR(__xludf.DUMMYFUNCTION("""COMPUTED_VALUE"""),"Printing expenses") -> Printing expenses | D65: =IFERROR(__xludf.DUMMYFUNCTION("""COMPUTED_VALUE"""),93204) -> 93204 | E65: =IFERROR(__xludf.DUMMYFUNCTION("""COMPUTED_VALUE"""),0) -> 0 | S65: =_xludf.ifs(A65="INDIA",E65/'Shared Summary by Dept_US$'!$B$31,A65="INDO",E65/'Shared Summary by Dept_US$'!$B$32,A65="BD",E65/'Shared Summary by Dept_US$'!$B$33,A65="Nepal",E65/'Shared Summary by Dept_US$'!$B$34,A65="US",E65/'Shared Summary by Dept_US$'!$B$35) -> #NAME? | T65: INDIA-Digital Product-Product Management
A66: India | B66: =IFERROR(__xludf.DUMMYFUNCTION("""COMPUTED_VALUE"""),"Communication Cost") -> Communication Cost | C66: =IFERROR(__xludf.DUMMYFUNCTION("""COMPUTED_VALUE"""),"Internet Expenses") -> Internet Expenses | D66: =IFERROR(__xludf.DUMMYFUNCTION("""COMPUTED_VALUE"""),93301) -> 93301 | E66: =IFERROR(__xludf.DUMMYFUNCTION("""COMPUTED_VALUE"""),0) -> 0 | S66: =_xludf.ifs(A66="INDIA",E66/'Shared Summary by Dept_US$'!$B$31,A66="INDO",E66/'Shared Summary by Dept_US$'!$B$32,A66="BD",E66/'Shared Summary by Dept_US$'!$B$33,A66="Nepal",E66/'Shared Summary by Dept_US$'!$B$34,A66="US",E66/'Shared Summary by Dept_US$'!$B$35) -> #NAME? | T66: INDIA-Digital Product-Product Management
A67: India | B67: =IFERROR(__xludf.DUMMYFUNCTION("""COMPUTED_VALUE"""),"Communication Cost") -> Communication Cost | C67: =IFERROR(__xludf.DUMMYFUNCTION("""COMPUTED_VALUE"""),"Postage & Courier Expenses") -> Postage & Courier Expenses | D67: =IFERROR(__xludf.DUMMYFUNCTION("""COMPUTED_VALUE"""),93302) -> 93302 | E67: =IFERROR(__xludf.DUMMYFUNCTION("""COMPUTED_VALUE"""),0) -> 0 | S67: =_xludf.ifs(A67="INDIA",E67/'Shared Summary by Dept_US$'!$B$31,A67="INDO",E67/'Shared Summary by Dept_US$'!$B$32,A67="BD",E67/'Shared Summary by Dept_US$'!$B$33,A67="Nepal",E67/'Shared Summary by Dept_US$'!$B$34,A67="US",E67/'Shared Summary by Dept_US$'!$B$35) -> #NAME? | T67: INDIA-Digital Product-Product Management
A68: India | B68: =IFERROR(__xludf.DUMMYFUNCTION("""COMPUTED_VALUE"""),"Communication Cost") -> Communication Cost | C68: =IFERROR(__xludf.DUMMYFUNCTION("""COMPUTED_VALUE"""),"Telecommunication expenses") -> Telecommunication expenses | D68: =IFERROR(__xludf.DUMMYFUNCTION("""COMPUTED_VALUE"""),93303) -> 93303 | E68: =IFERROR(__xludf.DUMMYFUNCTION("""COMPUTED_VALUE"""),0) -> 0 | S68: =_xludf.ifs(A68="INDIA",E68/'Shared Summary by Dept_US$'!$B$31,A68="INDO",E68/'Shared Summary by Dept_US$'!$B$32,A68="BD",E68/'Shared Summary by Dept_US$'!$B$33,A68="Nepal",E68/'Shared Summary by Dept_US$'!$B$34,A68="US",E68/'Shared Summary by Dept_US$'!$B$35) -> #NAME? | T68: INDIA-Digital Product-Product Management
A69: India | B69: =IFERROR(__xludf.DUMMYFUNCTION("""COMPUTED_VALUE"""),"Office Expenses") -> Office Expenses | C69: =IFERROR(__xludf.DUMMYFUNCTION("""COMPUTED_VALUE"""),"Software and Subscriptions") -> Software and Subscriptions | D69: =IFERROR(__xludf.DUMMYFUNCTION("""COMPUTED_VALUE"""),93401) -> 93401 | E69: =IFERROR(__xludf.DUMMYFUNCTION("""COMPUTED_VALUE"""),0) -> 0 | S69: =_xludf.ifs(A69="INDIA",E69/'Shared Summary by Dept_US$'!$B$31,A69="INDO",E69/'Shared Summary by Dept_US$'!$B$32,A69="BD",E69/'Shared Summary by Dept_US$'!$B$33,A69="Nepal",E69/'Shared Summary by Dept_US$'!$B$34,A69="US",E69/'Shared Summary by Dept_US$'!$B$35) -> #NAME? | T69: INDIA-Digital Product-Product Management
A70: India | B70: =IFERROR(__xludf.DUMMYFUNCTION("""COMPUTED_VALUE"""),"Office Expenses") -> Office Expenses | C70: =IFERROR(__xludf.DUMMYFUNCTION("""COMPUTED_VALUE"""),"Stationery & Consumables") -> Stationery & Consumables | D70: =IFERROR(__xludf.DUMMYFUNCTION("""COMPUTED_VALUE"""),93404) -> 93404 | E70: =IFERROR(__xludf.DUMMYFUNCTION("""COMPUTED_VALUE"""),0) -> 0 | S70: =_xludf.ifs(A70="INDIA",E70/'Shared Summary by Dept_US$'!$B$31,A70="INDO",E70/'Shared Summary by Dept_US$'!$B$32,A70="BD",E70/'Shared Summary by Dept_US$'!$B$33,A70="Nepal",E70/'Shared Summary by Dept_US$'!$B$34,A70="US",E70/'Shared Summary by Dept_US$'!$B$35) -> #NAME? | T70: INDIA-Digital Product-Product Management
A71: India | B71: =IFERROR(__xludf.DUMMYFUNCTION("""COMPUTED_VALUE"""),"Office Expenses") -> Office Expenses | C71: =IFERROR(__xludf.DUMMYFUNCTION("""COMPUTED_VALUE"""),"Office Equipment Expense") -> Office Equipment Expense | D71: =IFERROR(__xludf.DUMMYFUNCTION("""COMPUTED_VALUE"""),93405) -> 93405 | E71: =IFERROR(__xludf.DUMMYFUNCTION("""COMPUTED_VALUE"""),0) -> 0 | S71: =_xludf.ifs(A71="INDIA",E71/'Shared Summary by Dept_US$'!$B$31,A71="INDO",E71/'Shared Summary by Dept_US$'!$B$32,A71="BD",E71/'Shared Summary by Dept_US$'!$B$33,A71="Nepal",E71/'Shared Summary by Dept_US$'!$B$34,A71="US",E71/'Shared Summary by Dept_US$'!$B$35) -> #NAME? | T71: INDIA-Digital Product-Product Management
A72: India | B72: =IFERROR(__xludf.DUMMYFUNCTION("""COMPUTED_VALUE"""),"Professional & Consultancy Charges") -> Professional & Consultancy Charges | C72: =IFERROR(__xludf.DUMMYFUNCTION("""COMPUTED_VALUE"""),"Admin Consultants") -> Admin Consultants | D72: =IFERROR(__xludf.DUMMYFUNCTION("""COMPUTED_VALUE"""),93703) -> 93703 | E72: =IFERROR(__xludf.DUMMYFUNCTION("""COMPUTED_VALUE"""),0) -> 0 | S72: =_xludf.ifs(A72="INDIA",E72/'Shared Summary by Dept_US$'!$B$31,A72="INDO",E72/'Shared Summary by Dept_US$'!$B$32,A72="BD",E72/'Shared Summary by Dept_US$'!$B$33,A72="Nepal",E72/'Shared Summary by Dept_US$'!$B$34,A72="US",E72/'Shared Summary by Dept_US$'!$B$35) -> #NAME? | T72: INDIA-Digital Product-Product Management
A73: India | B73: =IFERROR(__xludf.DUMMYFUNCTION("""COMPUTED_VALUE"""),"Supplies & Printing Costs") -> Supplies & Printing Costs | C73: =IFERROR(__xludf.DUMMYFUNCTION("""COMPUTED_VALUE"""),"RES (Exotel Expensess)") -> RES (Exotel Expensess) | D73: =IFERROR(__xludf.DUMMYFUNCTION("""COMPUTED_VALUE"""),93202) -> 93202 | E73: =IFERROR(__xludf.DUMMYFUNCTION("""COMPUTED_VALUE"""),0) -> 0 | S73: =_xludf.ifs(A73="INDIA",E73/'Shared Summary by Dept_US$'!$B$31,A73="INDO",E73/'Shared Summary by Dept_US$'!$B$32,A73="BD",E73/'Shared Summary by Dept_US$'!$B$33,A73="Nepal",E73/'Shared Summary by Dept_US$'!$B$34,A73="US",E73/'Shared Summary by Dept_US$'!$B$35) -> #NAME? | T73: INDIA-Digital Product-Product Management
A74: India | B74: =IFERROR(__xludf.DUMMYFUNCTION("""COMPUTED_VALUE"""),"Fixed Assets") -> Fixed Assets | C74: =IFERROR(__xludf.DUMMYFUNCTION("""COMPUTED_VALUE"""),"Laptop/ Printer") -> Laptop/ Printer | D74: =IFERROR(__xludf.DUMMYFUNCTION("""COMPUTED_VALUE"""),11301) -> 11301 | E74: =IFERROR(__xludf.DUMMYFUNCTION("""COMPUTED_VALUE"""),0) -> 0 | F74: =IFERROR(__xludf.DUMMYFUNCTION("""COMPUTED_VALUE"""),0) -> 0 | G74: =IFERROR(__xludf.DUMMYFUNCTION("""COMPUTED_VALUE"""),0) -> 0 | H74: =IFERROR(__xludf.DUMMYFUNCTION("""COMPUTED_VALUE"""),0) -> 0 | I74: =IFERROR(__xludf.DUMMYFUNCTION("""COMPUTED_VALUE"""),0) -> 0 | J74: =IFERROR(__xludf.DUMMYFUNCTION("""COMPUTED_VALUE"""),0) -> 0 | K74: =IFERROR(__xludf.DUMMYFUNCTION("""COMPUTED_VALUE"""),0) -> 0 | L74: =IFERROR(__xludf.DUMMYFUNCTION("""COMPUTED_VALUE"""),0) -> 0 | ... Q74: =IFERROR(__xludf.DUMMYFUNCTION("""COMPUTED_VALUE"""),0) -> 0 | S74: =_xludf.ifs(A74="INDIA",E74/'Shared Summary by Dept_US$'!$B$31,A74="INDO",E74/'Shared Summary by Dept_US$'!$B$32,A74="BD",E74/'Shared Summary by Dept_US$'!$B$33,A74="Nepal",E74/'Shared Summary by Dept_US$'!$B$34,A74="US",E74/'Shared Summary by Dept_US$'!$B$35) -> #NAME? | T74: INDIA-Digital Product-Product Management
A75: India | B75: =IFERROR(__xludf.DUMMYFUNCTION("""COMPUTED_VALUE"""),"Salaries and Wages") -> Salaries and Wages | C75: =IFERROR(__xludf.DUMMYFUNCTION("""COMPUTED_VALUE"""),"Salaries and Wages") -> Salaries and Wages | E75: =IFERROR(__xludf.DUMMYFUNCTION("""COMPUTED_VALUE"""),16607391.2224999) -> 16607391 | F75: =IFERROR(__xludf.DUMMYFUNCTION("""COMPUTED_VALUE"""),1519307.57666666) -> 1519307.6 | G75: =IFERROR(__xludf.DUMMYFUNCTION("""COMPUTED_VALUE"""),1519307.57666666) -> 1519307.6 | H75: =IFERROR(__xludf.DUMMYFUNCTION("""COMPUTED_VALUE"""),1519307.57666666) -> 1519307.6 | I75: =IFERROR(__xludf.DUMMYFUNCTION("""COMPUTED_VALUE"""),1338829.8325) -> 1338829.8 | J75: =IFERROR(__xludf.DUMMYFUNCTION("""COMPUTED_VALUE"""),1338829.8325) -> 1338829.8 | K75: =IFERROR(__xludf.DUMMYFUNCTION("""COMPUTED_VALUE"""),1338829.8325) -> 1338829.8 | L75: =IFERROR(__xludf.DUMMYFUNCTION("""COMPUTED_VALUE"""),1338829.8325) -> 1338829.8 | M75: =IFERROR(__xludf.DUMMYFUNCTION("""COMPUTED_VALUE"""),1338829.8325) -> 1338829.8 | N75: =IFERROR(__xludf.DUMMYFUNCTION("""COMPUTED_VALUE"""),1338829.8325) -> 1338829.8 | O75: =IFERROR(__xludf.DUMMYFUNCTION("""COMPUTED_VALUE"""),1338829.8325) -> 1338829.8 | P75: =IFERROR(__xludf.DUMMYFUNCTION("""COMPUTED_VALUE"""),1338829.8325) -> 1338829.8 | Q75: =IFERROR(__xludf.DUMMYFUNCTION("""COMPUTED_VALUE"""),1338829.8325) -> 1338829.8 | S75: =_xludf.ifs(A75="INDIA",E75/'Shared Summary by Dept_US$'!$B$31,A75="INDO",E75/'Shared Summary by Dept_US$'!$B$32,A75="BD",E75/'Shared Summary by Dept_US$'!$B$33,A75="Nepal",E75/'Shared Summary by Dept_US$'!$B$34,A75="US",E75/'Shared Summary by Dept_US$'!$B$35) -> #NAME? | T75: INDIA-Digital Product-Product Management
A76: India | B76: =IFERROR(__xludf.DUMMYFUNCTION("""COMPUTED_VALUE"""),"Health and Retirement Benefits") -> Health and Retirement Benefits | C76: =IFERROR(__xludf.DUMMYFUNCTION("""COMPUTED_VALUE"""),"Gratuity & Bonus") -> Gratuity & Bonus | E76: =IFERROR(__xludf.DUMMYFUNCTION("""COMPUTED_VALUE"""),1593093.4) -> 1593093.4 | F76: =IFERROR(__xludf.DUMMYFUNCTION("""COMPUTED_VALUE"""),129730) -> 129730 | G76: =IFERROR(__xludf.DUMMYFUNCTION("""COMPUTED_VALUE"""),72836.4) -> 72836.4 | H76: =IFERROR(__xludf.DUMMYFUNCTION("""COMPUTED_VALUE"""),1322800) -> 1322800 | I76: =IFERROR(__xludf.DUMMYFUNCTION("""COMPUTED_VALUE"""),0) -> 0 | J76: =IFERROR(__xludf.DUMMYFUNCTION("""COMPUTED_VALUE"""),0) -> 0 | K76: =IFERROR(__xludf.DUMMYFUNCTION("""COMPUTED_VALUE"""),0) -> 0 | L76: =IFERROR(__xludf.DUMMYFUNCTION("""COMPUTED_VALUE"""),0) -> 0 | M76: =IFERROR(__xludf.DUMMYFUNCTION("""COMPUTED_VALUE"""),0) -> 0 | N76: =IFERROR(__xludf.DUMMYFUNCTION("""COMPUTED_VALUE"""),0) -> 0 | O76: =IFERROR(__xludf.DUMMYFUNCTION("""COMPUTED_VALUE"""),0) -> 0 | P76: =IFERROR(__xludf.DUMMYFUNCTION("""COMPUTED_VALUE"""),67727) -> 67727 | Q76: =IFERROR(__xludf.DUMMYFUNCTION("""COMPUTED_VALUE"""),0) -> 0 | S76: =_xludf.ifs(A76="INDIA",E76/'Shared Summary by Dept_US$'!$B$31,A76="INDO",E76/'Shared Summary by Dept_US$'!$B$32,A76="BD",E76/'Shared Summary by Dept_US$'!$B$33,A76="Nepal",E76/'Shared Summary by Dept_US$'!$B$34,A76="US",E76/'Shared Summary by Dept_US$'!$B$35) -> #NAME? | T76: INDIA-Digital Product-Product Management
A77: India | B77: =IFERROR(__xludf.DUMMYFUNCTION("""COMPUTED_VALUE"""),"Other Staff Expenses") -> Other Staff Expenses | C77: =IFERROR(__xludf.DUMMYFUNCTION("""COMPUTED_VALUE"""),"Staff Training, Learning & Development Exp") -> Staff Training, Learning & Development Exp | D77: =IFERROR(__xludf.DUMMYFUNCTION("""COMPUTED_VALUE"""),91302) -> 91302 | E77: =IFERROR(__xludf.DUMMYFUNCTION("""COMPUTED_VALUE"""),0) -> 0 | F77: =IFERROR(__xludf.DUMMYFUNCTION("""COMPUTED_VALUE"""),0) -> 0 | G77: =IFERROR(__xludf.DUMMYFUNCTION("""COMPUTED_VALUE"""),0) -> 0 | H77: =IFERROR(__xludf.DUMMYFUNCTION("""COMPUTED_VALUE"""),0) -> 0 | I77: =IFERROR(__xludf.DUMMYFUNCTION("""COMPUTED_VALUE"""),0) -> 0 | J77: =IFERROR(__xludf.DUMMYFUNCTION("""COMPUTED_VALUE"""),0) -> 0 | K77: =IFERROR(__xludf.DUMMYFUNCTION("""COMPUTED_VALUE"""),0) -> 0 | L77: =IFERROR(__xludf.DUMMYFUNCTION("""COMPUTED_VALUE"""),0) -> 0 | ... Q77: =IFERROR(__xludf.DUMMYFUNCTION("""COMPUTED_VALUE"""),0) -> 0 | S77: =_xludf.ifs(A77="INDIA",E77/'Shared Summary by Dept_US$'!$B$31,A77="INDO",E77/'Shared Summary by Dept_US$'!$B$32,A77="BD",E77/'Shared Summary by Dept_US$'!$B$33,A77="Nepal",E77/'Shared Summary by Dept_US$'!$B$34,A77="US",E77/'Shared Summary by Dept_US$'!$B$35) -> #NAME? | T77: INDIA-Digital Product-Product Management
A78: India | B78: =IFERROR(__xludf.DUMMYFUNCTION("""COMPUTED_VALUE"""),"Resource Persons") -> Resource Persons | C78: =IFERROR(__xludf.DUMMYFUNCTION("""COMPUTED_VALUE"""),"Program Resource Consultant (EHA)") -> Program Resource Consultant (EHA) | D78: =IFERROR(__xludf.DUMMYFUNCTION("""COMPUTED_VALUE"""),92101) -> 92101 | E78: =IFERROR(__xludf.DUMMYFUNCTION("""COMPUTED_VALUE"""),3061126.2) -> 3061126.2 | F78: =IFERROR(__xludf.DUMMYFUNCTION("""COMPUTED_VALUE"""),674946.6) -> 674946.6 | G78: =IFERROR(__xludf.DUMMYFUNCTION("""COMPUTED_VALUE"""),265209.6) -> 265209.6 | H78: =IFERROR(__xludf.DUMMYFUNCTION("""COMPUTED_VALUE"""),265209.6) -> 265209.6 | I78: =IFERROR(__xludf.DUMMYFUNCTION("""COMPUTED_VALUE"""),206195.6) -> 206195.6 | J78: =IFERROR(__xludf.DUMMYFUNCTION("""COMPUTED_VALUE"""),206195.6) -> 206195.6 | K78: =IFERROR(__xludf.DUMMYFUNCTION("""COMPUTED_VALUE"""),206195.6) -> 206195.6 | L78: =IFERROR(__xludf.DUMMYFUNCTION("""COMPUTED_VALUE"""),206195.6) -> 206195.6 | M78: =IFERROR(__xludf.DUMMYFUNCTION("""COMPUTED_VALUE"""),206195.6) -> 206195.6 | N78: =IFERROR(__xludf.DUMMYFUNCTION("""COMPUTED_VALUE"""),206195.6) -> 206195.6 | O78: =IFERROR(__xludf.DUMMYFUNCTION("""COMPUTED_VALUE"""),206195.6) -> 206195.6 | P78: =IFERROR(__xludf.DUMMYFUNCTION("""COMPUTED_VALUE"""),206195.6) -> 206195.6 | Q78: =IFERROR(__xludf.DUMMYFUNCTION("""COMPUTED_VALUE"""),206195.6) -> 206195.6 | S78: =_xludf.ifs(A78="INDIA",E78/'Shared Summary by Dept_US$'!$B$31,A78="INDO",E78/'Shared Summary by Dept_US$'!$B$32,A78="BD",E78/'Shared Summary by Dept_US$'!$B$33,A78="Nepal",E78/'Shared Summary by Dept_US$'!$B$34,A78="US",E78/'Shared Summary by Dept_US$'!$B$35) -> #NAME? | T78: INDIA-Digital Product-Product Management
A79: India | B79: =IFERROR(__xludf.DUMMYFUNCTION("""COMPUTED_VALUE"""),"Travel & Lodging Expenses") -> Travel & Lodging Expenses | C79: =IFERROR(__xludf.DUMMYFUNCTION("""COMPUTED_VALUE"""),"Hotel Accomodation") -> Hotel Accomodation | D79: =IFERROR(__xludf.DUMMYFUNCTION("""COMPUTED_VALUE"""),93101) -> 93101 | E79: =IFERROR(__xludf.DUMMYFUNCTION("""COMPUTED_VALUE"""),47250) -> 47250 | F79: =IFERROR(__xludf.DUMMYFUNCTION("""COMPUTED_VALUE"""),0) -> 0 | G79: =IFERROR(__xludf.DUMMYFUNCTION("""COMPUTED_VALUE"""),0) -> 0 | H79: =IFERROR(__xludf.DUMMYFUNCTION("""COMPUTED_VALUE"""),10500) -> 10500 | I79: =IFERROR(__xludf.DUMMYFUNCTION("""COMPUTED_VALUE"""),26250) -> 26250 | J79: =IFERROR(__xludf.DUMMYFUNCTION("""COMPUTED_VALUE"""),0) -> 0 | K79: =IFERROR(__xludf.DUMMYFUNCTION("""COMPUTED_VALUE"""),0) -> 0 | L79: =IFERROR(__xludf.DUMMYFUNCTION("""COMPUTED_VALUE"""),0) -> 0 | M79: =IFERROR(__xludf.DUMMYFUNCTION("""COMPUTED_VALUE"""),10500) -> 10500 | N79: =IFERROR(__xludf.DUMMYFUNCTION("""COMPUTED_VALUE"""),0) -> 0 | O79: =IFERROR(__xludf.DUMMYFUNCTION("""COMPUTED_VALUE"""),0) -> 0 | P79: =IFERROR(__xludf.DUMMYFUNCTION("""COMPUTED_VALUE"""),0) -> 0 | Q79: =IFERROR(__xludf.DUMMYFUNCTION("""COMPUTED_VALUE"""),0) -> 0 | S79: =_xludf.ifs(A79="INDIA",E79/'Shared Summary by Dept_US$'!$B$31,A79="INDO",E79/'Shared Summary by Dept_US$'!$B$32,A79="BD",E79/'Shared Summary by Dept_US$'!$B$33,A79="Nepal",E79/'Shared Summary by Dept_US$'!$B$34,A79="US",E79/'Shared Summary by Dept_US$'!$B$35) -> #NAME? | T79: INDIA-Digital Product-Product Management
A80: India | B80: =IFERROR(__xludf.DUMMYFUNCTION("""COMPUTED_VALUE"""),"Travel & Lodging Expenses") -> Travel & Lodging Expenses | C80: =IFERROR(__xludf.DUMMYFUNCTION("""COMPUTED_VALUE"""),"Food Expenses") -> Food Expenses | D80: =IFERROR(__xludf.DUMMYFUNCTION("""COMPUTED_VALUE"""),93102) -> 93102 | E80: =IFERROR(__xludf.DUMMYFUNCTION("""COMPUTED_VALUE"""),25500) -> 25500 | F80: =IFERROR(__xludf.DUMMYFUNCTION("""COMPUTED_VALUE"""),0) -> 0 | G80: =IFERROR(__xludf.DUMMYFUNCTION("""COMPUTED_VALUE"""),3000) -> 3000 | H80: =IFERROR(__xludf.DUMMYFUNCTION("""COMPUTED_VALUE"""),6000) -> 6000 | I80: =IFERROR(__xludf.DUMMYFUNCTION("""COMPUTED_VALUE"""),7500) -> 7500 | J80: =IFERROR(__xludf.DUMMYFUNCTION("""COMPUTED_VALUE"""),0) -> 0 | K80: =IFERROR(__xludf.DUMMYFUNCTION("""COMPUTED_VALUE"""),0) -> 0 | L80: =IFERROR(__xludf.DUMMYFUNCTION("""COMPUTED_VALUE"""),0) -> 0 | M80: =IFERROR(__xludf.DUMMYFUNCTION("""COMPUTED_VALUE"""),6000) -> 6000 | N80: =IFERROR(__xludf.DUMMYFUNCTION("""COMPUTED_VALUE"""),3000) -> 3000 | O80: =IFERROR(__xludf.DUMMYFUNCTION("""COMPUTED_VALUE"""),0) -> 0 | P80: =IFERROR(__xludf.DUMMYFUNCTION("""COMPUTED_VALUE"""),0) -> 0 | Q80: =IFERROR(__xludf.DUMMYFUNCTION("""COMPUTED_VALUE"""),0) -> 0 | S80: =_xludf.ifs(A80="INDIA",E80/'Shared Summary by Dept_US$'!$B$31,A80="INDO",E80/'Shared Summary by Dept_US$'!$B$32,A80="BD",E80/'Shared Summary by Dept_US$'!$B$33,A80="Nepal",E80/'Shared Summary by Dept_US$'!$B$34,A80="US",E80/'Shared Summary by Dept_US$'!$B$35) -> #NAME? | T80: INDIA-Digital Product-Product Management
A81: India | B81: =IFERROR(__xludf.DUMMYFUNCTION("""COMPUTED_VALUE"""),"Travel & Lodging Expenses") -> Travel & Lodging Expenses | C81: =IFERROR(__xludf.DUMMYFUNCTION("""COMPUTED_VALUE"""),"Air fare") -> Air fare | D81: =IFERROR(__xludf.DUMMYFUNCTION("""COMPUTED_VALUE"""),93103) -> 93103 | E81: =IFERROR(__xludf.DUMMYFUNCTION("""COMPUTED_VALUE"""),216000) -> 216000 | F81: =IFERROR(__xludf.DUMMYFUNCTION("""COMPUTED_VALUE"""),0) -> 0 | G81: =IFERROR(__xludf.DUMMYFUNCTION("""COMPUTED_VALUE"""),0) -> 0 | H81: =IFERROR(__xludf.DUMMYFUNCTION("""COMPUTED_VALUE"""),18000) -> 18000 | I81: =IFERROR(__xludf.DUMMYFUNCTION("""COMPUTED_VALUE"""),180000) -> 180000 | J81: =IFERROR(__xludf.DUMMYFUNCTION("""COMPUTED_VALUE"""),0) -> 0 | K81: =IFERROR(__xludf.DUMMYFUNCTION("""COMPUTED_VALUE"""),0) -> 0 | L81: =IFERROR(__xludf.DUMMYFUNCTION("""COMPUTED_VALUE"""),0) -> 0 | M81: =IFERROR(__xludf.DUMMYFUNCTION("""COMPUTED_VALUE"""),18000) -> 18000 | N81: =IFERROR(__xludf.DUMMYFUNCTION("""COMPUTED_VALUE"""),0) -> 0 | O81: =IFERROR(__xludf.DUMMYFUNCTION("""COMPUTED_VALUE"""),0) -> 0 | P81: =IFERROR(__xludf.DUMMYFUNCTION("""COMPUTED_VALUE"""),0) -> 0 | Q81: =IFERROR(__xludf.DUMMYFUNCTION("""COMPUTED_VALUE"""),0) -> 0 | S81: =_xludf.ifs(A81="INDIA",E81/'Shared Summary by Dept_US$'!$B$31,A81="INDO",E81/'Shared Summary by Dept_US$'!$B$32,A81="BD",E81/'Shared Summary by Dept_US$'!$B$33,A81="Nepal",E81/'Shared Summary by Dept_US$'!$B$34,A81="US",E81/'Shared Summary by Dept_US$'!$B$35) -> #NAME? | T81: INDIA-Digital Product-Product Management
A82: India | B82: =IFERROR(__xludf.DUMMYFUNCTION("""COMPUTED_VALUE"""),"Travel & Lodging Expenses") -> Travel & Lodging Expenses | C82: =IFERROR(__xludf.DUMMYFUNCTION("""COMPUTED_VALUE"""),"Cab/Auto") -> Cab/Auto | D82: =IFERROR(__xludf.DUMMYFUNCTION("""COMPUTED_VALUE"""),93104) -> 93104 | E82: =IFERROR(__xludf.DUMMYFUNCTION("""COMPUTED_VALUE"""),147200) -> 147200 | F82: =IFERROR(__xludf.DUMMYFUNCTION("""COMPUTED_VALUE"""),0) -> 0 | G82: =IFERROR(__xludf.DUMMYFUNCTION("""COMPUTED_VALUE"""),20000) -> 20000 | H82: =IFERROR(__xludf.DUMMYFUNCTION("""COMPUTED_VALUE"""),28400) -> 28400 | I82: =IFERROR(__xludf.DUMMYFUNCTION("""COMPUTED_VALUE"""),50400) -> 50400 | J82: =IFERROR(__xludf.DUMMYFUNCTION("""COMPUTED_VALUE"""),0) -> 0 | K82: =IFERROR(__xludf.DUMMYFUNCTION("""COMPUTED_VALUE"""),0) -> 0 | L82: =IFERROR(__xludf.DUMMYFUNCTION("""COMPUTED_VALUE"""),0) -> 0 | M82: =IFERROR(__xludf.DUMMYFUNCTION("""COMPUTED_VALUE"""),28400) -> 28400 | N82: =IFERROR(__xludf.DUMMYFUNCTION("""COMPUTED_VALUE"""),20000) -> 20000 | O82: =IFERROR(__xludf.DUMMYFUNCTION("""COMPUTED_VALUE"""),0) -> 0 | P82: =IFERROR(__xludf.DUMMYFUNCTION("""COMPUTED_VALUE"""),0) -> 0 | Q82: =IFERROR(__xludf.DUMMYFUNCTION("""COMPUTED_VALUE"""),0) -> 0 | S82: =_xludf.ifs(A82="INDIA",E82/'Shared Summary by Dept_US$'!$B$31,A82="INDO",E82/'Shared Summary by Dept_US$'!$B$32,A82="BD",E82/'Shared Summary by Dept_US$'!$B$33,A82="Nepal",E82/'Shared Summary by Dept_US$'!$B$34,A82="US",E82/'Shared Summary by Dept_US$'!$B$35) -> #NAME? | T82: INDIA-Digital Product-Product Management
A83: India | B83: =IFERROR(__xludf.DUMMYFUNCTION("""COMPUTED_VALUE"""),"Travel & Lodging Expenses") -> Travel & Lodging Expenses | C83: =IFERROR(__xludf.DUMMYFUNCTION("""COMPUTED_VALUE"""),"Bus/Train") -> Bus/Train | D83: =IFERROR(__xludf.DUMMYFUNCTION("""COMPUTED_VALUE"""),93105) -> 93105 | E83: =IFERROR(__xludf.DUMMYFUNCTION("""COMPUTED_VALUE"""),3000) -> 3000 | F83: =IFERROR(__xludf.DUMMYFUNCTION("""COMPUTED_VALUE"""),0) -> 0 | G83: =IFERROR(__xludf.DUMMYFUNCTION("""COMPUTED_VALUE"""),0) -> 0 | H83: =IFERROR(__xludf.DUMMYFUNCTION("""COMPUTED_VALUE"""),1500) -> 1500 | I83: =IFERROR(__xludf.DUMMYFUNCTION("""COMPUTED_VALUE"""),0) -> 0 | J83: =IFERROR(__xludf.DUMMYFUNCTION("""COMPUTED_VALUE"""),0) -> 0 | K83: =IFERROR(__xludf.DUMMYFUNCTION("""COMPUTED_VALUE"""),0) -> 0 | L83: =IFERROR(__xludf.DUMMYFUNCTION("""COMPUTED_VALUE"""),0) -> 0 | M83: =IFERROR(__xludf.DUMMYFUNCTION("""COMPUTED_VALUE"""),1500) -> 1500 | N83: =IFERROR(__xludf.DUMMYFUNCTION("""COMPUTED_VALUE"""),0) -> 0 | O83: =IFERROR(__xludf.DUMMYFUNCTION("""COMPUTED_VALUE"""),0) -> 0 | P83: =IFERROR(__xludf.DUMMYFUNCTION("""COMPUTED_VALUE"""),0) -> 0 | Q83: =IFERROR(__xludf.DUMMYFUNCTION("""COMPUTED_VALUE"""),0) -> 0 | S83: =_xludf.ifs(A83="INDIA",E83/'Shared Summary by Dept_US$'!$B$31,A83="INDO",E83/'Shared Summary by Dept_US$'!$B$32,A83="BD",E83/'Shared Summary by Dept_US$'!$B$33,A83="Nepal",E83/'Shared Summary by Dept_US$'!$B$34,A83="US",E83/'Shared Summary by Dept_US$'!$B$35) -> #NAME? | T83: INDIA-Digital Product-Product Management
A84: India | B84: =IFERROR(__xludf.DUMMYFUNCTION("""COMPUTED_VALUE"""),"Travel & Lodging Expenses") -> Travel & Lodging Expenses | C84: =IFERROR(__xludf.DUMMYFUNCTION("""COMPUTED_VALUE"""),"Other incidental travel costs") -> Other incidental travel costs | D84: =IFERROR(__xludf.DUMMYFUNCTION("""COMPUTED_VALUE"""),93106) -> 93106 | E84: =IFERROR(__xludf.DUMMYFUNCTION("""COMPUTED_VALUE"""),4900) -> 4900 | F84: =IFERROR(__xludf.DUMMYFUNCTION("""COMPUTED_VALUE"""),0) -> 0 | G84: =IFERROR(__xludf.DUMMYFUNCTION("""COMPUTED_VALUE"""),0) -> 0 | H84: =IFERROR(__xludf.DUMMYFUNCTION("""COMPUTED_VALUE"""),700) -> 700 | I84: =IFERROR(__xludf.DUMMYFUNCTION("""COMPUTED_VALUE"""),3500) -> 3500 | J84: =IFERROR(__xludf.DUMMYFUNCTION("""COMPUTED_VALUE"""),0) -> 0 | K84: =IFERROR(__xludf.DUMMYFUNCTION("""COMPUTED_VALUE"""),0) -> 0 | L84: =IFERROR(__xludf.DUMMYFUNCTION("""COMPUTED_VALUE"""),0) -> 0 | M84: =IFERROR(__xludf.DUMMYFUNCTION("""COMPUTED_VALUE"""),700) -> 700 | N84: =IFERROR(__xludf.DUMMYFUNCTION("""COMPUTED_VALUE"""),0) -> 0 | O84: =IFERROR(__xludf.DUMMYFUNCTION("""COMPUTED_VALUE"""),0) -> 0 | P84: =IFERROR(__xludf.DUMMYFUNCTION("""COMPUTED_VALUE"""),0) -> 0 | Q84: =IFERROR(__xludf.DUMMYFUNCTION("""COMPUTED_VALUE"""),0) -> 0 | S84: =_xludf.ifs(A84="INDIA",E84/'Shared Summary by Dept_US$'!$B$31,A84="INDO",E84/'Shared Summary by Dept_US$'!$B$32,A84="BD",E84/'Shared Summary by Dept_US$'!$B$33,A84="Nepal",E84/'Shared Summary by Dept_US$'!$B$34,A84="US",E84/'Shared Summary by Dept_US$'!$B$35) -> #NAME? | T84: INDIA-Digital Product-Product Management
A85: India | B85: =IFERROR(__xludf.DUMMYFUNCTION("""COMPUTED_VALUE"""),"Supplies & Printing Costs") -> Supplies & Printing Costs | C85: =IFERROR(__xludf.DUMMYFUNCTION("""COMPUTED_VALUE"""),"Other Direct Expenses") -> Other Direct Expenses | D85: =IFERROR(__xludf.DUMMYFUNCTION("""COMPUTED_VALUE"""),93201) -> 93201 | E85: =IFERROR(__xludf.DUMMYFUNCTION("""COMPUTED_VALUE"""),0) -> 0 | F85: =IFERROR(__xludf.DUMMYFUNCTION("""COMPUTED_VALUE"""),0) -> 0 | G85: =IFERROR(__xludf.DUMMYFUNCTION("""COMPUTED_VALUE"""),0) -> 0 | H85: =IFERROR(__xludf.DUMMYFUNCTION("""COMPUTED_VALUE"""),0) -> 0 | I85: =IFERROR(__xludf.DUMMYFUNCTION("""COMPUTED_VALUE"""),0) -> 0 | J85: =IFERROR(__xludf.DUMMYFUNCTION("""COMPUTED_VALUE"""),0) -> 0 | K85: =IFERROR(__xludf.DUMMYFUNCTION("""COMPUTED_VALUE"""),0) -> 0 | L85: =IFERROR(__xludf.DUMMYFUNCTION("""COMPUTED_VALUE"""),0) -> 0 | M85: =IFERROR(__xludf.DUMMYFUNCTION("""COMPUTED_VALUE"""),0) -> 0 | Q85: =IFERROR(__xludf.DUMMYFUNCTION("""COMPUTED_VALUE"""),0) -> 0 | S85: =_xludf.ifs(A85="INDIA",E85/'Shared Summary by Dept_US$'!$B$31,A85="INDO",E85/'Shared Summary by Dept_US$'!$B$32,A85="BD",E85/'Shared Summary by Dept_US$'!$B$33,A85="Nepal",E85/'Shared Summary by Dept_US$'!$B$34,A85="US",E85/'Shared Summary by Dept_US$'!$B$35) -> #NAME? | T85: INDIA-Digital Product-Product Management
A86: India | B86: =IFERROR(__xludf.DUMMYFUNCTION("""COMPUTED_VALUE"""),"Supplies & Printing Costs") -> Supplies & Printing Costs | C86: =IFERROR(__xludf.DUMMYFUNCTION("""COMPUTED_VALUE"""),"Printing expenses") -> Printing expenses | D86: =IFERROR(__xludf.DUMMYFUNCTION("""COMPUTED_VALUE"""),93204) -> 93204 | E86: =IFERROR(__xludf.DUMMYFUNCTION("""COMPUTED_VALUE"""),0) -> 0 | F86: =IFERROR(__xludf.DUMMYFUNCTION("""COMPUTED_VALUE"""),0) -> 0 | G86: =IFERROR(__xludf.DUMMYFUNCTION("""COMPUTED_VALUE"""),0) -> 0 | H86: =IFERROR(__xludf.DUMMYFUNCTION("""COMPUTED_VALUE"""),0) -> 0 | I86: =IFERROR(__xludf.DUMMYFUNCTION("""COMPUTED_VALUE"""),0) -> 0 | J86: =IFERROR(__xludf.DUMMYFUNCTION("""COMPUTED_VALUE"""),0) -> 0 | K86: =IFERROR(__xludf.DUMMYFUNCTION("""COMPUTED_VALUE"""),0) -> 0 | L86: =IFERROR(__xludf.DUMMYFUNCTION("""COMPUTED_VALUE"""),0) -> 0 | M86: =IFERROR(__xludf.DUMMYFUNCTION("""COMPUTED_VALUE"""),0) -> 0 | S86: =_xludf.ifs(A86="INDIA",E86/'Shared Summary by Dept_US$'!$B$31,A86="INDO",E86/'Shared Summary by Dept_US$'!$B$32,A86="BD",E86/'Shared Summary by Dept_US$'!$B$33,A86="Nepal",E86/'Shared Summary by Dept_US$'!$B$34,A86="US",E86/'Shared Summary by Dept_US$'!$B$35) -> #NAME? | T86: INDIA-Digital Product-Product Management
A87: India | B87: =IFERROR(__xludf.DUMMYFUNCTION("""COMPUTED_VALUE"""),"Communication Cost") -> Communication Cost | C87: =IFERROR(__xludf.DUMMYFUNCTION("""COMPUTED_VALUE"""),"Internet Expenses") -> Internet Expenses | D87: =IFERROR(__xludf.DUMMYFUNCTION("""COMPUTED_VALUE"""),93301) -> 93301 | E87: =IFERROR(__xludf.DUMMYFUNCTION("""COMPUTED_VALUE"""),0) -> 0 | F87: =IFERROR(__xludf.DUMMYFUNCTION("""COMPUTED_VALUE"""),0) -> 0 | G87: =IFERROR(__xludf.DUMMYFUNCTION("""COMPUTED_VALUE"""),0) -> 0 | H87: =IFERROR(__xludf.DUMMYFUNCTION("""COMPUTED_VALUE"""),0) -> 0 | I87: =IFERROR(__xludf.DUMMYFUNCTION("""COMPUTED_VALUE"""),0) -> 0 | J87: =IFERROR(__xludf.DUMMYFUNCTION("""COMPUTED_VALUE"""),0) -> 0 | K87: =IFERROR(__xludf.DUMMYFUNCTION("""COMPUTED_VALUE"""),0) -> 0 | L87: =IFERROR(__xludf.DUMMYFUNCTION("""COMPUTED_VALUE"""),0) -> 0 | M87: =IFERROR(__xludf.DUMMYFUNCTION("""COMPUTED_VALUE"""),0) -> 0 | S87: =_xludf.ifs(A87="INDIA",E87/'Shared Summary by Dept_US$'!$B$31,A87="INDO",E87/'Shared Summary by Dept_US$'!$B$32,A87="BD",E87/'Shared Summary by Dept_US$'!$B$33,A87="Nepal",E87/'Shared Summary by Dept_US$'!$B$34,A87="US",E87/'Shared Summary by Dept_US$'!$B$35) -> #NAME? | T87: INDIA-Digital Product-Product Management
A88: India | B88: =IFERROR(__xludf.DUMMYFUNCTION("""COMPUTED_VALUE"""),"Communication Cost") -> Communication Cost | C88: =IFERROR(__xludf.DUMMYFUNCTION("""COMPUTED_VALUE"""),"Postage & Courier Expenses") -> Postage & Courier Expenses | D88: =IFERROR(__xludf.DUMMYFUNCTION("""COMPUTED_VALUE"""),93302) -> 93302 | E88: =IFERROR(__xludf.DUMMYFUNCTION("""COMPUTED_VALUE"""),0) -> 0 | F88: =IFERROR(__xludf.DUMMYFUNCTION("""COMPUTED_VALUE"""),0) -> 0 | G88: =IFERROR(__xludf.DUMMYFUNCTION("""COMPUTED_VALUE"""),0) -> 0 | H88: =IFERROR(__xludf.DUMMYFUNCTION("""COMPUTED_VALUE"""),0) -> 0 | I88: =IFERROR(__xludf.DUMMYFUNCTION("""COMPUTED_VALUE"""),0) -> 0 | J88: =IFERROR(__xludf.DUMMYFUNCTION("""COMPUTED_VALUE"""),0) -> 0 | K88: =IFERROR(__xludf.DUMMYFUNCTION("""COMPUTED_VALUE"""),0) -> 0 | L88: =IFERROR(__xludf.DUMMYFUNCTION("""COMPUTED_VALUE"""),0) -> 0 | M88: =IFERROR(__xludf.DUMMYFUNCTION("""COMPUTED_VALUE"""),0) -> 0 | S88: =_xludf.ifs(A88="INDIA",E88/'Shared Summary by Dept_US$'!$B$31,A88="INDO",E88/'Shared Summary by Dept_US$'!$B$32,A88="BD",E88/'Shared Summary by Dept_US$'!$B$33,A88="Nepal",E88/'Shared Summary by Dept_US$'!$B$34,A88="US",E88/'Shared Summary by Dept_US$'!$B$35) -> #NAME? | T88: INDIA-Digital Product-Product Management
A89: India | B89: =IFERROR(__xludf.DUMMYFUNCTION("""COMPUTED_VALUE"""),"Communication Cost") -> Communication Cost | C89: =IFERROR(__xludf.DUMMYFUNCTION("""COMPUTED_VALUE"""),"Telecommunication expenses") -> Telecommunication expenses | D89: =IFERROR(__xludf.DUMMYFUNCTION("""COMPUTED_VALUE"""),93303) -> 93303 | E89: =IFERROR(__xludf.DUMMYFUNCTION("""COMPUTED_VALUE"""),0) -> 0 | F89: =IFERROR(__xludf.DUMMYFUNCTION("""COMPUTED_VALUE"""),0) -> 0 | G89: =IFERROR(__xludf.DUMMYFUNCTION("""COMPUTED_VALUE"""),0) -> 0 | H89: =IFERROR(__xludf.DUMMYFUNCTION("""COMPUTED_VALUE"""),0) -> 0 | I89: =IFERROR(__xludf.DUMMYFUNCTION("""COMPUTED_VALUE"""),0) -> 0 | J89: =IFERROR(__xludf.DUMMYFUNCTION("""COMPUTED_VALUE"""),0) -> 0 | K89: =IFERROR(__xludf.DUMMYFUNCTION("""COMPUTED_VALUE"""),0) -> 0 | L89: =IFERROR(__xludf.DUMMYFUNCTION("""COMPUTED_VALUE"""),0) -> 0 | M89: =IFERROR(__xludf.DUMMYFUNCTION("""COMPUTED_VALUE"""),0) -> 0 | S89: =_xludf.ifs(A89="INDIA",E89/'Shared Summary by Dept_US$'!$B$31,A89="INDO",E89/'Shared Summary by Dept_US$'!$B$32,A89="BD",E89/'Shared Summary by Dept_US$'!$B$33,A89="Nepal",E89/'Shared Summary by Dept_US$'!$B$34,A89="US",E89/'Shared Summary by Dept_US$'!$B$35) -> #NAME? | T89: INDIA-Digital Product-Product Management
A90: India | B90: =IFERROR(__xludf.DUMMYFUNCTION("""COMPUTED_VALUE"""),"Office Expenses") -> Office Expenses | C90: =IFERROR(__xludf.DUMMYFUNCTION("""COMPUTED_VALUE"""),"Software and Subscriptions") -> Software and Subscriptions | D90: =IFERROR(__xludf.DUMMYFUNCTION("""COMPUTED_VALUE"""),93401) -> 93401 | E90: =IFERROR(__xludf.DUMMYFUNCTION("""COMPUTED_VALUE"""),53268) -> 53268 | F90: =IFERROR(__xludf.DUMMYFUNCTION("""COMPUTED_VALUE"""),53268) -> 53268 | S90: =_xludf.ifs(A90="INDIA",E90/'Shared Summary by Dept_US$'!$B$31,A90="INDO",E90/'Shared Summary by Dept_US$'!$B$32,A90="BD",E90/'Shared Summary by Dept_US$'!$B$33,A90="Nepal",E90/'Shared Summary by Dept_US$'!$B$34,A90="US",E90/'Shared Summary by Dept_US$'!$B$35) -> #NAME? | T90: INDIA-Digital Product-Product Management
A91: India | B91: =IFERROR(__xludf.DUMMYFUNCTION("""COMPUTED_VALUE"""),"Office Expenses") -> Office Expenses | C91: =IFERROR(__xludf.DUMMYFUNCTION("""COMPUTED_VALUE"""),"Stationery & Consumables") -> Stationery & Consumables | D91: =IFERROR(__xludf.DUMMYFUNCTION("""COMPUTED_VALUE"""),93404) -> 93404 | E91: =IFERROR(__xludf.DUMMYFUNCTION("""COMPUTED_VALUE"""),19000) -> 19000 | G91: =IFERROR(__xludf.DUMMYFUNCTION("""COMPUTED_VALUE"""),1000) -> 1000 | H91: =IFERROR(__xludf.DUMMYFUNCTION("""COMPUTED_VALUE"""),1000) -> 1000 | I91: =IFERROR(__xludf.DUMMYFUNCTION("""COMPUTED_VALUE"""),1000) -> 1000 | J91: =IFERROR(__xludf.DUMMYFUNCTION("""COMPUTED_VALUE"""),9000) -> 9000 | K91: =IFERROR(__xludf.DUMMYFUNCTION("""COMPUTED_VALUE"""),1000) -> 1000 | L91: =IFERROR(__xludf.DUMMYFUNCTION("""COMPUTED_VALUE"""),1000) -> 1000 | M91: =IFERROR(__xludf.DUMMYFUNCTION("""COMPUTED_VALUE"""),1000) -> 1000 | N91: =IFERROR(__xludf.DUMMYFUNCTION("""COMPUTED_VALUE"""),1000) -> 1000 | O91: =IFERROR(__xludf.DUMMYFUNCTION("""COMPUTED_VALUE"""),1000) -> 1000 | P91: =IFERROR(__xludf.DUMMYFUNCTION("""COMPUTED_VALUE"""),1000) -> 1000 | Q91: =IFERROR(__xludf.DUMMYFUNCTION("""COMPUTED_VALUE"""),1000) -> 1000 | S91: =_xludf.ifs(A91="INDIA",E91/'Shared Summary by Dept_US$'!$B$31,A91="INDO",E91/'Shared Summary by Dept_US$'!$B$32,A91="BD",E91/'Shared Summary by Dept_US$'!$B$33,A91="Nepal",E91/'Shared Summary by Dept_US$'!$B$34,A91="US",E91/'Shared Summary by Dept_US$'!$B$35) -> #NAME? | T91: INDIA-Digital Product-Product Management
A92: India | B92: =IFERROR(__xludf.DUMMYFUNCTION("""COMPUTED_VALUE"""),"Office Expenses") -> Office Expenses | C92: =IFERROR(__xludf.DUMMYFUNCTION("""COMPUTED_VALUE"""),"Office Equipment Expense") -> Office Equipment Expense | D92: =IFERROR(__xludf.DUMMYFUNCTION("""COMPUTED_VALUE"""),93405) -> 93405 | E92: =IFERROR(__xludf.DUMMYFUNCTION("""COMPUTED_VALUE"""),0) -> 0 | S92: =_xludf.ifs(A92="INDIA",E92/'Shared Summary by Dept_US$'!$B$31,A92="INDO",E92/'Shared Summary by Dept_US$'!$B$32,A92="BD",E92/'Shared Summary by Dept_US$'!$B$33,A92="Nepal",E92/'Shared Summary by Dept_US$'!$B$34,A92="US",E92/'Shared Summary by Dept_US$'!$B$35) -> #NAME? | T92: INDIA-Digital Product-Product Management
A93: India | B93: =IFERROR(__xludf.DUMMYFUNCTION("""COMPUTED_VALUE"""),"Professional & Consultancy Charges") -> Professional & Consultancy Charges | C93: =IFERROR(__xludf.DUMMYFUNCTION("""COMPUTED_VALUE"""),"Admin Consultants") -> Admin Consultants | D93: =IFERROR(__xludf.DUMMYFUNCTION("""COMPUTED_VALUE"""),93703) -> 93703 | E93: =IFERROR(__xludf.DUMMYFUNCTION("""COMPUTED_VALUE"""),0) -> 0 | S93: =_xludf.ifs(A93="INDIA",E93/'Shared Summary by Dept_US$'!$B$31,A93="INDO",E93/'Shared Summary by Dept_US$'!$B$32,A93="BD",E93/'Shared Summary by Dept_US$'!$B$33,A93="Nepal",E93/'Shared Summary by Dept_US$'!$B$34,A93="US",E93/'Shared Summary by Dept_US$'!$B$35) -> #NAME? | T93: INDIA-Digital Product-Product Management
A94: India | B94: =IFERROR(__xludf.DUMMYFUNCTION("""COMPUTED_VALUE"""),"Supplies & Printing Costs") -> Supplies & Printing Costs | C94: =IFERROR(__xludf.DUMMYFUNCTION("""COMPUTED_VALUE"""),"RES (Exotel Expensess)") -> RES (Exotel Expensess) | D94: =IFERROR(__xludf.DUMMYFUNCTION("""COMPUTED_VALUE"""),93202) -> 93202 | E94: =IFERROR(__xludf.DUMMYFUNCTION("""COMPUTED_VALUE"""),3000000) -> 3000000 | F94: =IFERROR(__xludf.DUMMYFUNCTION("""COMPUTED_VALUE"""),250000) -> 250000 | G94: =IFERROR(__xludf.DUMMYFUNCTION("""COMPUTED_VALUE"""),250000) -> 250000 | H94: =IFERROR(__xludf.DUMMYFUNCTION("""COMPUTED_VALUE"""),250000) -> 250000 | I94: =IFERROR(__xludf.DUMMYFUNCTION("""COMPUTED_VALUE"""),250000) -> 250000 | J94: =IFERROR(__xludf.DUMMYFUNCTION("""COMPUTED_VALUE"""),250000) -> 250000 | K94: =IFERROR(__xludf.DUMMYFUNCTION("""COMPUTED_VALUE"""),250000) -> 250000 | L94: =IFERROR(__xludf.DUMMYFUNCTION("""COMPUTED_VALUE"""),250000) -> 250000 | M94: =IFERROR(__xludf.DUMMYFUNCTION("""COMPUTED_VALUE"""),250000) -> 250000 | ... Q94: =IFERROR(__xludf.DUMMYFUNCTION("""COMPUTED_VALUE"""),250000) -> 250000 | S94: =_xludf.ifs(A94="INDIA",E94/'Shared Summary by Dept_US$'!$B$31,A94="INDO",E94/'Shared Summary by Dept_US$'!$B$32,A94="BD",E94/'Shared Summary by Dept_US$'!$B$33,A94="Nepal",E94/'Shared Summary by Dept_US$'!$B$34,A94="US",E94/'Shared Summary by Dept_US$'!$B$35) -> #NAME? | T94: INDIA-Digital Product-Product Management
A95: India | B95: =IFERROR(__xludf.DUMMYFUNCTION("""COMPUTED_VALUE"""),"Fixed Assets") -> Fixed Assets | C95: =IFERROR(__xludf.DUMMYFUNCTION("""COMPUTED_VALUE"""),"Laptop/ Printer") -> Laptop/ Printer | D95: =IFERROR(__xludf.DUMMYFUNCTION("""COMPUTED_VALUE"""),11301) -> 11301 | E95: =IFERROR(__xludf.DUMMYFUNCTION("""COMPUTED_VALUE"""),0) -> 0 | F95: =IFERROR(__xludf.DUMMYFUNCTION("""COMPUTED_VALUE"""),0) -> 0 | G95: =IFERROR(__xludf.DUMMYFUNCTION("""COMPUTED_VALUE"""),0) -> 0 | H95: =IFERROR(__xludf.DUMMYFUNCTION("""COMPUTED_VALUE"""),0) -> 0 | I95: =IFERROR(__xludf.DUMMYFUNCTION("""COMPUTED_VALUE"""),0) -> 0 | J95: =IFERROR(__xludf.DUMMYFUNCTION("""COMPUTED_VALUE"""),0) -> 0 | K95: =IFERROR(__xludf.DUMMYFUNCTION("""COMPUTED_VALUE"""),0) -> 0 | L95: =IFERROR(__xludf.DUMMYFUNCTION("""COMPUTED_VALUE"""),0) -> 0 | ... Q95: =IFERROR(__xludf.DUMMYFUNCTION("""COMPUTED_VALUE"""),0) -> 0 | S95: =_xludf.ifs(A95="INDIA",E95/'Shared Summary by Dept_US$'!$B$31,A95="INDO",E95/'Shared Summary by Dept_US$'!$B$32,A95="BD",E95/'Shared Summary by Dept_US$'!$B$33,A95="Nepal",E95/'Shared Summary by Dept_US$'!$B$34,A95="US",E95/'Shared Summary by Dept_US$'!$B$35) -> #NAME? | T95: INDIA-Digital Product-Product Management
A96: India | B96: =IFERROR(__xludf.DUMMYFUNCTION("""COMPUTED_VALUE"""),"Salaries and Wages") -> Salaries and Wages | C96: =IFERROR(__xludf.DUMMYFUNCTION("""COMPUTED_VALUE"""),"Salaries and Wages") -> Salaries and Wages | E96: =IFERROR(__xludf.DUMMYFUNCTION("""COMPUTED_VALUE"""),12092681.9999999) -> 12092682 | F96: =IFERROR(__xludf.DUMMYFUNCTION("""COMPUTED_VALUE"""),576473.75) -> 576473.75 | G96: =IFERROR(__xludf.DUMMYFUNCTION("""COMPUTED_VALUE"""),576473.75) -> 576473.75 | H96: =IFERROR(__xludf.DUMMYFUNCTION("""COMPUTED_VALUE"""),576473.75) -> 576473.75 | I96: =IFERROR(__xludf.DUMMYFUNCTION("""COMPUTED_VALUE"""),1151473.41666666) -> 1151473.4 | J96: =IFERROR(__xludf.DUMMYFUNCTION("""COMPUTED_VALUE"""),1151473.41666666) -> 1151473.4 | K96: =IFERROR(__xludf.DUMMYFUNCTION("""COMPUTED_VALUE"""),1151473.41666666) -> 1151473.4 | L96: =IFERROR(__xludf.DUMMYFUNCTION("""COMPUTED_VALUE"""),1151473.41666666) -> 1151473.4 | M96: =IFERROR(__xludf.DUMMYFUNCTION("""COMPUTED_VALUE"""),1151473.41666666) -> 1151473.4 | N96: =IFERROR(__xludf.DUMMYFUNCTION("""COMPUTED_VALUE"""),1151473.41666666) -> 1151473.4 | O96: =IFERROR(__xludf.DUMMYFUNCTION("""COMPUTED_VALUE"""),1151473.41666666) -> 1151473.4 | P96: =IFERROR(__xludf.DUMMYFUNCTION("""COMPUTED_VALUE"""),1151473.41666666) -> 1151473.4 | Q96: =IFERROR(__xludf.DUMMYFUNCTION("""COMPUTED_VALUE"""),1151473.41666666) -> 1151473.4 | S96: =_xludf.ifs(A96="INDIA",E96/'Shared Summary by Dept_US$'!$B$31,A96="INDO",E96/'Shared Summary by Dept_US$'!$B$32,A96="BD",E96/'Shared Summary by Dept_US$'!$B$33,A96="Nepal",E96/'Shared Summary by Dept_US$'!$B$34,A96="US",E96/'Shared Summary by Dept_US$'!$B$35) -> #NAME? | T96: India-Digital Product-Country Product
A97: India | B97: =IFERROR(__xludf.DUMMYFUNCTION("""COMPUTED_VALUE"""),"Health and Retirement Benefits") -> Health and Retirement Benefits | C97: =IFERROR(__xludf.DUMMYFUNCTION("""COMPUTED_VALUE"""),"Gratuity & Bonus") -> Gratuity & Bonus | E97: =IFERROR(__xludf.DUMMYFUNCTION("""COMPUTED_VALUE"""),0) -> 0 | F97: =IFERROR(__xludf.DUMMYFUNCTION("""COMPUTED_VALUE"""),0) -> 0 | G97: =IFERROR(__xludf.DUMMYFUNCTION("""COMPUTED_VALUE"""),0) -> 0 | H97: =IFERROR(__xludf.DUMMYFUNCTION("""COMPUTED_VALUE"""),0) -> 0 | I97: =IFERROR(__xludf.DUMMYFUNCTION("""COMPUTED_VALUE"""),0) -> 0 | J97: =IFERROR(__xludf.DUMMYFUNCTION("""COMPUTED_VALUE"""),0) -> 0 | K97: =IFERROR(__xludf.DUMMYFUNCTION("""COMPUTED_VALUE"""),0) -> 0 | L97: =IFERROR(__xludf.DUMMYFUNCTION("""COMPUTED_VALUE"""),0) -> 0 | ... Q97: =IFERROR(__xludf.DUMMYFUNCTION("""COMPUTED_VALUE"""),0) -> 0 | S97: =_xludf.ifs(A97="INDIA",E97/'Shared Summary by Dept_US$'!$B$31,A97="INDO",E97/'Shared Summary by Dept_US$'!$B$32,A97="BD",E97/'Shared Summary by Dept_US$'!$B$33,A97="Nepal",E97/'Shared Summary by Dept_US$'!$B$34,A97="US",E97/'Shared Summary by Dept_US$'!$B$35) -> #NAME? | T97: India-Digital Product-Country Product
A98: India | B98: =IFERROR(__xludf.DUMMYFUNCTION("""COMPUTED_VALUE"""),"Other Staff Expenses") -> Other Staff Expenses | C98: =IFERROR(__xludf.DUMMYFUNCTION("""COMPUTED_VALUE"""),"Staff Training, Learning & Development Exp") -> Staff Training, Learning & Development Exp | D98: =IFERROR(__xludf.DUMMYFUNCTION("""COMPUTED_VALUE"""),91302) -> 91302 | E98: =IFERROR(__xludf.DUMMYFUNCTION("""COMPUTED_VALUE"""),0) -> 0 | F98: =IFERROR(__xludf.DUMMYFUNCTION("""COMPUTED_VALUE"""),0) -> 0 | G98: =IFERROR(__xludf.DUMMYFUNCTION("""COMPUTED_VALUE"""),0) -> 0 | H98: =IFERROR(__xludf.DUMMYFUNCTION("""COMPUTED_VALUE"""),0) -> 0 | I98: =IFERROR(__xludf.DUMMYFUNCTION("""COMPUTED_VALUE"""),0) -> 0 | J98: =IFERROR(__xludf.DUMMYFUNCTION("""COMPUTED_VALUE"""),0) -> 0 | K98: =IFERROR(__xludf.DUMMYFUNCTION("""COMPUTED_VALUE"""),0) -> 0 | L98: =IFERROR(__xludf.DUMMYFUNCTION("""COMPUTED_VALUE"""),0) -> 0 | ... Q98: =IFERROR(__xludf.DUMMYFUNCTION("""COMPUTED_VALUE"""),0) -> 0 | S98: =_xludf.ifs(A98="INDIA",E98/'Shared Summary by Dept_US$'!$B$31,A98="INDO",E98/'Shared Summary by Dept_US$'!$B$32,A98="BD",E98/'Shared Summary by Dept_US$'!$B$33,A98="Nepal",E98/'Shared Summary by Dept_US$'!$B$34,A98="US",E98/'Shared Summary by Dept_US$'!$B$35) -> #NAME? | T98: India-Digital Product-Country Product
A99: India | B99: =IFERROR(__xludf.DUMMYFUNCTION("""COMPUTED_VALUE"""),"Resource Persons") -> Resource Persons | C99: =IFERROR(__xludf.DUMMYFUNCTION("""COMPUTED_VALUE"""),"Program Resource Consultant (EHA)") -> Program Resource Consultant (EHA) | D99: =IFERROR(__xludf.DUMMYFUNCTION("""COMPUTED_VALUE"""),92101) -> 92101 | E99: =IFERROR(__xludf.DUMMYFUNCTION("""COMPUTED_VALUE"""),4898079.33333333) -> 4898079.3 | F99: =IFERROR(__xludf.DUMMYFUNCTION("""COMPUTED_VALUE"""),320506) -> 320506 | G99: =IFERROR(__xludf.DUMMYFUNCTION("""COMPUTED_VALUE"""),305840) -> 305840 | H99: =IFERROR(__xludf.DUMMYFUNCTION("""COMPUTED_VALUE"""),427173.333333333) -> 427173.33 | I99: =IFERROR(__xludf.DUMMYFUNCTION("""COMPUTED_VALUE"""),427173.333333333) -> 427173.33 | J99: =IFERROR(__xludf.DUMMYFUNCTION("""COMPUTED_VALUE"""),427173.333333333) -> 427173.33 | K99: =IFERROR(__xludf.DUMMYFUNCTION("""COMPUTED_VALUE"""),427173.333333333) -> 427173.33 | L99: =IFERROR(__xludf.DUMMYFUNCTION("""COMPUTED_VALUE"""),427173.333333333) -> 427173.33 | M99: =IFERROR(__xludf.DUMMYFUNCTION("""COMPUTED_VALUE"""),427173.333333333) -> 427173.33 | N99: =IFERROR(__xludf.DUMMYFUNCTION("""COMPUTED_VALUE"""),427173.333333333) -> 427173.33 | O99: =IFERROR(__xludf.DUMMYFUNCTION("""COMPUTED_VALUE"""),427173.333333333) -> 427173.33 | ... Q99: =IFERROR(__xludf.DUMMYFUNCTION("""COMPUTED_VALUE"""),427173.333333333) -> 427173.33 | S99: =_xludf.ifs(A99="INDIA",E99/'Shared Summary by Dept_US$'!$B$31,A99="INDO",E99/'Shared Summary by Dept_US$'!$B$32,A99="BD",E99/'Shared Summary by Dept_US$'!$B$33,A99="Nepal",E99/'Shared Summary by Dept_US$'!$B$34,A99="US",E99/'Shared Summary by Dept_US$'!$B$35) -> #NAME? | T99: India-Digital Product-Country Product
